Workbook

Sheet CheckoutGuard — Business plan ·
A1: CheckoutGuard — Business plan · User-supplied synthetic runtime observations
A2: Financial model (3 pages) · Main Scenario
A4: Variable / dimension | B4: Reported input tokens | C4: Reported output tokens | D4: Elapsed seconds | E4: Model decisions | F4: Screenshots | G4: Catalog-priced token estimate
A5: Run 1 | B5: =12227 -> 12227 | C5: =202 -> 202 | D5: =21.3 -> 21.3 | E5: =7 -> 7 | F5: =8 -> 8 | G5: =('CheckoutGuard — Business plan ·'!B5*'CheckoutGuard — Assumptions · C'!B5+'CheckoutGuard — Business plan ·'!C5*'CheckoutGuard — Assumptions · C'!B6)/1000000 -> 0.00315775
A6: Run 2 | B6: =12128 -> 12128 | C6: =179 -> 179 | D6: =28.92 -> 28.92 | E6: =7 -> 7 | F6: =8 -> 8 | G6: =('CheckoutGuard — Business plan ·'!B6*'CheckoutGuard — Assumptions · C'!B5+'CheckoutGuard — Business plan ·'!C6*'CheckoutGuard — Assumptions · C'!B6)/1000000 -> 0.0031215
A7: Run 3 | B7: =12335 -> 12335 | C7: =202 -> 202 | D7: =16.66 -> 16.66 | E7: =7 -> 7 | F7: =8 -> 8 | G7: =('CheckoutGuard — Business plan ·'!B7*'CheckoutGuard — Assumptions · C'!B5+'CheckoutGuard — Business plan ·'!C7*'CheckoutGuard — Assumptions · C'!B6)/1000000 -> 0.00318475

Sheet CheckoutGuard — Business pl (2)
A1: CheckoutGuard — Business plan · Pricing contribution by subscription — assumptions
A2: Financial model (3 pages) · Main Scenario
A4: Variable / dimension | B4: Monthly price | C4: Included runs | D4: Included workspaces | E4: Used runs per subscription | F4: Delivery cost per subscription | G4: Support cost per subscription | H4: Fees per subscription | I4: Contribution per subscription | J4: Unit contribution margin | K4: Full quota contribution | L4: Full quota margin
A5: Agency | B5: =299 -> 299 | C5: =2000 -> 2000 | D5: =10 -> 10 | E5: ='CheckoutGuard — Business pl (2)'!C5*'CheckoutGuard — Assumptions · C'!B17 -> 1000 | F5: ='CheckoutGuard — Business pl (2)'!E5*'CheckoutGuard — Assumptions (2)'!B12 -> 19.0856 | G5: ='CheckoutGuard — Assumptions · W'!E5/60*'CheckoutGuard — Assumptions · C'!B16 -> 30 | H5: ='CheckoutGuard — Business pl (2)'!B5*'CheckoutGuard — Assumptions · S'!B5+'CheckoutGuard — Assumptions · S'!B6 -> 9.27 | I5: ='CheckoutGuard — Business pl (2)'!B5-'CheckoutGuard — Business pl (2)'!F5-'CheckoutGuard — Business pl (2)'!G5-'CheckoutGuard — Business pl (2)'!H5 -> 240.6444 | J5: =IFERROR('CheckoutGuard — Business pl (2)'!I5/'CheckoutGuard — Business pl (2)'!B5,"") -> 0.80483077 | K5: ='CheckoutGuard — Business pl (2)'!B5-'CheckoutGuard — Business pl (2)'!C5*'CheckoutGuard — Assumptions (2)'!B12-'CheckoutGuard — Business pl (2)'!G5-'CheckoutGuard — Business pl (2)'!H5 -> 221.5588 | L5: =IFERROR('CheckoutGuard — Business pl (2)'!K5/'CheckoutGuard — Business pl (2)'!B5,"") -> 0.74099933
A6: Developer | B6: =29 -> 29 | C6: =100 -> 100 | D6: =1 -> 1 | E6: ='CheckoutGuard — Business pl (2)'!C6*'CheckoutGuard — Assumptions · C'!B17 -> 50 | F6: ='CheckoutGuard — Business pl (2)'!E6*'CheckoutGuard — Assumptions (2)'!B12 -> 0.95428 | G6: ='CheckoutGuard — Assumptions · W'!E6/60*'CheckoutGuard — Assumptions · C'!B16 -> 5 | H6: ='CheckoutGuard — Business pl (2)'!B6*'CheckoutGuard — Assumptions · S'!B5+'CheckoutGuard — Assumptions · S'!B6 -> 1.17 | I6: ='CheckoutGuard — Business pl (2)'!B6-'CheckoutGuard — Business pl (2)'!F6-'CheckoutGuard — Business pl (2)'!G6-'CheckoutGuard — Business pl (2)'!H6 -> 21.87572 | J6: =IFERROR('CheckoutGuard — Business pl (2)'!I6/'CheckoutGuard — Business pl (2)'!B6,"") -> 0.75433517 | K6: ='CheckoutGuard — Business pl (2)'!B6-'CheckoutGuard — Business pl (2)'!C6*'CheckoutGuard — Assumptions (2)'!B12-'CheckoutGuard — Business pl (2)'!G6-'CheckoutGuard — Business pl (2)'!H6 -> 20.92144 | L6: =IFERROR('CheckoutGuard — Business pl (2)'!K6/'CheckoutGuard — Business pl (2)'!B6,"") -> 0.72142897
A7: Team | B7: =99 -> 99 | C7: =500 -> 500 | D7: =3 -> 3 | E7: ='CheckoutGuard — Business pl (2)'!C7*'CheckoutGuard — Assumptions · C'!B17 -> 250 | F7: ='CheckoutGuard — Business pl (2)'!E7*'CheckoutGuard — Assumptions (2)'!B12 -> 4.7714 | G7: ='CheckoutGuard — Assumptions · W'!E7/60*'CheckoutGuard — Assumptions · C'!B16 -> 12.5 | H7: ='CheckoutGuard — Business pl (2)'!B7*'CheckoutGuard — Assumptions · S'!B5+'CheckoutGuard — Assumptions · S'!B6 -> 3.27 | I7: ='CheckoutGuard — Business pl (2)'!B7-'CheckoutGuard — Business pl (2)'!F7-'CheckoutGuard — Business pl (2)'!G7-'CheckoutGuard — Business pl (2)'!H7 -> 78.4586 | J7: =IFERROR('CheckoutGuard — Business pl (2)'!I7/'CheckoutGuard — Business pl (2)'!B7,"") -> 0.79251111 | K7: ='CheckoutGuard — Business pl (2)'!B7-'CheckoutGuard — Business pl (2)'!C7*'CheckoutGuard — Assumptions (2)'!B12-'CheckoutGuard — Business pl (2)'!G7-'CheckoutGuard — Business pl (2)'!H7 -> 73.6872 | L7: =IFERROR('CheckoutGuard — Business pl (2)'!K7/'CheckoutGuard — Business pl (2)'!B7,"") -> 0.74431515

Sheet CheckoutGuard — Business pl (3)
A1: CheckoutGuard — Business plan · Conservative base growth comparison — assumptions
A2: Financial model (3 pages) · Main Scenario
A4: Variable / dimension | B4: 2027-10 | C4: 2027-10 > CheckoutGuard — Conservative | D4: 2027-10 > CheckoutGuard — Growth | E4: 2027-11 | F4: 2027-11 > CheckoutGuard — Conservative | G4: 2027-11 > CheckoutGuard — Growth | H4: 2027-12 | I4: 2027-12 > CheckoutGuard — Conservative | J4: 2027-12 > CheckoutGuard — Growth | K4: 2028-01 | L4: 2028-01 > CheckoutGuard — Conservative | M4: 2028-01 > CheckoutGuard — Growth | N4: 2028-02 | O4: 2028-02 > CheckoutGuard — Conservative | P4: 2028-02 > CheckoutGuard — Growth | Q4: 2028-03 | R4: 2028-03 > CheckoutGuard — Conservative | S4: 2028-03 > CheckoutGuard — Growth | T4: 2028-04 | U4: 2028-04 > CheckoutGuard — Conservative | V4: 2028-04 > CheckoutGuard — Growth | W4: 2028-05 | X4: 2028-05 > CheckoutGuard — Conservative | Y4: 2028-05 > CheckoutGuard — Growth | Z4: 2028-06 | AA4: 2028-06 > CheckoutGuard — Conservative | AB4: 2028-06 > CheckoutGuard — Growth | AC4: 2028-07 | AD4: 2028-07 > CheckoutGuard — Conservative | AE4: 2028-07 > CheckoutGuard — Growth | AF4: 2028-08 | AG4: 2028-08 > CheckoutGuard — Conservative | AH4: 2028-08 > CheckoutGuard — Growth | AI4: 2028-09 | AJ4: 2028-09 > CheckoutGuard — Conservative | AK4: 2028-09 > CheckoutGuard — Growth | AL4: 2028-10 | AM4: 2028-10 > CheckoutGuard — Conservative | AN4: 2028-10 > CheckoutGuard — Growth
A5: Active subscriptions | B5: =SUM('CheckoutGuard — Forecast · Chec'!N18,'CheckoutGuard — Forecast · Chec'!N19,'CheckoutGuard — Forecast · Chec'!N20) -> 61.988286 | C5: =SUM('Model inputs'!O11,'Model inputs'!O12,'Model inputs'!O13) -> 20.683796 | D5: =SUM('Model inputs'!O15,'Model inputs'!O16,'Model inputs'!O17) -> 138.67627 | E5: =SUM('CheckoutGuard — Forecast · Chec'!O18,'CheckoutGuard — Forecast · Chec'!O19,'CheckoutGuard — Forecast · Chec'!O20) -> 68.20999 | F5: =SUM('Model inputs'!P11,'Model inputs'!P12,'Model inputs'!P13) -> 21.899606 | G5: =SUM('Model inputs'!P15,'Model inputs'!P16,'Model inputs'!P17) -> 156.04811 | H5: =SUM('CheckoutGuard — Forecast · Chec'!P18,'CheckoutGuard — Forecast · Chec'!P19,'CheckoutGuard — Forecast · Chec'!P20) -> 74.649112 | I5: =SUM('Model inputs'!Q11,'Model inputs'!Q12,'Model inputs'!Q13) -> 23.054626 | J5: =SUM('Model inputs'!Q15,'Model inputs'!Q16,'Model inputs'!Q17) -> 174.68413 | K5: =SUM('CheckoutGuard — Forecast · Chec'!Q18,'CheckoutGuard — Forecast · Chec'!Q19,'CheckoutGuard — Forecast · Chec'!Q20) -> 81.319331 | L5: =SUM('Model inputs'!R11,'Model inputs'!R12,'Model inputs'!R13) -> 24.151895 | M5: =SUM('Model inputs'!R15,'Model inputs'!R16,'Model inputs'!R17) -> 194.688 | N5: =SUM('CheckoutGuard — Forecast · Chec'!R18,'CheckoutGuard — Forecast · Chec'!R19,'CheckoutGuard — Forecast · Chec'!R20) -> 88.234928 | O5: =SUM('Model inputs'!S11,'Model inputs'!S12,'Model inputs'!S13) -> 25.1943 | P5: =SUM('Model inputs'!S15,'Model inputs'!S16,'Model inputs'!S17) -> 216.17159 | Q5: =SUM('CheckoutGuard — Forecast · Chec'!S18,'CheckoutGuard — Forecast · Chec'!S19,'CheckoutGuard — Forecast · Chec'!S20) -> 95.410815 | R5: =SUM('Model inputs'!T11,'Model inputs'!T12,'Model inputs'!T13) -> 26.184585 | S5: =SUM('Model inputs'!T15,'Model inputs'!T16,'Model inputs'!T17) -> 239.2557 | T5: =SUM('CheckoutGuard — Forecast · Chec'!T18,'CheckoutGuard — Forecast · Chec'!T19,'CheckoutGuard — Forecast · Chec'!T20) -> 102.86257 | U5: =SUM('Model inputs'!U11,'Model inputs'!U12,'Model inputs'!U13) -> 27.125356 | V5: =SUM('Model inputs'!U15,'Model inputs'!U16,'Model inputs'!U17) -> 264.07073 | W5: =SUM('CheckoutGuard — Forecast · Chec'!U18,'CheckoutGuard — Forecast · Chec'!U19,'CheckoutGuard — Forecast · Chec'!U20) -> 110.60648 | X5: =SUM('Model inputs'!V11,'Model inputs'!V12,'Model inputs'!V13) -> 28.019088 | Y5: =SUM('Model inputs'!V15,'Model inputs'!V16,'Model inputs'!V17) -> 290.75747 | Z5: =SUM('CheckoutGuard — Forecast · Chec'!V18,'CheckoutGuard — Forecast · Chec'!V19,'CheckoutGuard — Forecast · Chec'!V20) -> 118.65956 | AA5: =SUM('Model inputs'!W11,'Model inputs'!W12,'Model inputs'!W13) -> 28.868133 | AB5: =SUM('Model inputs'!W15,'Model inputs'!W16,'Model inputs'!W17) -> 319.46793 | AC5: =SUM('CheckoutGuard — Forecast · Chec'!W18,'CheckoutGuard — Forecast · Chec'!W19,'CheckoutGuard — Forecast · Chec'!W20) -> 127.03962 | AD5: =SUM('Model inputs'!X11,'Model inputs'!X12,'Model inputs'!X13) -> 29.674727 | AE5: =SUM('Model inputs'!X15,'Model inputs'!X16,'Model inputs'!X17) -> 350.36623 | AF5: =SUM('CheckoutGuard — Forecast · Chec'!X18,'CheckoutGuard — Forecast · Chec'!X19,'CheckoutGuard — Forecast · Chec'!X20) -> 135.76526 | AG5: =SUM('Model inputs'!Y11,'Model inputs'!Y12,'Model inputs'!Y13) -> 30.44099 | AH5: =SUM('Model inputs'!Y15,'Model inputs'!Y16,'Model inputs'!Y17) -> 383.62958 | AI5: =SUM('CheckoutGuard — Forecast · Chec'!Y18,'CheckoutGuard — Forecast · Chec'!Y19,'CheckoutGuard — Forecast · Chec'!Y20) -> 144.85598 | AJ5: =SUM('Model inputs'!Z11,'Model inputs'!Z12,'Model inputs'!Z13) -> 31.168941 | AK5: =SUM('Model inputs'!Z15,'Model inputs'!Z16,'Model inputs'!Z17) -> 419.44931 | AL5: =SUM('CheckoutGuard — Forecast · Chec'!Z18,'CheckoutGuard — Forecast · Chec'!Z19,'CheckoutGuard — Forecast · Chec'!Z20) -> 154.33215 | AM5: =SUM('Model inputs'!AA11,'Model inputs'!AA12,'Model inputs'!AA13) -> 31.860494 | AN5: =SUM('Model inputs'!AA15,'Model inputs'!AA16,'Model inputs'!AA17) -> 458.03203
A6: Subscription revenue | B6: =SUM('CheckoutGuard — Forecast · Chec'!N22,'CheckoutGuard — Forecast · Chec'!N23,'CheckoutGuard — Forecast · Chec'!N24) -> 5585.8333 | C6: =SUM('Model inputs'!O89,'Model inputs'!O90,'Model inputs'!O91) -> 1863.8398 | D6: =SUM('Model inputs'!O93,'Model inputs'!O94,'Model inputs'!O95) -> 12342.188 | E6: =SUM('CheckoutGuard — Forecast · Chec'!O22,'CheckoutGuard — Forecast · Chec'!O23,'CheckoutGuard — Forecast · Chec'!O24) -> 6146.478 | F6: =SUM('Model inputs'!P89,'Model inputs'!P90,'Model inputs'!P91) -> 1973.3979 | G6: =SUM('Model inputs'!P93,'Model inputs'!P94,'Model inputs'!P95) -> 13888.282 | H6: =SUM('CheckoutGuard — Forecast · Chec'!P22,'CheckoutGuard — Forecast · Chec'!P23,'CheckoutGuard — Forecast · Chec'!P24) -> 6726.7144 | I6: =SUM('Model inputs'!Q89,'Model inputs'!Q90,'Model inputs'!Q91) -> 2077.478 | J6: =SUM('Model inputs'!Q93,'Model inputs'!Q94,'Model inputs'!Q95) -> 15546.888 | K6: =SUM('CheckoutGuard — Forecast · Chec'!Q22,'CheckoutGuard — Forecast · Chec'!Q23,'CheckoutGuard — Forecast · Chec'!Q24) -> 7327.7752 | L6: =SUM('Model inputs'!R89,'Model inputs'!R90,'Model inputs'!R91) -> 2176.3541 | M6: =SUM('Model inputs'!R93,'Model inputs'!R94,'Model inputs'!R95) -> 17327.232 | N6: =SUM('CheckoutGuard — Forecast · Chec'!R22,'CheckoutGuard — Forecast · Chec'!R23,'CheckoutGuard — Forecast · Chec'!R24) -> 7950.9474 | O6: =SUM('Model inputs'!S89,'Model inputs'!S90,'Model inputs'!S91) -> 2270.2864 | P6: =SUM('Model inputs'!S93,'Model inputs'!S94,'Model inputs'!S95) -> 19239.272 | Q6: =SUM('CheckoutGuard — Forecast · Chec'!S22,'CheckoutGuard — Forecast · Chec'!S23,'CheckoutGuard — Forecast · Chec'!S24) -> 8597.5746 | R6: =SUM('Model inputs'!T89,'Model inputs'!T90,'Model inputs'!T91) -> 2359.522 | S6: =SUM('Model inputs'!T93,'Model inputs'!T94,'Model inputs'!T95) -> 21293.758 | T6: =SUM('CheckoutGuard — Forecast · Chec'!T22,'CheckoutGuard — Forecast · Chec'!T23,'CheckoutGuard — Forecast · Chec'!T24) -> 9269.0608 | U6: =SUM('Model inputs'!U89,'Model inputs'!U90,'Model inputs'!U91) -> 2444.2959 | V6: =SUM('Model inputs'!U93,'Model inputs'!U94,'Model inputs'!U95) -> 23502.295 | W6: =SUM('CheckoutGuard — Forecast · Chec'!U22,'CheckoutGuard — Forecast · Chec'!U23,'CheckoutGuard — Forecast · Chec'!U24) -> 9966.8731 | X6: =SUM('Model inputs'!V89,'Model inputs'!V90,'Model inputs'!V91) -> 2524.8311 | Y6: =SUM('Model inputs'!V93,'Model inputs'!V94,'Model inputs'!V95) -> 25877.415 | Z6: =SUM('CheckoutGuard — Forecast · Chec'!V22,'CheckoutGuard — Forecast · Chec'!V23,'CheckoutGuard — Forecast · Chec'!V24) -> 10692.545 | AA6: =SUM('Model inputs'!W89,'Model inputs'!W90,'Model inputs'!W91) -> 2601.3396 | AB6: =SUM('Model inputs'!W93,'Model inputs'!W94,'Model inputs'!W95) -> 28432.646 | AC6: =SUM('CheckoutGuard — Forecast · Chec'!W22,'CheckoutGuard — Forecast · Chec'!W23,'CheckoutGuard — Forecast · Chec'!W24) -> 11447.681 | AD6: =SUM('Model inputs'!X89,'Model inputs'!X90,'Model inputs'!X91) -> 2674.0226 | AE6: =SUM('Model inputs'!X93,'Model inputs'!X94,'Model inputs'!X95) -> 31182.595 | AF6: =SUM('CheckoutGuard — Forecast · Chec'!X22,'CheckoutGuard — Forecast · Chec'!X23,'CheckoutGuard — Forecast · Chec'!X24) -> 12233.958 | AG6: =SUM('Model inputs'!Y89,'Model inputs'!Y90,'Model inputs'!Y91) -> 2743.0715 | AH6: =SUM('Model inputs'!Y93,'Model inputs'!Y94,'Model inputs'!Y95) -> 34143.032 | AI6: =SUM('CheckoutGuard — Forecast · Chec'!Y22,'CheckoutGuard — Forecast · Chec'!Y23,'CheckoutGuard — Forecast · Chec'!Y24) -> 13053.133 | AJ6: =SUM('Model inputs'!Z89,'Model inputs'!Z90,'Model inputs'!Z91) -> 2808.6679 | AK6: =SUM('Model inputs'!Z93,'Model inputs'!Z94,'Model inputs'!Z95) -> 37330.989 | AL6: =SUM('CheckoutGuard — Forecast · Chec'!Z22,'CheckoutGuard — Forecast · Chec'!Z23,'CheckoutGuard — Forecast · Chec'!Z24) -> 13907.042 | AM6: =SUM('Model inputs'!AA89,'Model inputs'!AA90,'Model inputs'!AA91) -> 2870.9845 | AN6: =SUM('Model inputs'!AA93,'Model inputs'!AA94,'Model inputs'!AA95) -> 40764.851
A7: Contribution | B7: =SUM('CheckoutGuard — Forecast · Chec'!N38,'CheckoutGuard — Forecast · Chec'!N39,'CheckoutGuard — Forecast · Chec'!N40) -> 4421.7049 | C7: =SUM('Model inputs'!O24,'Model inputs'!O25,'Model inputs'!O26) -> 1475.402 | D7: =SUM('Model inputs'!O28,'Model inputs'!O29,'Model inputs'!O30) -> 9768.41 | E7: =SUM('CheckoutGuard — Forecast · Chec'!O38,'CheckoutGuard — Forecast · Chec'!O39,'CheckoutGuard — Forecast · Chec'!O40) -> 4865.5071 | F7: =SUM('Model inputs'!P24,'Model inputs'!P25,'Model inputs'!P26) -> 1562.1273 | G7: =SUM('Model inputs'!P28,'Model inputs'!P29,'Model inputs'!P30) -> 10992.089 | H7: =SUM('CheckoutGuard — Forecast · Chec'!P38,'CheckoutGuard — Forecast · Chec'!P39,'CheckoutGuard — Forecast · Chec'!P40) -> 5324.818 | I7: =SUM('Model inputs'!Q24,'Model inputs'!Q25,'Model inputs'!Q26) -> 1644.5164 | J7: =SUM('Model inputs'!Q28,'Model inputs'!Q29,'Model inputs'!Q30) -> 12304.818 | K7: =SUM('CheckoutGuard — Forecast · Chec'!Q38,'CheckoutGuard — Forecast · Chec'!Q39,'CheckoutGuard — Forecast · Chec'!Q40) -> 5800.6134 | L7: =SUM('Model inputs'!R24,'Model inputs'!R25,'Model inputs'!R26) -> 1722.786 | M7: =SUM('Model inputs'!R28,'Model inputs'!R29,'Model inputs'!R30) -> 13713.898 | N7: =SUM('CheckoutGuard — Forecast · Chec'!R38,'CheckoutGuard — Forecast · Chec'!R39,'CheckoutGuard — Forecast · Chec'!R40) -> 6293.9119 | O7: =SUM('Model inputs'!S24,'Model inputs'!S25,'Model inputs'!S26) -> 1797.1421 | P7: =SUM('Model inputs'!S28,'Model inputs'!S29,'Model inputs'!S30) -> 15227.21 | Q7: =SUM('CheckoutGuard — Forecast · Chec'!S38,'CheckoutGuard — Forecast · Chec'!S39,'CheckoutGuard — Forecast · Chec'!S40) -> 6805.7773 | R7: =SUM('Model inputs'!T24,'Model inputs'!T25,'Model inputs'!T26) -> 1867.7804 | S7: =SUM('Model inputs'!T28,'Model inputs'!T29,'Model inputs'!T30) -> 16853.264 | T7: =SUM('CheckoutGuard — Forecast · Chec'!T38,'CheckoutGuard — Forecast · Chec'!T39,'CheckoutGuard — Forecast · Chec'!T40) -> 7337.3209 | U7: =SUM('Model inputs'!U24,'Model inputs'!U25,'Model inputs'!U26) -> 1934.8868 | V7: =SUM('Model inputs'!U28,'Model inputs'!U29,'Model inputs'!U30) -> 18601.244 | W7: =SUM('CheckoutGuard — Forecast · Chec'!U38,'CheckoutGuard — Forecast · Chec'!U39,'CheckoutGuard — Forecast · Chec'!U40) -> 7889.704 | X7: =SUM('Model inputs'!V24,'Model inputs'!V25,'Model inputs'!V26) -> 1998.6379 | Y7: =SUM('Model inputs'!V28,'Model inputs'!V29,'Model inputs'!V30) -> 20481.068 | Z7: =SUM('CheckoutGuard — Forecast · Chec'!V38,'CheckoutGuard — Forecast · Chec'!V39,'CheckoutGuard — Forecast · Chec'!V40) -> 8464.1407 | AA7: =SUM('Model inputs'!W24,'Model inputs'!W25,'Model inputs'!W26) -> 2059.2014 | AB7: =SUM('Model inputs'!W28,'Model inputs'!W29,'Model inputs'!W30) -> 22503.444 | AC7: =SUM('CheckoutGuard — Forecast · Chec'!W38,'CheckoutGuard — Forecast · Chec'!W39,'CheckoutGuard — Forecast · Chec'!W40) -> 9061.9007 | AD7: =SUM('Model inputs'!X24,'Model inputs'!X25,'Model inputs'!X26) -> 2116.7368 | AE7: =SUM('Model inputs'!X28,'Model inputs'!X29,'Model inputs'!X30) -> 24679.932 | AF7: =SUM('CheckoutGuard — Forecast · Chec'!X38,'CheckoutGuard — Forecast · Chec'!X39,'CheckoutGuard — Forecast · Chec'!X40) -> 9684.3122 | AG7: =SUM('Model inputs'!Y24,'Model inputs'!Y25,'Model inputs'!Y26) -> 2171.3954 | AH7: =SUM('Model inputs'!Y28,'Model inputs'!Y29,'Model inputs'!Y30) -> 27023.015 | AI7: =SUM('CheckoutGuard — Forecast · Chec'!Y38,'CheckoutGuard — Forecast · Chec'!Y39,'CheckoutGuard — Forecast · Chec'!Y40) -> 10332.765 | AJ7: =SUM('Model inputs'!Z24,'Model inputs'!Z25,'Model inputs'!Z26) -> 2223.321 | AK7: =SUM('Model inputs'!Z28,'Model inputs'!Z29,'Model inputs'!Z30) -> 29546.171 | AL7: =SUM('CheckoutGuard — Forecast · Chec'!Z38,'CheckoutGuard — Forecast · Chec'!Z39,'CheckoutGuard — Forecast · Chec'!Z40) -> 11008.713 | AM7: =SUM('Model inputs'!AA24,'Model inputs'!AA25,'Model inputs'!AA26) -> 2272.6504 | AN7: =SUM('Model inputs'!AA28,'Model inputs'!AA29,'Model inputs'!AA30) -> 32263.953
A8: Contribution margin | B8: =IFERROR('CheckoutGuard — Business pl (3)'!B7/'CheckoutGuard — Business pl (3)'!B6,"") -> 0.7915927 | C8: =IFERROR('CheckoutGuard — Business pl (3)'!C7/'CheckoutGuard — Business pl (3)'!C6,"") -> 0.7915927 | D8: =IFERROR('CheckoutGuard — Business pl (3)'!D7/'CheckoutGuard — Business pl (3)'!D6,"") -> 0.791465 | E8: =IFERROR('CheckoutGuard — Business pl (3)'!E7/'CheckoutGuard — Business pl (3)'!E6,"") -> 0.7915927 | F8: =IFERROR('CheckoutGuard — Business pl (3)'!F7/'CheckoutGuard — Business pl (3)'!F6,"") -> 0.7915927 | G8: =IFERROR('CheckoutGuard — Business pl (3)'!G7/'CheckoutGuard — Business pl (3)'!G6,"") -> 0.791465 | H8: =IFERROR('CheckoutGuard — Business pl (3)'!H7/'CheckoutGuard — Business pl (3)'!H6,"") -> 0.7915927 | I8: =IFERROR('CheckoutGuard — Business pl (3)'!I7/'CheckoutGuard — Business pl (3)'!I6,"") -> 0.7915927 | ... AN8: =IFERROR('CheckoutGuard — Business pl (3)'!AN7/'CheckoutGuard — Business pl (3)'!AN6,"") -> 0.791465
A9: Operating result | B9: ='CheckoutGuard — Business pl (3)'!B7-'CheckoutGuard — Assumptions (2)'!B13 -> -2378.2951 | C9: ='CheckoutGuard — Business pl (3)'!C7-'Model inputs'!AB37 -> -5324.598 | D9: ='CheckoutGuard — Business pl (3)'!D7-'Model inputs'!AB38 -> 2968.41 | E9: ='CheckoutGuard — Business pl (3)'!E7-'CheckoutGuard — Assumptions (2)'!B13 -> -1934.4929 | F9: ='CheckoutGuard — Business pl (3)'!F7-'Model inputs'!AB37 -> -5237.8727 | G9: ='CheckoutGuard — Business pl (3)'!G7-'Model inputs'!AB38 -> 4192.0887 | H9: ='CheckoutGuard — Business pl (3)'!H7-'CheckoutGuard — Assumptions (2)'!B13 -> -1475.182 | I9: ='CheckoutGuard — Business pl (3)'!I7-'Model inputs'!AB37 -> -5155.4836 | J9: ='CheckoutGuard — Business pl (3)'!J7-'Model inputs'!AB38 -> 5504.8177 | K9: ='CheckoutGuard — Business pl (3)'!K7-'CheckoutGuard — Assumptions (2)'!B13 -> -999.38661 | L9: ='CheckoutGuard — Business pl (3)'!L7-'Model inputs'!AB37 -> -5077.214 | M9: ='CheckoutGuard — Business pl (3)'!M7-'Model inputs'!AB38 -> 6913.8977 | N9: ='CheckoutGuard — Business pl (3)'!N7-'CheckoutGuard — Assumptions (2)'!B13 -> -506.08811 | O9: ='CheckoutGuard — Business pl (3)'!O7-'Model inputs'!AB37 -> -5002.8579 | P9: ='CheckoutGuard — Business pl (3)'!P7-'Model inputs'!AB38 -> 8427.2103 | Q9: ='CheckoutGuard — Business pl (3)'!Q7-'CheckoutGuard — Assumptions (2)'!B13 -> 5.7772852 | R9: ='CheckoutGuard — Business pl (3)'!R7-'Model inputs'!AB37 -> -4932.2196 | S9: ='CheckoutGuard — Business pl (3)'!S7-'Model inputs'!AB38 -> 10053.264 | T9: ='CheckoutGuard — Business pl (3)'!T7-'CheckoutGuard — Assumptions (2)'!B13 -> 537.32085 | U9: ='CheckoutGuard — Business pl (3)'!U7-'Model inputs'!AB37 -> -4865.1132 | V9: ='CheckoutGuard — Business pl (3)'!V7-'Model inputs'!AB38 -> 11801.244 | W9: ='CheckoutGuard — Business pl (3)'!W7-'CheckoutGuard — Assumptions (2)'!B13 -> 1089.704 | X9: ='CheckoutGuard — Business pl (3)'!X7-'Model inputs'!AB37 -> -4801.3621 | Y9: ='CheckoutGuard — Business pl (3)'!Y7-'Model inputs'!AB38 -> 13681.068 | Z9: ='CheckoutGuard — Business pl (3)'!Z7-'CheckoutGuard — Assumptions (2)'!B13 -> 1664.1407 | AA9: ='CheckoutGuard — Business pl (3)'!AA7-'Model inputs'!AB37 -> -4740.7986 | AB9: ='CheckoutGuard — Business pl (3)'!AB7-'Model inputs'!AB38 -> 15703.444 | AC9: ='CheckoutGuard — Business pl (3)'!AC7-'CheckoutGuard — Assumptions (2)'!B13 -> 2261.9007 | AD9: ='CheckoutGuard — Business pl (3)'!AD7-'Model inputs'!AB37 -> -4683.2632 | AE9: ='CheckoutGuard — Business pl (3)'!AE7-'Model inputs'!AB38 -> 17879.932 | AF9: ='CheckoutGuard — Business pl (3)'!AF7-'CheckoutGuard — Assumptions (2)'!B13 -> 2884.3122 | AG9: ='CheckoutGuard — Business pl (3)'!AG7-'Model inputs'!AB37 -> -4628.6046 | AH9: ='CheckoutGuard — Business pl (3)'!AH7-'Model inputs'!AB38 -> 20223.015 | AI9: ='CheckoutGuard — Business pl (3)'!AI7-'CheckoutGuard — Assumptions (2)'!B13 -> 3532.7647 | AJ9: ='CheckoutGuard — Business pl (3)'!AJ7-'Model inputs'!AB37 -> -4576.679 | AK9: ='CheckoutGuard — Business pl (3)'!AK7-'Model inputs'!AB38 -> 22746.171 | AL9: ='CheckoutGuard — Business pl (3)'!AL7-'CheckoutGuard — Assumptions (2)'!B13 -> 4208.7128 | AM9: ='CheckoutGuard — Business pl (3)'!AM7-'Model inputs'!AB37 -> -4527.3496 | AN9: ='CheckoutGuard — Business pl (3)'!AN7-'Model inputs'!AB38 -> 25463.953
A10: Break-even subscriptions | B10: =IFERROR(CEILING('CheckoutGuard — Assumptions (2)'!B13/('CheckoutGuard — Business pl (3)'!B7/'CheckoutGuard — Business pl (3)'!B5),1),"") -> 96 | C10: =IFERROR(CEILING('Model inputs'!AB37/('CheckoutGuard — Business pl (3)'!C7/'CheckoutGuard — Business pl (3)'!C5),1),"") -> 96 | D10: =IFERROR(CEILING('Model inputs'!AB38/('CheckoutGuard — Business pl (3)'!D7/'CheckoutGuard — Business pl (3)'!D5),1),"") -> 97 | E10: =IFERROR(CEILING('CheckoutGuard — Assumptions (2)'!B13/('CheckoutGuard — Business pl (3)'!E7/'CheckoutGuard — Business pl (3)'!E5),1),"") -> 96 | F10: =IFERROR(CEILING('Model inputs'!AB37/('CheckoutGuard — Business pl (3)'!F7/'CheckoutGuard — Business pl (3)'!F5),1),"") -> 96 | G10: =IFERROR(CEILING('Model inputs'!AB38/('CheckoutGuard — Business pl (3)'!G7/'CheckoutGuard — Business pl (3)'!G5),1),"") -> 97 | H10: =IFERROR(CEILING('CheckoutGuard — Assumptions (2)'!B13/('CheckoutGuard — Business pl (3)'!H7/'CheckoutGuard — Business pl (3)'!H5),1),"") -> 96 | I10: =IFERROR(CEILING('Model inputs'!AB37/('CheckoutGuard — Business pl (3)'!I7/'CheckoutGuard — Business pl (3)'!I5),1),"") -> 96 | J10: =IFERROR(CEILING('Model inputs'!AB38/('CheckoutGuard — Business pl (3)'!J7/'CheckoutGuard — Business pl (3)'!J5),1),"") -> 97 | K10: =IFERROR(CEILING('CheckoutGuard — Assumptions (2)'!B13/('CheckoutGuard — Business pl (3)'!K7/'CheckoutGuard — Business pl (3)'!K5),1),"") -> 96 | L10: =IFERROR(CEILING('Model inputs'!AB37/('CheckoutGuard — Business pl (3)'!L7/'CheckoutGuard — Business pl (3)'!L5),1),"") -> 96 | M10: =IFERROR(CEILING('Model inputs'!AB38/('CheckoutGuard — Business pl (3)'!M7/'CheckoutGuard — Business pl (3)'!M5),1),"") -> 97 | N10: =IFERROR(CEILING('CheckoutGuard — Assumptions (2)'!B13/('CheckoutGuard — Business pl (3)'!N7/'CheckoutGuard — Business pl (3)'!N5),1),"") -> 96 | O10: =IFERROR(CEILING('Model inputs'!AB37/('CheckoutGuard — Business pl (3)'!O7/'CheckoutGuard — Business pl (3)'!O5),1),"") -> 96 | P10: =IFERROR(CEILING('Model inputs'!AB38/('CheckoutGuard — Business pl (3)'!P7/'CheckoutGuard — Business pl (3)'!P5),1),"") -> 97 | Q10: =IFERROR(CEILING('CheckoutGuard — Assumptions (2)'!B13/('CheckoutGuard — Business pl (3)'!Q7/'CheckoutGuard — Business pl (3)'!Q5),1),"") -> 96 | R10: =IFERROR(CEILING('Model inputs'!AB37/('CheckoutGuard — Business pl (3)'!R7/'CheckoutGuard — Business pl (3)'!R5),1),"") -> 96 | S10: =IFERROR(CEILING('Model inputs'!AB38/('CheckoutGuard — Business pl (3)'!S7/'CheckoutGuard — Business pl (3)'!S5),1),"") -> 97 | T10: =IFERROR(CEILING('CheckoutGuard — Assumptions (2)'!B13/('CheckoutGuard — Business pl (3)'!T7/'CheckoutGuard — Business pl (3)'!T5),1),"") -> 96 | U10: =IFERROR(CEILING('Model inputs'!AB37/('CheckoutGuard — Business pl (3)'!U7/'CheckoutGuard — Business pl (3)'!U5),1),"") -> 96 | V10: =IFERROR(CEILING('Model inputs'!AB38/('CheckoutGuard — Business pl (3)'!V7/'CheckoutGuard — Business pl (3)'!V5),1),"") -> 97 | W10: =IFERROR(CEILING('CheckoutGuard — Assumptions (2)'!B13/('CheckoutGuard — Business pl (3)'!W7/'CheckoutGuard — Business pl (3)'!W5),1),"") -> 96 | X10: =IFERROR(CEILING('Model inputs'!AB37/('CheckoutGuard — Business pl (3)'!X7/'CheckoutGuard — Business pl (3)'!X5),1),"") -> 96 | Y10: =IFERROR(CEILING('Model inputs'!AB38/('CheckoutGuard — Business pl (3)'!Y7/'CheckoutGuard — Business pl (3)'!Y5),1),"") -> 97 | Z10: =IFERROR(CEILING('CheckoutGuard — Assumptions (2)'!B13/('CheckoutGuard — Business pl (3)'!Z7/'CheckoutGuard — Business pl (3)'!Z5),1),"") -> 96 | AA10: =IFERROR(CEILING('Model inputs'!AB37/('CheckoutGuard — Business pl (3)'!AA7/'CheckoutGuard — Business pl (3)'!AA5),1),"") -> 96 | AB10: =IFERROR(CEILING('Model inputs'!AB38/('CheckoutGuard — Business pl (3)'!AB7/'CheckoutGuard — Business pl (3)'!AB5),1),"") -> 97 | AC10: =IFERROR(CEILING('CheckoutGuard — Assumptions (2)'!B13/('CheckoutGuard — Business pl (3)'!AC7/'CheckoutGuard — Business pl (3)'!AC5),1),"") -> 96 | AD10: =IFERROR(CEILING('Model inputs'!AB37/('CheckoutGuard — Business pl (3)'!AD7/'CheckoutGuard — Business pl (3)'!AD5),1),"") -> 96 | AE10: =IFERROR(CEILING('Model inputs'!AB38/('CheckoutGuard — Business pl (3)'!AE7/'CheckoutGuard — Business pl (3)'!AE5),1),"") -> 97 | AF10: =IFERROR(CEILING('CheckoutGuard — Assumptions (2)'!B13/('CheckoutGuard — Business pl (3)'!AF7/'CheckoutGuard — Business pl (3)'!AF5),1),"") -> 96 | AG10: =IFERROR(CEILING('Model inputs'!AB37/('CheckoutGuard — Business pl (3)'!AG7/'CheckoutGuard — Business pl (3)'!AG5),1),"") -> 96 | AH10: =IFERROR(CEILING('Model inputs'!AB38/('CheckoutGuard — Business pl (3)'!AH7/'CheckoutGuard — Business pl (3)'!AH5),1),"") -> 97 | AI10: =IFERROR(CEILING('CheckoutGuard — Assumptions (2)'!B13/('CheckoutGuard — Business pl (3)'!AI7/'CheckoutGuard — Business pl (3)'!AI5),1),"") -> 96 | AJ10: =IFERROR(CEILING('Model inputs'!AB37/('CheckoutGuard — Business pl (3)'!AJ7/'CheckoutGuard — Business pl (3)'!AJ5),1),"") -> 96 | AK10: =IFERROR(CEILING('Model inputs'!AB38/('CheckoutGuard — Business pl (3)'!AK7/'CheckoutGuard — Business pl (3)'!AK5),1),"") -> 97 | AL10: =IFERROR(CEILING('CheckoutGuard — Assumptions (2)'!B13/('CheckoutGuard — Business pl (3)'!AL7/'CheckoutGuard — Business pl (3)'!AL5),1),"") -> 96 | AM10: =IFERROR(CEILING('Model inputs'!AB37/('CheckoutGuard — Business pl (3)'!AM7/'CheckoutGuard — Business pl (3)'!AM5),1),"") -> 96 | AN10: =IFERROR(CEILING('Model inputs'!AB38/('CheckoutGuard — Business pl (3)'!AN7/'CheckoutGuard — Business pl (3)'!AN5),1),"") -> 97
A11: Cumulative operating result | B11: ='CheckoutGuard — Forecast · Chec'!M49+'CheckoutGuard — Business pl (3)'!B9 -> -54260.063 | C11: ='Model inputs'!N32+'CheckoutGuard — Business pl (3)'!C9 -> -71113.737 | D11: ='Model inputs'!N33+'CheckoutGuard — Business pl (3)'!D9 -> -25549.65 | E11: ='CheckoutGuard — Business pl (3)'!B11+'CheckoutGuard — Business pl (3)'!E9 -> -56194.556 | F11: ='CheckoutGuard — Business pl (3)'!C11+'CheckoutGuard — Business pl (3)'!F9 -> -76351.61 | G11: ='CheckoutGuard — Business pl (3)'!D11+'CheckoutGuard — Business pl (3)'!G9 -> -21357.561 | H11: ='CheckoutGuard — Business pl (3)'!E11+'CheckoutGuard — Business pl (3)'!H9 -> -57669.738 | I11: ='CheckoutGuard — Business pl (3)'!F11+'CheckoutGuard — Business pl (3)'!I9 -> -81507.094 | J11: ='CheckoutGuard — Business pl (3)'!G11+'CheckoutGuard — Business pl (3)'!J9 -> -15852.744 | K11: ='CheckoutGuard — Business pl (3)'!H11+'CheckoutGuard — Business pl (3)'!K9 -> -58669.125 | L11: ='CheckoutGuard — Business pl (3)'!I11+'CheckoutGuard — Business pl (3)'!L9 -> -86584.308 | ... AN11: ='CheckoutGuard — Business pl (3)'!AK11+'CheckoutGuard — Business pl (3)'!AN9 -> 137040.46

Sheet CheckoutGuard — Assumptions · C
A1: CheckoutGuard — Assumptions · Cost and growth assumptions — not actuals
A2: Financial model (3 pages) · Main Scenario
A4: Variable / dimension | B4: Value
A5: Input rate per million | B5: =0.25 -> 0.25
A6: Output rate per million | B6: =0.5 -> 0.5
A7: Provider cost multiplier | B7: =1 -> 1
A8: Extra attempt ratio | B8: =0.2 -> 0.2
A9: Timeout token allowance ratio | B9: =1 -> 1
A10: Browser seconds per attempt | B10: =45 -> 45
A11: Browser cost per hour | B11: =0.12 -> 0.12
A12: Database cost per run | B12: =0.002 -> 0.002
A13: Evidence cost per run | B13: =0.001 -> 0.001
A14: Telemetry cost per run | B14: =0.0005 -> 0.0005
A15: Support minutes per run | B15: =0.02 -> 0.02
A16: Support cost per hour | B16: =30 -> 30
A17: Run utilization | B17: =0.5 -> 0.5
A18: Prospect monthly growth | B18: =0.05 -> 0.05
A19: Monthly churn | B19: =0.03 -> 0.03
A20: Fixed app hosting per month | B20: =150 -> 150
A21: Fixed database per month | B21: =60 -> 60
A22: Fixed telemetry per month | B22: =30 -> 30
A23: Other overhead per month | B23: =60 -> 60
A24: Founder compensation per month | B24: =6000 -> 6000
A25: Sales budget per month | B25: =500 -> 500

Sheet CheckoutGuard — Assumptions · W
A1: CheckoutGuard — Assumptions · Workspace pricing options — assumptions
A2: Financial model (3 pages) · Main Scenario
A4: Variable / dimension | B4: Monthly price | C4: Included runs | D4: Included workspaces | E4: Support minutes per workspace | F4: Monthly qualified prospects | G4: Paid conversion
A5: Agency | B5: ='CheckoutGuard — Business pl (2)'!B5 -> 299 | C5: ='CheckoutGuard — Business pl (2)'!C5 -> 2000 | D5: ='CheckoutGuard — Business pl (2)'!D5 -> 10 | E5: =60 -> 60 | F5: =5 -> 5 | G5: =0.1 -> 0.1
A6: Developer | B6: ='CheckoutGuard — Business pl (2)'!B6 -> 29 | C6: ='CheckoutGuard — Business pl (2)'!C6 -> 100 | D6: ='CheckoutGuard — Business pl (2)'!D6 -> 1 | E6: =10 -> 10 | F6: =40 -> 40 | G6: =0.05 -> 0.05
A7: Team | B7: ='CheckoutGuard — Business pl (2)'!B7 -> 99 | C7: ='CheckoutGuard — Business pl (2)'!C7 -> 500 | D7: ='CheckoutGuard — Business pl (2)'!D7 -> 3 | E7: =25 -> 25 | F7: =20 -> 20 | G7: =0.1 -> 0.1

Sheet CheckoutGuard — Assumptions (2)
A1: CheckoutGuard — Assumptions · Cost per run and contribution economics — estimates
A2: Financial model (3 pages) · Main Scenario
A4: Variable / dimension | B4: Value
A5: Mean input tokens | B5: =AVERAGE('CheckoutGuard — Business plan ·'!B5,'CheckoutGuard — Business plan ·'!B6,'CheckoutGuard — Business plan ·'!B7) -> 12230
A6: Mean output tokens | B6: =AVERAGE('CheckoutGuard — Business plan ·'!C5,'CheckoutGuard — Business plan ·'!C6,'CheckoutGuard — Business plan ·'!C7) -> 194.33333
A7: Mean elapsed seconds | B7: =AVERAGE('CheckoutGuard — Business plan ·'!D5,'CheckoutGuard — Business plan ·'!D6,'CheckoutGuard — Business plan ·'!D7) -> 22.293333
A8: Known token estimate per run | B8: =('CheckoutGuard — Assumptions (2)'!B5*'CheckoutGuard — Assumptions · C'!B5+'CheckoutGuard — Assumptions (2)'!B6*'CheckoutGuard — Assumptions · C'!B6)/1000000 -> 0.0031546667
A9: AI allowance per completed run | B9: ='CheckoutGuard — Assumptions (2)'!B8*'CheckoutGuard — Assumptions · C'!B7*(1+'CheckoutGuard — Assumptions · C'!B8*'CheckoutGuard — Assumptions · C'!B9) -> 0.0037856
A10: Browser cost per completed run | B10: ='CheckoutGuard — Assumptions · C'!B10/3600*'CheckoutGuard — Assumptions · C'!B11*(1+'CheckoutGuard — Assumptions · C'!B8) -> 0.0018
A11: Support cost per run | B11: ='CheckoutGuard — Assumptions · C'!B15/60*'CheckoutGuard — Assumptions · C'!B16 -> 0.01
A12: Estimated cost per completed run | B12: ='CheckoutGuard — Assumptions (2)'!B9+'CheckoutGuard — Assumptions (2)'!B10+'CheckoutGuard — Assumptions · C'!B12+'CheckoutGuard — Assumptions · C'!B13+'CheckoutGuard — Assumptions · C'!B14+'CheckoutGuard — Assumptions (2)'!B11 -> 0.0190856
A13: Fixed monthly cost | B13: ='CheckoutGuard — Assumptions · C'!B20+'CheckoutGuard — Assumptions · C'!B21+'CheckoutGuard — Assumptions · C'!B22+'CheckoutGuard — Assumptions · C'!B23+'CheckoutGuard — Assumptions · C'!B24+'CheckoutGuard — Assumptions · C'!B25 -> 6800

Sheet CheckoutGuard — Assumptions · S
A1: CheckoutGuard — Assumptions · Sensitivity assumptions
A2: Financial model (3 pages) · Main Scenario
A4: Variable / dimension | B4: Value
A5: Payment processing rate | B5: =0.03 -> 0.03
A6: Payment transaction fee | B6: =0.3 -> 0.3
A7: Provider stress factor | B7: =10 -> 10
A8: Stress extra attempt ratio | B8: =1 -> 1
A9: Usage stress factor | B9: =2 -> 2
A10: Support stress factor | B10: =2 -> 2
A11: Browser stress factor | B11: =3 -> 3

Sheet CheckoutGuard — Forecast · Chec
A1: CheckoutGuard — Forecast · CheckoutGuard monthly forecast — assumptions
A2: Financial model (3 pages) · Main Scenario
A4: Variable / dimension | B4: 2026-10 | C4: 2026-11 | D4: 2026-12 | E4: 2027-01 | F4: 2027-02 | G4: 2027-03 | H4: 2027-04 | I4: 2027-05 | J4: 2027-06 | K4: 2027-07 | L4: 2027-08 | M4: 2027-09 | N4: 2027-10 | O4: 2027-11 | P4: 2027-12 | Q4: 2028-01 | R4: 2028-02 | S4: 2028-03 | T4: 2028-04 | U4: 2028-05 | V4: 2028-06 | W4: 2028-07 | X4: 2028-08 | Y4: 2028-09 | Z4: 2028-10
A5: Qualified prospects | B5: =SUM('CheckoutGuard — Forecast · Chec'!B6,'CheckoutGuard — Forecast · Chec'!B7,'CheckoutGuard — Forecast · Chec'!B8) -> 0 | C5: =SUM('CheckoutGuard — Forecast · Chec'!C6,'CheckoutGuard — Forecast · Chec'!C7,'CheckoutGuard — Forecast · Chec'!C8) -> 65 | D5: =SUM('CheckoutGuard — Forecast · Chec'!D6,'CheckoutGuard — Forecast · Chec'!D7,'CheckoutGuard — Forecast · Chec'!D8) -> 68.25 | E5: =SUM('CheckoutGuard — Forecast · Chec'!E6,'CheckoutGuard — Forecast · Chec'!E7,'CheckoutGuard — Forecast · Chec'!E8) -> 71.6625 | F5: =SUM('CheckoutGuard — Forecast · Chec'!F6,'CheckoutGuard — Forecast · Chec'!F7,'CheckoutGuard — Forecast · Chec'!F8) -> 75.245625 | G5: =SUM('CheckoutGuard — Forecast · Chec'!G6,'CheckoutGuard — Forecast · Chec'!G7,'CheckoutGuard — Forecast · Chec'!G8) -> 79.007906 | H5: =SUM('CheckoutGuard — Forecast · Chec'!H6,'CheckoutGuard — Forecast · Chec'!H7,'CheckoutGuard — Forecast · Chec'!H8) -> 82.958302 | I5: =SUM('CheckoutGuard — Forecast · Chec'!I6,'CheckoutGuard — Forecast · Chec'!I7,'CheckoutGuard — Forecast · Chec'!I8) -> 87.106217 | ... Z5: =SUM('CheckoutGuard — Forecast · Chec'!Z6,'CheckoutGuard — Forecast · Chec'!Z7,'CheckoutGuard — Forecast · Chec'!Z8) -> 199.64904
A6: Agency | B6: =0 -> 0 | C6: ='CheckoutGuard — Assumptions · W'!F5*IF(AND((1+'CheckoutGuard — Assumptions · C'!B18)=0,DATEDIF(DATE(2026,11,1),DATE(2026,11,1),"M")=0),SQRT(-1),(1+'CheckoutGuard — Assumptions · C'!B18)^DATEDIF(DATE(2026,11,1),DATE(2026,11,1),"M")) -> 5 | D6: ='CheckoutGuard — Assumptions · W'!F5*IF(AND((1+'CheckoutGuard — Assumptions · C'!B18)=0,DATEDIF(DATE(2026,11,1),DATE(2026,12,1),"M")=0),SQRT(-1),(1+'CheckoutGuard — Assumptions · C'!B18)^DATEDIF(DATE(2026,11,1),DATE(2026,12,1),"M")) -> 5.25 | E6: ='CheckoutGuard — Assumptions · W'!F5*IF(AND((1+'CheckoutGuard — Assumptions · C'!B18)=0,DATEDIF(DATE(2026,11,1),DATE(2027,1,1),"M")=0),SQRT(-1),(1+'CheckoutGuard — Assumptions · C'!B18)^DATEDIF(DATE(2026,11,1),DATE(2027,1,1),"M")) -> 5.5125 | F6: ='CheckoutGuard — Assumptions · W'!F5*IF(AND((1+'CheckoutGuard — Assumptions · C'!B18)=0,DATEDIF(DATE(2026,11,1),DATE(2027,2,1),"M")=0),SQRT(-1),(1+'CheckoutGuard — Assumptions · C'!B18)^DATEDIF(DATE(2026,11,1),DATE(2027,2,1),"M")) -> 5.788125 | G6: ='CheckoutGuard — Assumptions · W'!F5*IF(AND((1+'CheckoutGuard — Assumptions · C'!B18)=0,DATEDIF(DATE(2026,11,1),DATE(2027,3,1),"M")=0),SQRT(-1),(1+'CheckoutGuard — Assumptions · C'!B18)^DATEDIF(DATE(2026,11,1),DATE(2027,3,1),"M")) -> 6.0775313 | H6: ='CheckoutGuard — Assumptions · W'!F5*IF(AND((1+'CheckoutGuard — Assumptions · C'!B18)=0,DATEDIF(DATE(2026,11,1),DATE(2027,4,1),"M")=0),SQRT(-1),(1+'CheckoutGuard — Assumptions · C'!B18)^DATEDIF(DATE(2026,11,1),DATE(2027,4,1),"M")) -> 6.3814078 | I6: ='CheckoutGuard — Assumptions · W'!F5*IF(AND((1+'CheckoutGuard — Assumptions · C'!B18)=0,DATEDIF(DATE(2026,11,1),DATE(2027,5,1),"M")=0),SQRT(-1),(1+'CheckoutGuard — Assumptions · C'!B18)^DATEDIF(DATE(2026,11,1),DATE(2027,5,1),"M")) -> 6.7004782 | J6: ='CheckoutGuard — Assumptions · W'!F5*IF(AND((1+'CheckoutGuard — Assumptions · C'!B18)=0,DATEDIF(DATE(2026,11,1),DATE(2027,6,1),"M")=0),SQRT(-1),(1+'CheckoutGuard — Assumptions · C'!B18)^DATEDIF(DATE(2026,11,1),DATE(2027,6,1),"M")) -> 7.0355021 | K6: ='CheckoutGuard — Assumptions · W'!F5*IF(AND((1+'CheckoutGuard — Assumptions · C'!B18)=0,DATEDIF(DATE(2026,11,1),DATE(2027,7,1),"M")=0),SQRT(-1),(1+'CheckoutGuard — Assumptions · C'!B18)^DATEDIF(DATE(2026,11,1),DATE(2027,7,1),"M")) -> 7.3872772 | L6: ='CheckoutGuard — Assumptions · W'!F5*IF(AND((1+'CheckoutGuard — Assumptions · C'!B18)=0,DATEDIF(DATE(2026,11,1),DATE(2027,8,1),"M")=0),SQRT(-1),(1+'CheckoutGuard — Assumptions · C'!B18)^DATEDIF(DATE(2026,11,1),DATE(2027,8,1),"M")) -> 7.7566411 | M6: ='CheckoutGuard — Assumptions · W'!F5*IF(AND((1+'CheckoutGuard — Assumptions · C'!B18)=0,DATEDIF(DATE(2026,11,1),DATE(2027,9,1),"M")=0),SQRT(-1),(1+'CheckoutGuard — Assumptions · C'!B18)^DATEDIF(DATE(2026,11,1),DATE(2027,9,1),"M")) -> 8.1444731 | N6: ='CheckoutGuard — Assumptions · W'!F5*IF(AND((1+'CheckoutGuard — Assumptions · C'!B18)=0,DATEDIF(DATE(2026,11,1),DATE(2027,10,1),"M")=0),SQRT(-1),(1+'CheckoutGuard — Assumptions · C'!B18)^DATEDIF(DATE(2026,11,1),DATE(2027,10,1),"M")) -> 8.5516968 | O6: ='CheckoutGuard — Assumptions · W'!F5*IF(AND((1+'CheckoutGuard — Assumptions · C'!B18)=0,DATEDIF(DATE(2026,11,1),DATE(2027,11,1),"M")=0),SQRT(-1),(1+'CheckoutGuard — Assumptions · C'!B18)^DATEDIF(DATE(2026,11,1),DATE(2027,11,1),"M")) -> 8.9792816 | P6: ='CheckoutGuard — Assumptions · W'!F5*IF(AND((1+'CheckoutGuard — Assumptions · C'!B18)=0,DATEDIF(DATE(2026,11,1),DATE(2027,12,1),"M")=0),SQRT(-1),(1+'CheckoutGuard — Assumptions · C'!B18)^DATEDIF(DATE(2026,11,1),DATE(2027,12,1),"M")) -> 9.4282457 | Q6: ='CheckoutGuard — Assumptions · W'!F5*IF(AND((1+'CheckoutGuard — Assumptions · C'!B18)=0,DATEDIF(DATE(2026,11,1),DATE(2028,1,1),"M")=0),SQRT(-1),(1+'CheckoutGuard — Assumptions · C'!B18)^DATEDIF(DATE(2026,11,1),DATE(2028,1,1),"M")) -> 9.899658 | R6: ='CheckoutGuard — Assumptions · W'!F5*IF(AND((1+'CheckoutGuard — Assumptions · C'!B18)=0,DATEDIF(DATE(2026,11,1),DATE(2028,2,1),"M")=0),SQRT(-1),(1+'CheckoutGuard — Assumptions · C'!B18)^DATEDIF(DATE(2026,11,1),DATE(2028,2,1),"M")) -> 10.394641 | S6: ='CheckoutGuard — Assumptions · W'!F5*IF(AND((1+'CheckoutGuard — Assumptions · C'!B18)=0,DATEDIF(DATE(2026,11,1),DATE(2028,3,1),"M")=0),SQRT(-1),(1+'CheckoutGuard — Assumptions · C'!B18)^DATEDIF(DATE(2026,11,1),DATE(2028,3,1),"M")) -> 10.914373 | T6: ='CheckoutGuard — Assumptions · W'!F5*IF(AND((1+'CheckoutGuard — Assumptions · C'!B18)=0,DATEDIF(DATE(2026,11,1),DATE(2028,4,1),"M")=0),SQRT(-1),(1+'CheckoutGuard — Assumptions · C'!B18)^DATEDIF(DATE(2026,11,1),DATE(2028,4,1),"M")) -> 11.460092 | U6: ='CheckoutGuard — Assumptions · W'!F5*IF(AND((1+'CheckoutGuard — Assumptions · C'!B18)=0,DATEDIF(DATE(2026,11,1),DATE(2028,5,1),"M")=0),SQRT(-1),(1+'CheckoutGuard — Assumptions · C'!B18)^DATEDIF(DATE(2026,11,1),DATE(2028,5,1),"M")) -> 12.033096 | V6: ='CheckoutGuard — Assumptions · W'!F5*IF(AND((1+'CheckoutGuard — Assumptions · C'!B18)=0,DATEDIF(DATE(2026,11,1),DATE(2028,6,1),"M")=0),SQRT(-1),(1+'CheckoutGuard — Assumptions · C'!B18)^DATEDIF(DATE(2026,11,1),DATE(2028,6,1),"M")) -> 12.634751 | W6: ='CheckoutGuard — Assumptions · W'!F5*IF(AND((1+'CheckoutGuard — Assumptions · C'!B18)=0,DATEDIF(DATE(2026,11,1),DATE(2028,7,1),"M")=0),SQRT(-1),(1+'CheckoutGuard — Assumptions · C'!B18)^DATEDIF(DATE(2026,11,1),DATE(2028,7,1),"M")) -> 13.266489 | X6: ='CheckoutGuard — Assumptions · W'!F5*IF(AND((1+'CheckoutGuard — Assumptions · C'!B18)=0,DATEDIF(DATE(2026,11,1),DATE(2028,8,1),"M")=0),SQRT(-1),(1+'CheckoutGuard — Assumptions · C'!B18)^DATEDIF(DATE(2026,11,1),DATE(2028,8,1),"M")) -> 13.929813 | Y6: ='CheckoutGuard — Assumptions · W'!F5*IF(AND((1+'CheckoutGuard — Assumptions · C'!B18)=0,DATEDIF(DATE(2026,11,1),DATE(2028,9,1),"M")=0),SQRT(-1),(1+'CheckoutGuard — Assumptions · C'!B18)^DATEDIF(DATE(2026,11,1),DATE(2028,9,1),"M")) -> 14.626304 | Z6: ='CheckoutGuard — Assumptions · W'!F5*IF(AND((1+'CheckoutGuard — Assumptions · C'!B18)=0,DATEDIF(DATE(2026,11,1),DATE(2028,10,1),"M")=0),SQRT(-1),(1+'CheckoutGuard — Assumptions · C'!B18)^DATEDIF(DATE(2026,11,1),DATE(2028,10,1),"M")) -> 15.357619
A7: Developer | B7: =0 -> 0 | C7: ='CheckoutGuard — Assumptions · W'!F6*IF(AND((1+'CheckoutGuard — Assumptions · C'!B18)=0,DATEDIF(DATE(2026,11,1),DATE(2026,11,1),"M")=0),SQRT(-1),(1+'CheckoutGuard — Assumptions · C'!B18)^DATEDIF(DATE(2026,11,1),DATE(2026,11,1),"M")) -> 40 | D7: ='CheckoutGuard — Assumptions · W'!F6*IF(AND((1+'CheckoutGuard — Assumptions · C'!B18)=0,DATEDIF(DATE(2026,11,1),DATE(2026,12,1),"M")=0),SQRT(-1),(1+'CheckoutGuard — Assumptions · C'!B18)^DATEDIF(DATE(2026,11,1),DATE(2026,12,1),"M")) -> 42 | E7: ='CheckoutGuard — Assumptions · W'!F6*IF(AND((1+'CheckoutGuard — Assumptions · C'!B18)=0,DATEDIF(DATE(2026,11,1),DATE(2027,1,1),"M")=0),SQRT(-1),(1+'CheckoutGuard — Assumptions · C'!B18)^DATEDIF(DATE(2026,11,1),DATE(2027,1,1),"M")) -> 44.1 | F7: ='CheckoutGuard — Assumptions · W'!F6*IF(AND((1+'CheckoutGuard — Assumptions · C'!B18)=0,DATEDIF(DATE(2026,11,1),DATE(2027,2,1),"M")=0),SQRT(-1),(1+'CheckoutGuard — Assumptions · C'!B18)^DATEDIF(DATE(2026,11,1),DATE(2027,2,1),"M")) -> 46.305 | G7: ='CheckoutGuard — Assumptions · W'!F6*IF(AND((1+'CheckoutGuard — Assumptions · C'!B18)=0,DATEDIF(DATE(2026,11,1),DATE(2027,3,1),"M")=0),SQRT(-1),(1+'CheckoutGuard — Assumptions · C'!B18)^DATEDIF(DATE(2026,11,1),DATE(2027,3,1),"M")) -> 48.62025 | H7: ='CheckoutGuard — Assumptions · W'!F6*IF(AND((1+'CheckoutGuard — Assumptions · C'!B18)=0,DATEDIF(DATE(2026,11,1),DATE(2027,4,1),"M")=0),SQRT(-1),(1+'CheckoutGuard — Assumptions · C'!B18)^DATEDIF(DATE(2026,11,1),DATE(2027,4,1),"M")) -> 51.051263 | I7: ='CheckoutGuard — Assumptions · W'!F6*IF(AND((1+'CheckoutGuard — Assumptions · C'!B18)=0,DATEDIF(DATE(2026,11,1),DATE(2027,5,1),"M")=0),SQRT(-1),(1+'CheckoutGuard — Assumptions · C'!B18)^DATEDIF(DATE(2026,11,1),DATE(2027,5,1),"M")) -> 53.603826 | J7: ='CheckoutGuard — Assumptions · W'!F6*IF(AND((1+'CheckoutGuard — Assumptions · C'!B18)=0,DATEDIF(DATE(2026,11,1),DATE(2027,6,1),"M")=0),SQRT(-1),(1+'CheckoutGuard — Assumptions · C'!B18)^DATEDIF(DATE(2026,11,1),DATE(2027,6,1),"M")) -> 56.284017 | K7: ='CheckoutGuard — Assumptions · W'!F6*IF(AND((1+'CheckoutGuard — Assumptions · C'!B18)=0,DATEDIF(DATE(2026,11,1),DATE(2027,7,1),"M")=0),SQRT(-1),(1+'CheckoutGuard — Assumptions · C'!B18)^DATEDIF(DATE(2026,11,1),DATE(2027,7,1),"M")) -> 59.098218 | L7: ='CheckoutGuard — Assumptions · W'!F6*IF(AND((1+'CheckoutGuard — Assumptions · C'!B18)=0,DATEDIF(DATE(2026,11,1),DATE(2027,8,1),"M")=0),SQRT(-1),(1+'CheckoutGuard — Assumptions · C'!B18)^DATEDIF(DATE(2026,11,1),DATE(2027,8,1),"M")) -> 62.053129 | M7: ='CheckoutGuard — Assumptions · W'!F6*IF(AND((1+'CheckoutGuard — Assumptions · C'!B18)=0,DATEDIF(DATE(2026,11,1),DATE(2027,9,1),"M")=0),SQRT(-1),(1+'CheckoutGuard — Assumptions · C'!B18)^DATEDIF(DATE(2026,11,1),DATE(2027,9,1),"M")) -> 65.155785 | N7: ='CheckoutGuard — Assumptions · W'!F6*IF(AND((1+'CheckoutGuard — Assumptions · C'!B18)=0,DATEDIF(DATE(2026,11,1),DATE(2027,10,1),"M")=0),SQRT(-1),(1+'CheckoutGuard — Assumptions · C'!B18)^DATEDIF(DATE(2026,11,1),DATE(2027,10,1),"M")) -> 68.413574 | O7: ='CheckoutGuard — Assumptions · W'!F6*IF(AND((1+'CheckoutGuard — Assumptions · C'!B18)=0,DATEDIF(DATE(2026,11,1),DATE(2027,11,1),"M")=0),SQRT(-1),(1+'CheckoutGuard — Assumptions · C'!B18)^DATEDIF(DATE(2026,11,1),DATE(2027,11,1),"M")) -> 71.834253 | P7: ='CheckoutGuard — Assumptions · W'!F6*IF(AND((1+'CheckoutGuard — Assumptions · C'!B18)=0,DATEDIF(DATE(2026,11,1),DATE(2027,12,1),"M")=0),SQRT(-1),(1+'CheckoutGuard — Assumptions · C'!B18)^DATEDIF(DATE(2026,11,1),DATE(2027,12,1),"M")) -> 75.425966 | Q7: ='CheckoutGuard — Assumptions · W'!F6*IF(AND((1+'CheckoutGuard — Assumptions · C'!B18)=0,DATEDIF(DATE(2026,11,1),DATE(2028,1,1),"M")=0),SQRT(-1),(1+'CheckoutGuard — Assumptions · C'!B18)^DATEDIF(DATE(2026,11,1),DATE(2028,1,1),"M")) -> 79.197264 | R7: ='CheckoutGuard — Assumptions · W'!F6*IF(AND((1+'CheckoutGuard — Assumptions · C'!B18)=0,DATEDIF(DATE(2026,11,1),DATE(2028,2,1),"M")=0),SQRT(-1),(1+'CheckoutGuard — Assumptions · C'!B18)^DATEDIF(DATE(2026,11,1),DATE(2028,2,1),"M")) -> 83.157127 | S7: ='CheckoutGuard — Assumptions · W'!F6*IF(AND((1+'CheckoutGuard — Assumptions · C'!B18)=0,DATEDIF(DATE(2026,11,1),DATE(2028,3,1),"M")=0),SQRT(-1),(1+'CheckoutGuard — Assumptions · C'!B18)^DATEDIF(DATE(2026,11,1),DATE(2028,3,1),"M")) -> 87.314984 | T7: ='CheckoutGuard — Assumptions · W'!F6*IF(AND((1+'CheckoutGuard — Assumptions · C'!B18)=0,DATEDIF(DATE(2026,11,1),DATE(2028,4,1),"M")=0),SQRT(-1),(1+'CheckoutGuard — Assumptions · C'!B18)^DATEDIF(DATE(2026,11,1),DATE(2028,4,1),"M")) -> 91.680733 | U7: ='CheckoutGuard — Assumptions · W'!F6*IF(AND((1+'CheckoutGuard — Assumptions · C'!B18)=0,DATEDIF(DATE(2026,11,1),DATE(2028,5,1),"M")=0),SQRT(-1),(1+'CheckoutGuard — Assumptions · C'!B18)^DATEDIF(DATE(2026,11,1),DATE(2028,5,1),"M")) -> 96.264769 | V7: ='CheckoutGuard — Assumptions · W'!F6*IF(AND((1+'CheckoutGuard — Assumptions · C'!B18)=0,DATEDIF(DATE(2026,11,1),DATE(2028,6,1),"M")=0),SQRT(-1),(1+'CheckoutGuard — Assumptions · C'!B18)^DATEDIF(DATE(2026,11,1),DATE(2028,6,1),"M")) -> 101.07801 | W7: ='CheckoutGuard — Assumptions · W'!F6*IF(AND((1+'CheckoutGuard — Assumptions · C'!B18)=0,DATEDIF(DATE(2026,11,1),DATE(2028,7,1),"M")=0),SQRT(-1),(1+'CheckoutGuard — Assumptions · C'!B18)^DATEDIF(DATE(2026,11,1),DATE(2028,7,1),"M")) -> 106.13191 | X7: ='CheckoutGuard — Assumptions · W'!F6*IF(AND((1+'CheckoutGuard — Assumptions · C'!B18)=0,DATEDIF(DATE(2026,11,1),DATE(2028,8,1),"M")=0),SQRT(-1),(1+'CheckoutGuard — Assumptions · C'!B18)^DATEDIF(DATE(2026,11,1),DATE(2028,8,1),"M")) -> 111.4385 | Y7: ='CheckoutGuard — Assumptions · W'!F6*IF(AND((1+'CheckoutGuard — Assumptions · C'!B18)=0,DATEDIF(DATE(2026,11,1),DATE(2028,9,1),"M")=0),SQRT(-1),(1+'CheckoutGuard — Assumptions · C'!B18)^DATEDIF(DATE(2026,11,1),DATE(2028,9,1),"M")) -> 117.01043 | Z7: ='CheckoutGuard — Assumptions · W'!F6*IF(AND((1+'CheckoutGuard — Assumptions · C'!B18)=0,DATEDIF(DATE(2026,11,1),DATE(2028,10,1),"M")=0),SQRT(-1),(1+'CheckoutGuard — Assumptions · C'!B18)^DATEDIF(DATE(2026,11,1),DATE(2028,10,1),"M")) -> 122.86095
A8: Team | B8: =0 -> 0 | C8: ='CheckoutGuard — Assumptions · W'!F7*IF(AND((1+'CheckoutGuard — Assumptions · C'!B18)=0,DATEDIF(DATE(2026,11,1),DATE(2026,11,1),"M")=0),SQRT(-1),(1+'CheckoutGuard — Assumptions · C'!B18)^DATEDIF(DATE(2026,11,1),DATE(2026,11,1),"M")) -> 20 | D8: ='CheckoutGuard — Assumptions · W'!F7*IF(AND((1+'CheckoutGuard — Assumptions · C'!B18)=0,DATEDIF(DATE(2026,11,1),DATE(2026,12,1),"M")=0),SQRT(-1),(1+'CheckoutGuard — Assumptions · C'!B18)^DATEDIF(DATE(2026,11,1),DATE(2026,12,1),"M")) -> 21 | E8: ='CheckoutGuard — Assumptions · W'!F7*IF(AND((1+'CheckoutGuard — Assumptions · C'!B18)=0,DATEDIF(DATE(2026,11,1),DATE(2027,1,1),"M")=0),SQRT(-1),(1+'CheckoutGuard — Assumptions · C'!B18)^DATEDIF(DATE(2026,11,1),DATE(2027,1,1),"M")) -> 22.05 | F8: ='CheckoutGuard — Assumptions · W'!F7*IF(AND((1+'CheckoutGuard — Assumptions · C'!B18)=0,DATEDIF(DATE(2026,11,1),DATE(2027,2,1),"M")=0),SQRT(-1),(1+'CheckoutGuard — Assumptions · C'!B18)^DATEDIF(DATE(2026,11,1),DATE(2027,2,1),"M")) -> 23.1525 | G8: ='CheckoutGuard — Assumptions · W'!F7*IF(AND((1+'CheckoutGuard — Assumptions · C'!B18)=0,DATEDIF(DATE(2026,11,1),DATE(2027,3,1),"M")=0),SQRT(-1),(1+'CheckoutGuard — Assumptions · C'!B18)^DATEDIF(DATE(2026,11,1),DATE(2027,3,1),"M")) -> 24.310125 | H8: ='CheckoutGuard — Assumptions · W'!F7*IF(AND((1+'CheckoutGuard — Assumptions · C'!B18)=0,DATEDIF(DATE(2026,11,1),DATE(2027,4,1),"M")=0),SQRT(-1),(1+'CheckoutGuard — Assumptions · C'!B18)^DATEDIF(DATE(2026,11,1),DATE(2027,4,1),"M")) -> 25.525631 | I8: ='CheckoutGuard — Assumptions · W'!F7*IF(AND((1+'CheckoutGuard — Assumptions · C'!B18)=0,DATEDIF(DATE(2026,11,1),DATE(2027,5,1),"M")=0),SQRT(-1),(1+'CheckoutGuard — Assumptions · C'!B18)^DATEDIF(DATE(2026,11,1),DATE(2027,5,1),"M")) -> 26.801913 | J8: ='CheckoutGuard — Assumptions · W'!F7*IF(AND((1+'CheckoutGuard — Assumptions · C'!B18)=0,DATEDIF(DATE(2026,11,1),DATE(2027,6,1),"M")=0),SQRT(-1),(1+'CheckoutGuard — Assumptions · C'!B18)^DATEDIF(DATE(2026,11,1),DATE(2027,6,1),"M")) -> 28.142008 | K8: ='CheckoutGuard — Assumptions · W'!F7*IF(AND((1+'CheckoutGuard — Assumptions · C'!B18)=0,DATEDIF(DATE(2026,11,1),DATE(2027,7,1),"M")=0),SQRT(-1),(1+'CheckoutGuard — Assumptions · C'!B18)^DATEDIF(DATE(2026,11,1),DATE(2027,7,1),"M")) -> 29.549109 | L8: ='CheckoutGuard — Assumptions · W'!F7*IF(AND((1+'CheckoutGuard — Assumptions · C'!B18)=0,DATEDIF(DATE(2026,11,1),DATE(2027,8,1),"M")=0),SQRT(-1),(1+'CheckoutGuard — Assumptions · C'!B18)^DATEDIF(DATE(2026,11,1),DATE(2027,8,1),"M")) -> 31.026564 | M8: ='CheckoutGuard — Assumptions · W'!F7*IF(AND((1+'CheckoutGuard — Assumptions · C'!B18)=0,DATEDIF(DATE(2026,11,1),DATE(2027,9,1),"M")=0),SQRT(-1),(1+'CheckoutGuard — Assumptions · C'!B18)^DATEDIF(DATE(2026,11,1),DATE(2027,9,1),"M")) -> 32.577893 | N8: ='CheckoutGuard — Assumptions · W'!F7*IF(AND((1+'CheckoutGuard — Assumptions · C'!B18)=0,DATEDIF(DATE(2026,11,1),DATE(2027,10,1),"M")=0),SQRT(-1),(1+'CheckoutGuard — Assumptions · C'!B18)^DATEDIF(DATE(2026,11,1),DATE(2027,10,1),"M")) -> 34.206787 | O8: ='CheckoutGuard — Assumptions · W'!F7*IF(AND((1+'CheckoutGuard — Assumptions · C'!B18)=0,DATEDIF(DATE(2026,11,1),DATE(2027,11,1),"M")=0),SQRT(-1),(1+'CheckoutGuard — Assumptions · C'!B18)^DATEDIF(DATE(2026,11,1),DATE(2027,11,1),"M")) -> 35.917127 | P8: ='CheckoutGuard — Assumptions · W'!F7*IF(AND((1+'CheckoutGuard — Assumptions · C'!B18)=0,DATEDIF(DATE(2026,11,1),DATE(2027,12,1),"M")=0),SQRT(-1),(1+'CheckoutGuard — Assumptions · C'!B18)^DATEDIF(DATE(2026,11,1),DATE(2027,12,1),"M")) -> 37.712983 | Q8: ='CheckoutGuard — Assumptions · W'!F7*IF(AND((1+'CheckoutGuard — Assumptions · C'!B18)=0,DATEDIF(DATE(2026,11,1),DATE(2028,1,1),"M")=0),SQRT(-1),(1+'CheckoutGuard — Assumptions · C'!B18)^DATEDIF(DATE(2026,11,1),DATE(2028,1,1),"M")) -> 39.598632 | R8: ='CheckoutGuard — Assumptions · W'!F7*IF(AND((1+'CheckoutGuard — Assumptions · C'!B18)=0,DATEDIF(DATE(2026,11,1),DATE(2028,2,1),"M")=0),SQRT(-1),(1+'CheckoutGuard — Assumptions · C'!B18)^DATEDIF(DATE(2026,11,1),DATE(2028,2,1),"M")) -> 41.578564 | S8: ='CheckoutGuard — Assumptions · W'!F7*IF(AND((1+'CheckoutGuard — Assumptions · C'!B18)=0,DATEDIF(DATE(2026,11,1),DATE(2028,3,1),"M")=0),SQRT(-1),(1+'CheckoutGuard — Assumptions · C'!B18)^DATEDIF(DATE(2026,11,1),DATE(2028,3,1),"M")) -> 43.657492 | T8: ='CheckoutGuard — Assumptions · W'!F7*IF(AND((1+'CheckoutGuard — Assumptions · C'!B18)=0,DATEDIF(DATE(2026,11,1),DATE(2028,4,1),"M")=0),SQRT(-1),(1+'CheckoutGuard — Assumptions · C'!B18)^DATEDIF(DATE(2026,11,1),DATE(2028,4,1),"M")) -> 45.840366 | U8: ='CheckoutGuard — Assumptions · W'!F7*IF(AND((1+'CheckoutGuard — Assumptions · C'!B18)=0,DATEDIF(DATE(2026,11,1),DATE(2028,5,1),"M")=0),SQRT(-1),(1+'CheckoutGuard — Assumptions · C'!B18)^DATEDIF(DATE(2026,11,1),DATE(2028,5,1),"M")) -> 48.132385 | V8: ='CheckoutGuard — Assumptions · W'!F7*IF(AND((1+'CheckoutGuard — Assumptions · C'!B18)=0,DATEDIF(DATE(2026,11,1),DATE(2028,6,1),"M")=0),SQRT(-1),(1+'CheckoutGuard — Assumptions · C'!B18)^DATEDIF(DATE(2026,11,1),DATE(2028,6,1),"M")) -> 50.539004 | W8: ='CheckoutGuard — Assumptions · W'!F7*IF(AND((1+'CheckoutGuard — Assumptions · C'!B18)=0,DATEDIF(DATE(2026,11,1),DATE(2028,7,1),"M")=0),SQRT(-1),(1+'CheckoutGuard — Assumptions · C'!B18)^DATEDIF(DATE(2026,11,1),DATE(2028,7,1),"M")) -> 53.065954 | X8: ='CheckoutGuard — Assumptions · W'!F7*IF(AND((1+'CheckoutGuard — Assumptions · C'!B18)=0,DATEDIF(DATE(2026,11,1),DATE(2028,8,1),"M")=0),SQRT(-1),(1+'CheckoutGuard — Assumptions · C'!B18)^DATEDIF(DATE(2026,11,1),DATE(2028,8,1),"M")) -> 55.719252 | Y8: ='CheckoutGuard — Assumptions · W'!F7*IF(AND((1+'CheckoutGuard — Assumptions · C'!B18)=0,DATEDIF(DATE(2026,11,1),DATE(2028,9,1),"M")=0),SQRT(-1),(1+'CheckoutGuard — Assumptions · C'!B18)^DATEDIF(DATE(2026,11,1),DATE(2028,9,1),"M")) -> 58.505214 | Z8: ='CheckoutGuard — Assumptions · W'!F7*IF(AND((1+'CheckoutGuard — Assumptions · C'!B18)=0,DATEDIF(DATE(2026,11,1),DATE(2028,10,1),"M")=0),SQRT(-1),(1+'CheckoutGuard — Assumptions · C'!B18)^DATEDIF(DATE(2026,11,1),DATE(2028,10,1),"M")) -> 61.430475
A9: New paid subscriptions | B9: =SUM('CheckoutGuard — Forecast · Chec'!B10,'CheckoutGuard — Forecast · Chec'!B11,'CheckoutGuard — Forecast · Chec'!B12) -> 0 | C9: =SUM('CheckoutGuard — Forecast · Chec'!C10,'CheckoutGuard — Forecast · Chec'!C11,'CheckoutGuard — Forecast · Chec'!C12) -> 4.5 | D9: =SUM('CheckoutGuard — Forecast · Chec'!D10,'CheckoutGuard — Forecast · Chec'!D11,'CheckoutGuard — Forecast · Chec'!D12) -> 4.725 | E9: =SUM('CheckoutGuard — Forecast · Chec'!E10,'CheckoutGuard — Forecast · Chec'!E11,'CheckoutGuard — Forecast · Chec'!E12) -> 4.96125 | F9: =SUM('CheckoutGuard — Forecast · Chec'!F10,'CheckoutGuard — Forecast · Chec'!F11,'CheckoutGuard — Forecast · Chec'!F12) -> 5.2093125 | G9: =SUM('CheckoutGuard — Forecast · Chec'!G10,'CheckoutGuard — Forecast · Chec'!G11,'CheckoutGuard — Forecast · Chec'!G12) -> 5.4697781 | H9: =SUM('CheckoutGuard — Forecast · Chec'!H10,'CheckoutGuard — Forecast · Chec'!H11,'CheckoutGuard — Forecast · Chec'!H12) -> 5.743267 | I9: =SUM('CheckoutGuard — Forecast · Chec'!I10,'CheckoutGuard — Forecast · Chec'!I11,'CheckoutGuard — Forecast · Chec'!I12) -> 6.0304304 | ... Z9: =SUM('CheckoutGuard — Forecast · Chec'!Z10,'CheckoutGuard — Forecast · Chec'!Z11,'CheckoutGuard — Forecast · Chec'!Z12) -> 13.821857
A10: Agency | B10: ='CheckoutGuard — Forecast · Chec'!B6*'CheckoutGuard — Assumptions · W'!G5 -> 0 | C10: ='CheckoutGuard — Forecast · Chec'!C6*'CheckoutGuard — Assumptions · W'!G5 -> 0.5 | D10: ='CheckoutGuard — Forecast · Chec'!D6*'CheckoutGuard — Assumptions · W'!G5 -> 0.525 | E10: ='CheckoutGuard — Forecast · Chec'!E6*'CheckoutGuard — Assumptions · W'!G5 -> 0.55125 | F10: ='CheckoutGuard — Forecast · Chec'!F6*'CheckoutGuard — Assumptions · W'!G5 -> 0.5788125 | G10: ='CheckoutGuard — Forecast · Chec'!G6*'CheckoutGuard — Assumptions · W'!G5 -> 0.60775313 | H10: ='CheckoutGuard — Forecast · Chec'!H6*'CheckoutGuard — Assumptions · W'!G5 -> 0.63814078 | I10: ='CheckoutGuard — Forecast · Chec'!I6*'CheckoutGuard — Assumptions · W'!G5 -> 0.67004782 | J10: ='CheckoutGuard — Forecast · Chec'!J6*'CheckoutGuard — Assumptions · W'!G5 -> 0.70355021 | K10: ='CheckoutGuard — Forecast · Chec'!K6*'CheckoutGuard — Assumptions · W'!G5 -> 0.73872772 | L10: ='CheckoutGuard — Forecast · Chec'!L6*'CheckoutGuard — Assumptions · W'!G5 -> 0.77566411 | M10: ='CheckoutGuard — Forecast · Chec'!M6*'CheckoutGuard — Assumptions · W'!G5 -> 0.81444731 | N10: ='CheckoutGuard — Forecast · Chec'!N6*'CheckoutGuard — Assumptions · W'!G5 -> 0.85516968 | O10: ='CheckoutGuard — Forecast · Chec'!O6*'CheckoutGuard — Assumptions · W'!G5 -> 0.89792816 | P10: ='CheckoutGuard — Forecast · Chec'!P6*'CheckoutGuard — Assumptions · W'!G5 -> 0.94282457 | Q10: ='CheckoutGuard — Forecast · Chec'!Q6*'CheckoutGuard — Assumptions · W'!G5 -> 0.9899658 | R10: ='CheckoutGuard — Forecast · Chec'!R6*'CheckoutGuard — Assumptions · W'!G5 -> 1.0394641 | S10: ='CheckoutGuard — Forecast · Chec'!S6*'CheckoutGuard — Assumptions · W'!G5 -> 1.0914373 | T10: ='CheckoutGuard — Forecast · Chec'!T6*'CheckoutGuard — Assumptions · W'!G5 -> 1.1460092 | U10: ='CheckoutGuard — Forecast · Chec'!U6*'CheckoutGuard — Assumptions · W'!G5 -> 1.2033096 | V10: ='CheckoutGuard — Forecast · Chec'!V6*'CheckoutGuard — Assumptions · W'!G5 -> 1.2634751 | W10: ='CheckoutGuard — Forecast · Chec'!W6*'CheckoutGuard — Assumptions · W'!G5 -> 1.3266489 | X10: ='CheckoutGuard — Forecast · Chec'!X6*'CheckoutGuard — Assumptions · W'!G5 -> 1.3929813 | Y10: ='CheckoutGuard — Forecast · Chec'!Y6*'CheckoutGuard — Assumptions · W'!G5 -> 1.4626304 | Z10: ='CheckoutGuard — Forecast · Chec'!Z6*'CheckoutGuard — Assumptions · W'!G5 -> 1.5357619
A11: Developer | B11: ='CheckoutGuard — Forecast · Chec'!B7*'CheckoutGuard — Assumptions · W'!G6 -> 0 | C11: ='CheckoutGuard — Forecast · Chec'!C7*'CheckoutGuard — Assumptions · W'!G6 -> 2 | D11: ='CheckoutGuard — Forecast · Chec'!D7*'CheckoutGuard — Assumptions · W'!G6 -> 2.1 | E11: ='CheckoutGuard — Forecast · Chec'!E7*'CheckoutGuard — Assumptions · W'!G6 -> 2.205 | F11: ='CheckoutGuard — Forecast · Chec'!F7*'CheckoutGuard — Assumptions · W'!G6 -> 2.31525 | G11: ='CheckoutGuard — Forecast · Chec'!G7*'CheckoutGuard — Assumptions · W'!G6 -> 2.4310125 | H11: ='CheckoutGuard — Forecast · Chec'!H7*'CheckoutGuard — Assumptions · W'!G6 -> 2.5525631 | I11: ='CheckoutGuard — Forecast · Chec'!I7*'CheckoutGuard — Assumptions · W'!G6 -> 2.6801913 | J11: ='CheckoutGuard — Forecast · Chec'!J7*'CheckoutGuard — Assumptions · W'!G6 -> 2.8142008 | K11: ='CheckoutGuard — Forecast · Chec'!K7*'CheckoutGuard — Assumptions · W'!G6 -> 2.9549109 | L11: ='CheckoutGuard — Forecast · Chec'!L7*'CheckoutGuard — Assumptions · W'!G6 -> 3.1026564 | M11: ='CheckoutGuard — Forecast · Chec'!M7*'CheckoutGuard — Assumptions · W'!G6 -> 3.2577893 | N11: ='CheckoutGuard — Forecast · Chec'!N7*'CheckoutGuard — Assumptions · W'!G6 -> 3.4206787 | O11: ='CheckoutGuard — Forecast · Chec'!O7*'CheckoutGuard — Assumptions · W'!G6 -> 3.5917127 | P11: ='CheckoutGuard — Forecast · Chec'!P7*'CheckoutGuard — Assumptions · W'!G6 -> 3.7712983 | Q11: ='CheckoutGuard — Forecast · Chec'!Q7*'CheckoutGuard — Assumptions · W'!G6 -> 3.9598632 | R11: ='CheckoutGuard — Forecast · Chec'!R7*'CheckoutGuard — Assumptions · W'!G6 -> 4.1578564 | S11: ='CheckoutGuard — Forecast · Chec'!S7*'CheckoutGuard — Assumptions · W'!G6 -> 4.3657492 | T11: ='CheckoutGuard — Forecast · Chec'!T7*'CheckoutGuard — Assumptions · W'!G6 -> 4.5840366 | U11: ='CheckoutGuard — Forecast · Chec'!U7*'CheckoutGuard — Assumptions · W'!G6 -> 4.8132385 | V11: ='CheckoutGuard — Forecast · Chec'!V7*'CheckoutGuard — Assumptions · W'!G6 -> 5.0539004 | W11: ='CheckoutGuard — Forecast · Chec'!W7*'CheckoutGuard — Assumptions · W'!G6 -> 5.3065954 | X11: ='CheckoutGuard — Forecast · Chec'!X7*'CheckoutGuard — Assumptions · W'!G6 -> 5.5719252 | Y11: ='CheckoutGuard — Forecast · Chec'!Y7*'CheckoutGuard — Assumptions · W'!G6 -> 5.8505214 | Z11: ='CheckoutGuard — Forecast · Chec'!Z7*'CheckoutGuard — Assumptions · W'!G6 -> 6.1430475
A12: Team | B12: ='CheckoutGuard — Forecast · Chec'!B8*'CheckoutGuard — Assumptions · W'!G7 -> 0 | C12: ='CheckoutGuard — Forecast · Chec'!C8*'CheckoutGuard — Assumptions · W'!G7 -> 2 | D12: ='CheckoutGuard — Forecast · Chec'!D8*'CheckoutGuard — Assumptions · W'!G7 -> 2.1 | E12: ='CheckoutGuard — Forecast · Chec'!E8*'CheckoutGuard — Assumptions · W'!G7 -> 2.205 | F12: ='CheckoutGuard — Forecast · Chec'!F8*'CheckoutGuard — Assumptions · W'!G7 -> 2.31525 | G12: ='CheckoutGuard — Forecast · Chec'!G8*'CheckoutGuard — Assumptions · W'!G7 -> 2.4310125 | H12: ='CheckoutGuard — Forecast · Chec'!H8*'CheckoutGuard — Assumptions · W'!G7 -> 2.5525631 | I12: ='CheckoutGuard — Forecast · Chec'!I8*'CheckoutGuard — Assumptions · W'!G7 -> 2.6801913 | J12: ='CheckoutGuard — Forecast · Chec'!J8*'CheckoutGuard — Assumptions · W'!G7 -> 2.8142008 | K12: ='CheckoutGuard — Forecast · Chec'!K8*'CheckoutGuard — Assumptions · W'!G7 -> 2.9549109 | L12: ='CheckoutGuard — Forecast · Chec'!L8*'CheckoutGuard — Assumptions · W'!G7 -> 3.1026564 | M12: ='CheckoutGuard — Forecast · Chec'!M8*'CheckoutGuard — Assumptions · W'!G7 -> 3.2577893 | N12: ='CheckoutGuard — Forecast · Chec'!N8*'CheckoutGuard — Assumptions · W'!G7 -> 3.4206787 | O12: ='CheckoutGuard — Forecast · Chec'!O8*'CheckoutGuard — Assumptions · W'!G7 -> 3.5917127 | P12: ='CheckoutGuard — Forecast · Chec'!P8*'CheckoutGuard — Assumptions · W'!G7 -> 3.7712983 | Q12: ='CheckoutGuard — Forecast · Chec'!Q8*'CheckoutGuard — Assumptions · W'!G7 -> 3.9598632 | R12: ='CheckoutGuard — Forecast · Chec'!R8*'CheckoutGuard — Assumptions · W'!G7 -> 4.1578564 | S12: ='CheckoutGuard — Forecast · Chec'!S8*'CheckoutGuard — Assumptions · W'!G7 -> 4.3657492 | T12: ='CheckoutGuard — Forecast · Chec'!T8*'CheckoutGuard — Assumptions · W'!G7 -> 4.5840366 | U12: ='CheckoutGuard — Forecast · Chec'!U8*'CheckoutGuard — Assumptions · W'!G7 -> 4.8132385 | V12: ='CheckoutGuard — Forecast · Chec'!V8*'CheckoutGuard — Assumptions · W'!G7 -> 5.0539004 | W12: ='CheckoutGuard — Forecast · Chec'!W8*'CheckoutGuard — Assumptions · W'!G7 -> 5.3065954 | X12: ='CheckoutGuard — Forecast · Chec'!X8*'CheckoutGuard — Assumptions · W'!G7 -> 5.5719252 | Y12: ='CheckoutGuard — Forecast · Chec'!Y8*'CheckoutGuard — Assumptions · W'!G7 -> 5.8505214 | Z12: ='CheckoutGuard — Forecast · Chec'!Z8*'CheckoutGuard — Assumptions · W'!G7 -> 6.1430475
A13: Lost subscriptions | B13: =SUM('CheckoutGuard — Forecast · Chec'!B14,'CheckoutGuard — Forecast · Chec'!B15,'CheckoutGuard — Forecast · Chec'!B16) -> 0 | C13: =SUM('CheckoutGuard — Forecast · Chec'!C14,'CheckoutGuard — Forecast · Chec'!C15,'CheckoutGuard — Forecast · Chec'!C16) -> 0 | D13: =SUM('CheckoutGuard — Forecast · Chec'!D14,'CheckoutGuard — Forecast · Chec'!D15,'CheckoutGuard — Forecast · Chec'!D16) -> 0.135 | E13: =SUM('CheckoutGuard — Forecast · Chec'!E14,'CheckoutGuard — Forecast · Chec'!E15,'CheckoutGuard — Forecast · Chec'!E16) -> 0.2727 | F13: =SUM('CheckoutGuard — Forecast · Chec'!F14,'CheckoutGuard — Forecast · Chec'!F15,'CheckoutGuard — Forecast · Chec'!F16) -> 0.4133565 | G13: =SUM('CheckoutGuard — Forecast · Chec'!G14,'CheckoutGuard — Forecast · Chec'!G15,'CheckoutGuard — Forecast · Chec'!G16) -> 0.55723518 | H13: =SUM('CheckoutGuard — Forecast · Chec'!H14,'CheckoutGuard — Forecast · Chec'!H15,'CheckoutGuard — Forecast · Chec'!H16) -> 0.70461147 | I13: =SUM('CheckoutGuard — Forecast · Chec'!I14,'CheckoutGuard — Forecast · Chec'!I15,'CheckoutGuard — Forecast · Chec'!I16) -> 0.85577114 | ... Z13: =SUM('CheckoutGuard — Forecast · Chec'!Z14,'CheckoutGuard — Forecast · Chec'!Z15,'CheckoutGuard — Forecast · Chec'!Z16) -> 4.3456793
A14: Agency | B14: ='Model inputs'!B7*'CheckoutGuard — Assumptions · C'!B19 -> 0 | C14: ='CheckoutGuard — Forecast · Chec'!B18*'CheckoutGuard — Assumptions · C'!B19 -> 0 | D14: ='CheckoutGuard — Forecast · Chec'!C18*'CheckoutGuard — Assumptions · C'!B19 -> 0.015 | E14: ='CheckoutGuard — Forecast · Chec'!D18*'CheckoutGuard — Assumptions · C'!B19 -> 0.0303 | F14: ='CheckoutGuard — Forecast · Chec'!E18*'CheckoutGuard — Assumptions · C'!B19 -> 0.0459285 | G14: ='CheckoutGuard — Forecast · Chec'!F18*'CheckoutGuard — Assumptions · C'!B19 -> 0.06191502 | H14: ='CheckoutGuard — Forecast · Chec'!G18*'CheckoutGuard — Assumptions · C'!B19 -> 0.078290163 | I14: ='CheckoutGuard — Forecast · Chec'!H18*'CheckoutGuard — Assumptions · C'!B19 -> 0.095085682 | J14: ='CheckoutGuard — Forecast · Chec'!I18*'CheckoutGuard — Assumptions · C'!B19 -> 0.11233455 | K14: ='CheckoutGuard — Forecast · Chec'!J18*'CheckoutGuard — Assumptions · C'!B19 -> 0.13007102 | L14: ='CheckoutGuard — Forecast · Chec'!K18*'CheckoutGuard — Assumptions · C'!B19 -> 0.14833072 | M14: ='CheckoutGuard — Forecast · Chec'!L18*'CheckoutGuard — Assumptions · C'!B19 -> 0.16715072 | N14: ='CheckoutGuard — Forecast · Chec'!M18*'CheckoutGuard — Assumptions · C'!B19 -> 0.18656962 | O14: ='CheckoutGuard — Forecast · Chec'!N18*'CheckoutGuard — Assumptions · C'!B19 -> 0.20662762 | P14: ='CheckoutGuard — Forecast · Chec'!O18*'CheckoutGuard — Assumptions · C'!B19 -> 0.22736663 | Q14: ='CheckoutGuard — Forecast · Chec'!P18*'CheckoutGuard — Assumptions · C'!B19 -> 0.24883037 | R14: ='CheckoutGuard — Forecast · Chec'!Q18*'CheckoutGuard — Assumptions · C'!B19 -> 0.27106444 | S14: ='CheckoutGuard — Forecast · Chec'!R18*'CheckoutGuard — Assumptions · C'!B19 -> 0.29411643 | T14: ='CheckoutGuard — Forecast · Chec'!S18*'CheckoutGuard — Assumptions · C'!B19 -> 0.31803605 | U14: ='CheckoutGuard — Forecast · Chec'!T18*'CheckoutGuard — Assumptions · C'!B19 -> 0.34287524 | V14: ='CheckoutGuard — Forecast · Chec'!U18*'CheckoutGuard — Assumptions · C'!B19 -> 0.36868828 | W14: ='CheckoutGuard — Forecast · Chec'!V18*'CheckoutGuard — Assumptions · C'!B19 -> 0.39553188 | X14: ='CheckoutGuard — Forecast · Chec'!W18*'CheckoutGuard — Assumptions · C'!B19 -> 0.42346539 | Y14: ='CheckoutGuard — Forecast · Chec'!X18*'CheckoutGuard — Assumptions · C'!B19 -> 0.45255087 | Z14: ='CheckoutGuard — Forecast · Chec'!Y18*'CheckoutGuard — Assumptions · C'!B19 -> 0.48285325
A15: Developer | B15: ='Model inputs'!B8*'CheckoutGuard — Assumptions · C'!B19 -> 0 | C15: ='CheckoutGuard — Forecast · Chec'!B19*'CheckoutGuard — Assumptions · C'!B19 -> 0 | D15: ='CheckoutGuard — Forecast · Chec'!C19*'CheckoutGuard — Assumptions · C'!B19 -> 0.06 | E15: ='CheckoutGuard — Forecast · Chec'!D19*'CheckoutGuard — Assumptions · C'!B19 -> 0.1212 | F15: ='CheckoutGuard — Forecast · Chec'!E19*'CheckoutGuard — Assumptions · C'!B19 -> 0.183714 | G15: ='CheckoutGuard — Forecast · Chec'!F19*'CheckoutGuard — Assumptions · C'!B19 -> 0.24766008 | H15: ='CheckoutGuard — Forecast · Chec'!G19*'CheckoutGuard — Assumptions · C'!B19 -> 0.31316065 | I15: ='CheckoutGuard — Forecast · Chec'!H19*'CheckoutGuard — Assumptions · C'!B19 -> 0.38034273 | J15: ='CheckoutGuard — Forecast · Chec'!I19*'CheckoutGuard — Assumptions · C'!B19 -> 0.44933818 | K15: ='CheckoutGuard — Forecast · Chec'!J19*'CheckoutGuard — Assumptions · C'!B19 -> 0.52028406 | L15: ='CheckoutGuard — Forecast · Chec'!K19*'CheckoutGuard — Assumptions · C'!B19 -> 0.59332287 | M15: ='CheckoutGuard — Forecast · Chec'!L19*'CheckoutGuard — Assumptions · C'!B19 -> 0.66860287 | N15: ='CheckoutGuard — Forecast · Chec'!M19*'CheckoutGuard — Assumptions · C'!B19 -> 0.74627847 | O15: ='CheckoutGuard — Forecast · Chec'!N19*'CheckoutGuard — Assumptions · C'!B19 -> 0.82651047 | P15: ='CheckoutGuard — Forecast · Chec'!O19*'CheckoutGuard — Assumptions · C'!B19 -> 0.90946654 | Q15: ='CheckoutGuard — Forecast · Chec'!P19*'CheckoutGuard — Assumptions · C'!B19 -> 0.99532149 | R15: ='CheckoutGuard — Forecast · Chec'!Q19*'CheckoutGuard — Assumptions · C'!B19 -> 1.0842577 | S15: ='CheckoutGuard — Forecast · Chec'!R19*'CheckoutGuard — Assumptions · C'!B19 -> 1.1764657 | T15: ='CheckoutGuard — Forecast · Chec'!S19*'CheckoutGuard — Assumptions · C'!B19 -> 1.2721442 | U15: ='CheckoutGuard — Forecast · Chec'!T19*'CheckoutGuard — Assumptions · C'!B19 -> 1.371501 | V15: ='CheckoutGuard — Forecast · Chec'!U19*'CheckoutGuard — Assumptions · C'!B19 -> 1.4747531 | W15: ='CheckoutGuard — Forecast · Chec'!V19*'CheckoutGuard — Assumptions · C'!B19 -> 1.5821275 | X15: ='CheckoutGuard — Forecast · Chec'!W19*'CheckoutGuard — Assumptions · C'!B19 -> 1.6938616 | Y15: ='CheckoutGuard — Forecast · Chec'!X19*'CheckoutGuard — Assumptions · C'!B19 -> 1.8102035 | Z15: ='CheckoutGuard — Forecast · Chec'!Y19*'CheckoutGuard — Assumptions · C'!B19 -> 1.931413
A16: Team | B16: ='Model inputs'!B9*'CheckoutGuard — Assumptions · C'!B19 -> 0 | C16: ='CheckoutGuard — Forecast · Chec'!B20*'CheckoutGuard — Assumptions · C'!B19 -> 0 | D16: ='CheckoutGuard — Forecast · Chec'!C20*'CheckoutGuard — Assumptions · C'!B19 -> 0.06 | E16: ='CheckoutGuard — Forecast · Chec'!D20*'CheckoutGuard — Assumptions · C'!B19 -> 0.1212 | F16: ='CheckoutGuard — Forecast · Chec'!E20*'CheckoutGuard — Assumptions · C'!B19 -> 0.183714 | G16: ='CheckoutGuard — Forecast · Chec'!F20*'CheckoutGuard — Assumptions · C'!B19 -> 0.24766008 | H16: ='CheckoutGuard — Forecast · Chec'!G20*'CheckoutGuard — Assumptions · C'!B19 -> 0.31316065 | I16: ='CheckoutGuard — Forecast · Chec'!H20*'CheckoutGuard — Assumptions · C'!B19 -> 0.38034273 | J16: ='CheckoutGuard — Forecast · Chec'!I20*'CheckoutGuard — Assumptions · C'!B19 -> 0.44933818 | K16: ='CheckoutGuard — Forecast · Chec'!J20*'CheckoutGuard — Assumptions · C'!B19 -> 0.52028406 | L16: ='CheckoutGuard — Forecast · Chec'!K20*'CheckoutGuard — Assumptions · C'!B19 -> 0.59332287 | M16: ='CheckoutGuard — Forecast · Chec'!L20*'CheckoutGuard — Assumptions · C'!B19 -> 0.66860287 | N16: ='CheckoutGuard — Forecast · Chec'!M20*'CheckoutGuard — Assumptions · C'!B19 -> 0.74627847 | O16: ='CheckoutGuard — Forecast · Chec'!N20*'CheckoutGuard — Assumptions · C'!B19 -> 0.82651047 | P16: ='CheckoutGuard — Forecast · Chec'!O20*'CheckoutGuard — Assumptions · C'!B19 -> 0.90946654 | Q16: ='CheckoutGuard — Forecast · Chec'!P20*'CheckoutGuard — Assumptions · C'!B19 -> 0.99532149 | R16: ='CheckoutGuard — Forecast · Chec'!Q20*'CheckoutGuard — Assumptions · C'!B19 -> 1.0842577 | S16: ='CheckoutGuard — Forecast · Chec'!R20*'CheckoutGuard — Assumptions · C'!B19 -> 1.1764657 | T16: ='CheckoutGuard — Forecast · Chec'!S20*'CheckoutGuard — Assumptions · C'!B19 -> 1.2721442 | U16: ='CheckoutGuard — Forecast · Chec'!T20*'CheckoutGuard — Assumptions · C'!B19 -> 1.371501 | V16: ='CheckoutGuard — Forecast · Chec'!U20*'CheckoutGuard — Assumptions · C'!B19 -> 1.4747531 | W16: ='CheckoutGuard — Forecast · Chec'!V20*'CheckoutGuard — Assumptions · C'!B19 -> 1.5821275 | X16: ='CheckoutGuard — Forecast · Chec'!W20*'CheckoutGuard — Assumptions · C'!B19 -> 1.6938616 | Y16: ='CheckoutGuard — Forecast · Chec'!X20*'CheckoutGuard — Assumptions · C'!B19 -> 1.8102035 | Z16: ='CheckoutGuard — Forecast · Chec'!Y20*'CheckoutGuard — Assumptions · C'!B19 -> 1.931413
A17: Active subscriptions | B17: =SUM('CheckoutGuard — Forecast · Chec'!B18,'CheckoutGuard — Forecast · Chec'!B19,'CheckoutGuard — Forecast · Chec'!B20) -> 0 | C17: =SUM('CheckoutGuard — Forecast · Chec'!C18,'CheckoutGuard — Forecast · Chec'!C19,'CheckoutGuard — Forecast · Chec'!C20) -> 4.5 | D17: =SUM('CheckoutGuard — Forecast · Chec'!D18,'CheckoutGuard — Forecast · Chec'!D19,'CheckoutGuard — Forecast · Chec'!D20) -> 9.09 | E17: =SUM('CheckoutGuard — Forecast · Chec'!E18,'CheckoutGuard — Forecast · Chec'!E19,'CheckoutGuard — Forecast · Chec'!E20) -> 13.77855 | F17: =SUM('CheckoutGuard — Forecast · Chec'!F18,'CheckoutGuard — Forecast · Chec'!F19,'CheckoutGuard — Forecast · Chec'!F20) -> 18.574506 | G17: =SUM('CheckoutGuard — Forecast · Chec'!G18,'CheckoutGuard — Forecast · Chec'!G19,'CheckoutGuard — Forecast · Chec'!G20) -> 23.487049 | H17: =SUM('CheckoutGuard — Forecast · Chec'!H18,'CheckoutGuard — Forecast · Chec'!H19,'CheckoutGuard — Forecast · Chec'!H20) -> 28.525705 | I17: =SUM('CheckoutGuard — Forecast · Chec'!I18,'CheckoutGuard — Forecast · Chec'!I19,'CheckoutGuard — Forecast · Chec'!I20) -> 33.700364 | ... Z17: =SUM('CheckoutGuard — Forecast · Chec'!Z18,'CheckoutGuard — Forecast · Chec'!Z19,'CheckoutGuard — Forecast · Chec'!Z20) -> 154.33215
A18: Agency | B18: =0 -> 0 | C18: ='CheckoutGuard — Forecast · Chec'!B18+'CheckoutGuard — Forecast · Chec'!C10-'CheckoutGuard — Forecast · Chec'!C14 -> 0.5 | D18: ='CheckoutGuard — Forecast · Chec'!C18+'CheckoutGuard — Forecast · Chec'!D10-'CheckoutGuard — Forecast · Chec'!D14 -> 1.01 | E18: ='CheckoutGuard — Forecast · Chec'!D18+'CheckoutGuard — Forecast · Chec'!E10-'CheckoutGuard — Forecast · Chec'!E14 -> 1.53095 | F18: ='CheckoutGuard — Forecast · Chec'!E18+'CheckoutGuard — Forecast · Chec'!F10-'CheckoutGuard — Forecast · Chec'!F14 -> 2.063834 | G18: ='CheckoutGuard — Forecast · Chec'!F18+'CheckoutGuard — Forecast · Chec'!G10-'CheckoutGuard — Forecast · Chec'!G14 -> 2.6096721 | H18: ='CheckoutGuard — Forecast · Chec'!G18+'CheckoutGuard — Forecast · Chec'!H10-'CheckoutGuard — Forecast · Chec'!H14 -> 3.1695227 | I18: ='CheckoutGuard — Forecast · Chec'!H18+'CheckoutGuard — Forecast · Chec'!I10-'CheckoutGuard — Forecast · Chec'!I14 -> 3.7444849 | J18: ='CheckoutGuard — Forecast · Chec'!I18+'CheckoutGuard — Forecast · Chec'!J10-'CheckoutGuard — Forecast · Chec'!J14 -> 4.3357005 | ... Z18: ='CheckoutGuard — Forecast · Chec'!Y18+'CheckoutGuard — Forecast · Chec'!Z10-'CheckoutGuard — Forecast · Chec'!Z14 -> 17.148017
A19: Developer | B19: =0 -> 0 | C19: ='CheckoutGuard — Forecast · Chec'!B19+'CheckoutGuard — Forecast · Chec'!C11-'CheckoutGuard — Forecast · Chec'!C15 -> 2 | D19: ='CheckoutGuard — Forecast · Chec'!C19+'CheckoutGuard — Forecast · Chec'!D11-'CheckoutGuard — Forecast · Chec'!D15 -> 4.04 | E19: ='CheckoutGuard — Forecast · Chec'!D19+'CheckoutGuard — Forecast · Chec'!E11-'CheckoutGuard — Forecast · Chec'!E15 -> 6.1238 | F19: ='CheckoutGuard — Forecast · Chec'!E19+'CheckoutGuard — Forecast · Chec'!F11-'CheckoutGuard — Forecast · Chec'!F15 -> 8.255336 | G19: ='CheckoutGuard — Forecast · Chec'!F19+'CheckoutGuard — Forecast · Chec'!G11-'CheckoutGuard — Forecast · Chec'!G15 -> 10.438688 | H19: ='CheckoutGuard — Forecast · Chec'!G19+'CheckoutGuard — Forecast · Chec'!H11-'CheckoutGuard — Forecast · Chec'!H15 -> 12.678091 | I19: ='CheckoutGuard — Forecast · Chec'!H19+'CheckoutGuard — Forecast · Chec'!I11-'CheckoutGuard — Forecast · Chec'!I15 -> 14.977939 | J19: ='CheckoutGuard — Forecast · Chec'!I19+'CheckoutGuard — Forecast · Chec'!J11-'CheckoutGuard — Forecast · Chec'!J15 -> 17.342802 | ... Z19: ='CheckoutGuard — Forecast · Chec'!Y19+'CheckoutGuard — Forecast · Chec'!Z11-'CheckoutGuard — Forecast · Chec'!Z15 -> 68.592068
A20: Team | B20: =0 -> 0 | C20: ='CheckoutGuard — Forecast · Chec'!B20+'CheckoutGuard — Forecast · Chec'!C12-'CheckoutGuard — Forecast · Chec'!C16 -> 2 | D20: ='CheckoutGuard — Forecast · Chec'!C20+'CheckoutGuard — Forecast · Chec'!D12-'CheckoutGuard — Forecast · Chec'!D16 -> 4.04 | E20: ='CheckoutGuard — Forecast · Chec'!D20+'CheckoutGuard — Forecast · Chec'!E12-'CheckoutGuard — Forecast · Chec'!E16 -> 6.1238 | F20: ='CheckoutGuard — Forecast · Chec'!E20+'CheckoutGuard — Forecast · Chec'!F12-'CheckoutGuard — Forecast · Chec'!F16 -> 8.255336 | G20: ='CheckoutGuard — Forecast · Chec'!F20+'CheckoutGuard — Forecast · Chec'!G12-'CheckoutGuard — Forecast · Chec'!G16 -> 10.438688 | H20: ='CheckoutGuard — Forecast · Chec'!G20+'CheckoutGuard — Forecast · Chec'!H12-'CheckoutGuard — Forecast · Chec'!H16 -> 12.678091 | I20: ='CheckoutGuard — Forecast · Chec'!H20+'CheckoutGuard — Forecast · Chec'!I12-'CheckoutGuard — Forecast · Chec'!I16 -> 14.977939 | J20: ='CheckoutGuard — Forecast · Chec'!I20+'CheckoutGuard — Forecast · Chec'!J12-'CheckoutGuard — Forecast · Chec'!J16 -> 17.342802 | ... Z20: ='CheckoutGuard — Forecast · Chec'!Y20+'CheckoutGuard — Forecast · Chec'!Z12-'CheckoutGuard — Forecast · Chec'!Z16 -> 68.592068
A21: Subscription revenue | B21: =SUM('CheckoutGuard — Forecast · Chec'!B22,'CheckoutGuard — Forecast · Chec'!B23,'CheckoutGuard — Forecast · Chec'!B24) -> 0 | C21: =SUM('CheckoutGuard — Forecast · Chec'!C22,'CheckoutGuard — Forecast · Chec'!C23,'CheckoutGuard — Forecast · Chec'!C24) -> 405.5 | D21: =SUM('CheckoutGuard — Forecast · Chec'!D22,'CheckoutGuard — Forecast · Chec'!D23,'CheckoutGuard — Forecast · Chec'!D24) -> 819.11 | E21: =SUM('CheckoutGuard — Forecast · Chec'!E22,'CheckoutGuard — Forecast · Chec'!E23,'CheckoutGuard — Forecast · Chec'!E24) -> 1241.6004 | F21: =SUM('CheckoutGuard — Forecast · Chec'!F22,'CheckoutGuard — Forecast · Chec'!F23,'CheckoutGuard — Forecast · Chec'!F24) -> 1673.7694 | G21: =SUM('CheckoutGuard — Forecast · Chec'!G22,'CheckoutGuard — Forecast · Chec'!G23,'CheckoutGuard — Forecast · Chec'!G24) -> 2116.4441 | H21: =SUM('CheckoutGuard — Forecast · Chec'!H22,'CheckoutGuard — Forecast · Chec'!H23,'CheckoutGuard — Forecast · Chec'!H24) -> 2570.4829 | I21: =SUM('CheckoutGuard — Forecast · Chec'!I22,'CheckoutGuard — Forecast · Chec'!I23,'CheckoutGuard — Forecast · Chec'!I24) -> 3036.7772 | ... Z21: =SUM('CheckoutGuard — Forecast · Chec'!Z22,'CheckoutGuard — Forecast · Chec'!Z23,'CheckoutGuard — Forecast · Chec'!Z24) -> 13907.042
A22: Agency | B22: ='CheckoutGuard — Forecast · Chec'!B18*'CheckoutGuard — Business pl (2)'!B5 -> 0 | C22: ='CheckoutGuard — Forecast · Chec'!C18*'CheckoutGuard — Business pl (2)'!B5 -> 149.5 | D22: ='CheckoutGuard — Forecast · Chec'!D18*'CheckoutGuard — Business pl (2)'!B5 -> 301.99 | E22: ='CheckoutGuard — Forecast · Chec'!E18*'CheckoutGuard — Business pl (2)'!B5 -> 457.75405 | F22: ='CheckoutGuard — Forecast · Chec'!F18*'CheckoutGuard — Business pl (2)'!B5 -> 617.08637 | G22: ='CheckoutGuard — Forecast · Chec'!G18*'CheckoutGuard — Business pl (2)'!B5 -> 780.29196 | H22: ='CheckoutGuard — Forecast · Chec'!H18*'CheckoutGuard — Business pl (2)'!B5 -> 947.68729 | I22: ='CheckoutGuard — Forecast · Chec'!I18*'CheckoutGuard — Business pl (2)'!B5 -> 1119.601 | J22: ='CheckoutGuard — Forecast · Chec'!J18*'CheckoutGuard — Business pl (2)'!B5 -> 1296.3745 | K22: ='CheckoutGuard — Forecast · Chec'!K18*'CheckoutGuard — Business pl (2)'!B5 -> 1478.3628 | L22: ='CheckoutGuard — Forecast · Chec'!L18*'CheckoutGuard — Business pl (2)'!B5 -> 1665.9355 | M22: ='CheckoutGuard — Forecast · Chec'!M18*'CheckoutGuard — Business pl (2)'!B5 -> 1859.4772 | N22: ='CheckoutGuard — Forecast · Chec'!N18*'CheckoutGuard — Business pl (2)'!B5 -> 2059.3886 | O22: ='CheckoutGuard — Forecast · Chec'!O18*'CheckoutGuard — Business pl (2)'!B5 -> 2266.0875 | P22: ='CheckoutGuard — Forecast · Chec'!P18*'CheckoutGuard — Business pl (2)'!B5 -> 2480.0094 | Q22: ='CheckoutGuard — Forecast · Chec'!Q18*'CheckoutGuard — Business pl (2)'!B5 -> 2701.6089 | R22: ='CheckoutGuard — Forecast · Chec'!R18*'CheckoutGuard — Business pl (2)'!B5 -> 2931.3604 | S22: ='CheckoutGuard — Forecast · Chec'!S18*'CheckoutGuard — Business pl (2)'!B5 -> 3169.7593 | T22: ='CheckoutGuard — Forecast · Chec'!T18*'CheckoutGuard — Business pl (2)'!B5 -> 3417.3233 | U22: ='CheckoutGuard — Forecast · Chec'!U18*'CheckoutGuard — Business pl (2)'!B5 -> 3674.5931 | V22: ='CheckoutGuard — Forecast · Chec'!V18*'CheckoutGuard — Business pl (2)'!B5 -> 3942.1344 | W22: ='CheckoutGuard — Forecast · Chec'!W18*'CheckoutGuard — Business pl (2)'!B5 -> 4220.5384 | X22: ='CheckoutGuard — Forecast · Chec'!X18*'CheckoutGuard — Business pl (2)'!B5 -> 4510.4236 | Y22: ='CheckoutGuard — Forecast · Chec'!Y18*'CheckoutGuard — Business pl (2)'!B5 -> 4812.4374 | Z22: ='CheckoutGuard — Forecast · Chec'!Z18*'CheckoutGuard — Business pl (2)'!B5 -> 5127.2571
A23: Developer | B23: ='CheckoutGuard — Forecast · Chec'!B19*'CheckoutGuard — Business pl (2)'!B6 -> 0 | C23: ='CheckoutGuard — Forecast · Chec'!C19*'CheckoutGuard — Business pl (2)'!B6 -> 58 | D23: ='CheckoutGuard — Forecast · Chec'!D19*'CheckoutGuard — Business pl (2)'!B6 -> 117.16 | E23: ='CheckoutGuard — Forecast · Chec'!E19*'CheckoutGuard — Business pl (2)'!B6 -> 177.5902 | F23: ='CheckoutGuard — Forecast · Chec'!F19*'CheckoutGuard — Business pl (2)'!B6 -> 239.40474 | G23: ='CheckoutGuard — Forecast · Chec'!G19*'CheckoutGuard — Business pl (2)'!B6 -> 302.72196 | H23: ='CheckoutGuard — Forecast · Chec'!H19*'CheckoutGuard — Business pl (2)'!B6 -> 367.66464 | I23: ='CheckoutGuard — Forecast · Chec'!I19*'CheckoutGuard — Business pl (2)'!B6 -> 434.36024 | J23: ='CheckoutGuard — Forecast · Chec'!J19*'CheckoutGuard — Business pl (2)'!B6 -> 502.94126 | K23: ='CheckoutGuard — Forecast · Chec'!K19*'CheckoutGuard — Business pl (2)'!B6 -> 573.54544 | L23: ='CheckoutGuard — Forecast · Chec'!L19*'CheckoutGuard — Business pl (2)'!B6 -> 646.31611 | M23: ='CheckoutGuard — Forecast · Chec'!M19*'CheckoutGuard — Business pl (2)'!B6 -> 721.40252 | N23: ='CheckoutGuard — Forecast · Chec'!N19*'CheckoutGuard — Business pl (2)'!B6 -> 798.96012 | O23: ='CheckoutGuard — Forecast · Chec'!O19*'CheckoutGuard — Business pl (2)'!B6 -> 879.15099 | P23: ='CheckoutGuard — Forecast · Chec'!P19*'CheckoutGuard — Business pl (2)'!B6 -> 962.14411 | Q23: ='CheckoutGuard — Forecast · Chec'!Q19*'CheckoutGuard — Business pl (2)'!B6 -> 1048.1158 | R23: ='CheckoutGuard — Forecast · Chec'!R19*'CheckoutGuard — Business pl (2)'!B6 -> 1137.2502 | S23: ='CheckoutGuard — Forecast · Chec'!S19*'CheckoutGuard — Business pl (2)'!B6 -> 1229.7394 | T23: ='CheckoutGuard — Forecast · Chec'!T19*'CheckoutGuard — Business pl (2)'!B6 -> 1325.7843 | U23: ='CheckoutGuard — Forecast · Chec'!U19*'CheckoutGuard — Business pl (2)'!B6 -> 1425.5947 | V23: ='CheckoutGuard — Forecast · Chec'!V19*'CheckoutGuard — Business pl (2)'!B6 -> 1529.3899 | W23: ='CheckoutGuard — Forecast · Chec'!W19*'CheckoutGuard — Business pl (2)'!B6 -> 1637.3995 | X23: ='CheckoutGuard — Forecast · Chec'!X19*'CheckoutGuard — Business pl (2)'!B6 -> 1749.8634 | Y23: ='CheckoutGuard — Forecast · Chec'!Y19*'CheckoutGuard — Business pl (2)'!B6 -> 1867.0326 | Z23: ='CheckoutGuard — Forecast · Chec'!Z19*'CheckoutGuard — Business pl (2)'!B6 -> 1989.17
A24: Team | B24: ='CheckoutGuard — Forecast · Chec'!B20*'CheckoutGuard — Business pl (2)'!B7 -> 0 | C24: ='CheckoutGuard — Forecast · Chec'!C20*'CheckoutGuard — Business pl (2)'!B7 -> 198 | D24: ='CheckoutGuard — Forecast · Chec'!D20*'CheckoutGuard — Business pl (2)'!B7 -> 399.96 | E24: ='CheckoutGuard — Forecast · Chec'!E20*'CheckoutGuard — Business pl (2)'!B7 -> 606.2562 | F24: ='CheckoutGuard — Forecast · Chec'!F20*'CheckoutGuard — Business pl (2)'!B7 -> 817.27826 | G24: ='CheckoutGuard — Forecast · Chec'!G20*'CheckoutGuard — Business pl (2)'!B7 -> 1033.4302 | H24: ='CheckoutGuard — Forecast · Chec'!H20*'CheckoutGuard — Business pl (2)'!B7 -> 1255.131 | I24: ='CheckoutGuard — Forecast · Chec'!I20*'CheckoutGuard — Business pl (2)'!B7 -> 1482.816 | J24: ='CheckoutGuard — Forecast · Chec'!J20*'CheckoutGuard — Business pl (2)'!B7 -> 1716.9374 | K24: ='CheckoutGuard — Forecast · Chec'!K20*'CheckoutGuard — Business pl (2)'!B7 -> 1957.9655 | L24: ='CheckoutGuard — Forecast · Chec'!L20*'CheckoutGuard — Business pl (2)'!B7 -> 2206.3895 | M24: ='CheckoutGuard — Forecast · Chec'!M20*'CheckoutGuard — Business pl (2)'!B7 -> 2462.7189 | N24: ='CheckoutGuard — Forecast · Chec'!N20*'CheckoutGuard — Business pl (2)'!B7 -> 2727.4846 | O24: ='CheckoutGuard — Forecast · Chec'!O20*'CheckoutGuard — Business pl (2)'!B7 -> 3001.2396 | P24: ='CheckoutGuard — Forecast · Chec'!P20*'CheckoutGuard — Business pl (2)'!B7 -> 3284.5609 | Q24: ='CheckoutGuard — Forecast · Chec'!Q20*'CheckoutGuard — Business pl (2)'!B7 -> 3578.0506 | R24: ='CheckoutGuard — Forecast · Chec'!R20*'CheckoutGuard — Business pl (2)'!B7 -> 3882.3368 | S24: ='CheckoutGuard — Forecast · Chec'!S20*'CheckoutGuard — Business pl (2)'!B7 -> 4198.0759 | T24: ='CheckoutGuard — Forecast · Chec'!T20*'CheckoutGuard — Business pl (2)'!B7 -> 4525.9532 | U24: ='CheckoutGuard — Forecast · Chec'!U20*'CheckoutGuard — Business pl (2)'!B7 -> 4866.6852 | V24: ='CheckoutGuard — Forecast · Chec'!V20*'CheckoutGuard — Business pl (2)'!B7 -> 5221.0208 | W24: ='CheckoutGuard — Forecast · Chec'!W20*'CheckoutGuard — Business pl (2)'!B7 -> 5589.7431 | X24: ='CheckoutGuard — Forecast · Chec'!X20*'CheckoutGuard — Business pl (2)'!B7 -> 5973.6714 | Y24: ='CheckoutGuard — Forecast · Chec'!Y20*'CheckoutGuard — Business pl (2)'!B7 -> 6373.6629 | Z24: ='CheckoutGuard — Forecast · Chec'!Z20*'CheckoutGuard — Business pl (2)'!B7 -> 6790.6147
A25: Completed runs | B25: =SUM('CheckoutGuard — Forecast · Chec'!B26,'CheckoutGuard — Forecast · Chec'!B27,'CheckoutGuard — Forecast · Chec'!B28) -> 0 | C25: =SUM('CheckoutGuard — Forecast · Chec'!C26,'CheckoutGuard — Forecast · Chec'!C27,'CheckoutGuard — Forecast · Chec'!C28) -> 1100 | D25: =SUM('CheckoutGuard — Forecast · Chec'!D26,'CheckoutGuard — Forecast · Chec'!D27,'CheckoutGuard — Forecast · Chec'!D28) -> 2222 | E25: =SUM('CheckoutGuard — Forecast · Chec'!E26,'CheckoutGuard — Forecast · Chec'!E27,'CheckoutGuard — Forecast · Chec'!E28) -> 3368.09 | F25: =SUM('CheckoutGuard — Forecast · Chec'!F26,'CheckoutGuard — Forecast · Chec'!F27,'CheckoutGuard — Forecast · Chec'!F28) -> 4540.4348 | G25: =SUM('CheckoutGuard — Forecast · Chec'!G26,'CheckoutGuard — Forecast · Chec'!G27,'CheckoutGuard — Forecast · Chec'!G28) -> 5741.2786 | H25: =SUM('CheckoutGuard — Forecast · Chec'!H26,'CheckoutGuard — Forecast · Chec'!H27,'CheckoutGuard — Forecast · Chec'!H28) -> 6972.95 | I25: =SUM('CheckoutGuard — Forecast · Chec'!I26,'CheckoutGuard — Forecast · Chec'!I27,'CheckoutGuard — Forecast · Chec'!I28) -> 8237.8667 | ... Z25: =SUM('CheckoutGuard — Forecast · Chec'!Z26,'CheckoutGuard — Forecast · Chec'!Z27,'CheckoutGuard — Forecast · Chec'!Z28) -> 37725.637
A26: Agency | B26: ='CheckoutGuard — Forecast · Chec'!B18*'CheckoutGuard — Business pl (2)'!C5*'CheckoutGuard — Assumptions · C'!B17 -> 0 | C26: ='CheckoutGuard — Forecast · Chec'!C18*'CheckoutGuard — Business pl (2)'!C5*'CheckoutGuard — Assumptions · C'!B17 -> 500 | D26: ='CheckoutGuard — Forecast · Chec'!D18*'CheckoutGuard — Business pl (2)'!C5*'CheckoutGuard — Assumptions · C'!B17 -> 1010 | E26: ='CheckoutGuard — Forecast · Chec'!E18*'CheckoutGuard — Business pl (2)'!C5*'CheckoutGuard — Assumptions · C'!B17 -> 1530.95 | F26: ='CheckoutGuard — Forecast · Chec'!F18*'CheckoutGuard — Business pl (2)'!C5*'CheckoutGuard — Assumptions · C'!B17 -> 2063.834 | G26: ='CheckoutGuard — Forecast · Chec'!G18*'CheckoutGuard — Business pl (2)'!C5*'CheckoutGuard — Assumptions · C'!B17 -> 2609.6721 | H26: ='CheckoutGuard — Forecast · Chec'!H18*'CheckoutGuard — Business pl (2)'!C5*'CheckoutGuard — Assumptions · C'!B17 -> 3169.5227 | I26: ='CheckoutGuard — Forecast · Chec'!I18*'CheckoutGuard — Business pl (2)'!C5*'CheckoutGuard — Assumptions · C'!B17 -> 3744.4849 | J26: ='CheckoutGuard — Forecast · Chec'!J18*'CheckoutGuard — Business pl (2)'!C5*'CheckoutGuard — Assumptions · C'!B17 -> 4335.7005 | K26: ='CheckoutGuard — Forecast · Chec'!K18*'CheckoutGuard — Business pl (2)'!C5*'CheckoutGuard — Assumptions · C'!B17 -> 4944.3572 | L26: ='CheckoutGuard — Forecast · Chec'!L18*'CheckoutGuard — Business pl (2)'!C5*'CheckoutGuard — Assumptions · C'!B17 -> 5571.6906 | M26: ='CheckoutGuard — Forecast · Chec'!M18*'CheckoutGuard — Business pl (2)'!C5*'CheckoutGuard — Assumptions · C'!B17 -> 6218.9872 | N26: ='CheckoutGuard — Forecast · Chec'!N18*'CheckoutGuard — Business pl (2)'!C5*'CheckoutGuard — Assumptions · C'!B17 -> 6887.5873 | O26: ='CheckoutGuard — Forecast · Chec'!O18*'CheckoutGuard — Business pl (2)'!C5*'CheckoutGuard — Assumptions · C'!B17 -> 7578.8878 | P26: ='CheckoutGuard — Forecast · Chec'!P18*'CheckoutGuard — Business pl (2)'!C5*'CheckoutGuard — Assumptions · C'!B17 -> 8294.3458 | Q26: ='CheckoutGuard — Forecast · Chec'!Q18*'CheckoutGuard — Business pl (2)'!C5*'CheckoutGuard — Assumptions · C'!B17 -> 9035.4812 | R26: ='CheckoutGuard — Forecast · Chec'!R18*'CheckoutGuard — Business pl (2)'!C5*'CheckoutGuard — Assumptions · C'!B17 -> 9803.8808 | S26: ='CheckoutGuard — Forecast · Chec'!S18*'CheckoutGuard — Business pl (2)'!C5*'CheckoutGuard — Assumptions · C'!B17 -> 10601.202 | T26: ='CheckoutGuard — Forecast · Chec'!T18*'CheckoutGuard — Business pl (2)'!C5*'CheckoutGuard — Assumptions · C'!B17 -> 11429.175 | U26: ='CheckoutGuard — Forecast · Chec'!U18*'CheckoutGuard — Business pl (2)'!C5*'CheckoutGuard — Assumptions · C'!B17 -> 12289.609 | V26: ='CheckoutGuard — Forecast · Chec'!V18*'CheckoutGuard — Business pl (2)'!C5*'CheckoutGuard — Assumptions · C'!B17 -> 13184.396 | W26: ='CheckoutGuard — Forecast · Chec'!W18*'CheckoutGuard — Business pl (2)'!C5*'CheckoutGuard — Assumptions · C'!B17 -> 14115.513 | X26: ='CheckoutGuard — Forecast · Chec'!X18*'CheckoutGuard — Business pl (2)'!C5*'CheckoutGuard — Assumptions · C'!B17 -> 15085.029 | Y26: ='CheckoutGuard — Forecast · Chec'!Y18*'CheckoutGuard — Business pl (2)'!C5*'CheckoutGuard — Assumptions · C'!B17 -> 16095.108 | Z26: ='CheckoutGuard — Forecast · Chec'!Z18*'CheckoutGuard — Business pl (2)'!C5*'CheckoutGuard — Assumptions · C'!B17 -> 17148.017
A27: Developer | B27: ='CheckoutGuard — Forecast · Chec'!B19*'CheckoutGuard — Business pl (2)'!C6*'CheckoutGuard — Assumptions · C'!B17 -> 0 | C27: ='CheckoutGuard — Forecast · Chec'!C19*'CheckoutGuard — Business pl (2)'!C6*'CheckoutGuard — Assumptions · C'!B17 -> 100 | D27: ='CheckoutGuard — Forecast · Chec'!D19*'CheckoutGuard — Business pl (2)'!C6*'CheckoutGuard — Assumptions · C'!B17 -> 202 | E27: ='CheckoutGuard — Forecast · Chec'!E19*'CheckoutGuard — Business pl (2)'!C6*'CheckoutGuard — Assumptions · C'!B17 -> 306.19 | F27: ='CheckoutGuard — Forecast · Chec'!F19*'CheckoutGuard — Business pl (2)'!C6*'CheckoutGuard — Assumptions · C'!B17 -> 412.7668 | G27: ='CheckoutGuard — Forecast · Chec'!G19*'CheckoutGuard — Business pl (2)'!C6*'CheckoutGuard — Assumptions · C'!B17 -> 521.93442 | H27: ='CheckoutGuard — Forecast · Chec'!H19*'CheckoutGuard — Business pl (2)'!C6*'CheckoutGuard — Assumptions · C'!B17 -> 633.90454 | I27: ='CheckoutGuard — Forecast · Chec'!I19*'CheckoutGuard — Business pl (2)'!C6*'CheckoutGuard — Assumptions · C'!B17 -> 748.89697 | J27: ='CheckoutGuard — Forecast · Chec'!J19*'CheckoutGuard — Business pl (2)'!C6*'CheckoutGuard — Assumptions · C'!B17 -> 867.14011 | K27: ='CheckoutGuard — Forecast · Chec'!K19*'CheckoutGuard — Business pl (2)'!C6*'CheckoutGuard — Assumptions · C'!B17 -> 988.87145 | L27: ='CheckoutGuard — Forecast · Chec'!L19*'CheckoutGuard — Business pl (2)'!C6*'CheckoutGuard — Assumptions · C'!B17 -> 1114.3381 | M27: ='CheckoutGuard — Forecast · Chec'!M19*'CheckoutGuard — Business pl (2)'!C6*'CheckoutGuard — Assumptions · C'!B17 -> 1243.7974 | N27: ='CheckoutGuard — Forecast · Chec'!N19*'CheckoutGuard — Business pl (2)'!C6*'CheckoutGuard — Assumptions · C'!B17 -> 1377.5175 | O27: ='CheckoutGuard — Forecast · Chec'!O19*'CheckoutGuard — Business pl (2)'!C6*'CheckoutGuard — Assumptions · C'!B17 -> 1515.7776 | P27: ='CheckoutGuard — Forecast · Chec'!P19*'CheckoutGuard — Business pl (2)'!C6*'CheckoutGuard — Assumptions · C'!B17 -> 1658.8692 | Q27: ='CheckoutGuard — Forecast · Chec'!Q19*'CheckoutGuard — Business pl (2)'!C6*'CheckoutGuard — Assumptions · C'!B17 -> 1807.0962 | R27: ='CheckoutGuard — Forecast · Chec'!R19*'CheckoutGuard — Business pl (2)'!C6*'CheckoutGuard — Assumptions · C'!B17 -> 1960.7762 | S27: ='CheckoutGuard — Forecast · Chec'!S19*'CheckoutGuard — Business pl (2)'!C6*'CheckoutGuard — Assumptions · C'!B17 -> 2120.2403 | T27: ='CheckoutGuard — Forecast · Chec'!T19*'CheckoutGuard — Business pl (2)'!C6*'CheckoutGuard — Assumptions · C'!B17 -> 2285.835 | U27: ='CheckoutGuard — Forecast · Chec'!U19*'CheckoutGuard — Business pl (2)'!C6*'CheckoutGuard — Assumptions · C'!B17 -> 2457.9218 | V27: ='CheckoutGuard — Forecast · Chec'!V19*'CheckoutGuard — Business pl (2)'!C6*'CheckoutGuard — Assumptions · C'!B17 -> 2636.8792 | W27: ='CheckoutGuard — Forecast · Chec'!W19*'CheckoutGuard — Business pl (2)'!C6*'CheckoutGuard — Assumptions · C'!B17 -> 2823.1026 | X27: ='CheckoutGuard — Forecast · Chec'!X19*'CheckoutGuard — Business pl (2)'!C6*'CheckoutGuard — Assumptions · C'!B17 -> 3017.0058 | Y27: ='CheckoutGuard — Forecast · Chec'!Y19*'CheckoutGuard — Business pl (2)'!C6*'CheckoutGuard — Assumptions · C'!B17 -> 3219.0217 | Z27: ='CheckoutGuard — Forecast · Chec'!Z19*'CheckoutGuard — Business pl (2)'!C6*'CheckoutGuard — Assumptions · C'!B17 -> 3429.6034
A28: Team | B28: ='CheckoutGuard — Forecast · Chec'!B20*'CheckoutGuard — Business pl (2)'!C7*'CheckoutGuard — Assumptions · C'!B17 -> 0 | C28: ='CheckoutGuard — Forecast · Chec'!C20*'CheckoutGuard — Business pl (2)'!C7*'CheckoutGuard — Assumptions · C'!B17 -> 500 | D28: ='CheckoutGuard — Forecast · Chec'!D20*'CheckoutGuard — Business pl (2)'!C7*'CheckoutGuard — Assumptions · C'!B17 -> 1010 | E28: ='CheckoutGuard — Forecast · Chec'!E20*'CheckoutGuard — Business pl (2)'!C7*'CheckoutGuard — Assumptions · C'!B17 -> 1530.95 | F28: ='CheckoutGuard — Forecast · Chec'!F20*'CheckoutGuard — Business pl (2)'!C7*'CheckoutGuard — Assumptions · C'!B17 -> 2063.834 | G28: ='CheckoutGuard — Forecast · Chec'!G20*'CheckoutGuard — Business pl (2)'!C7*'CheckoutGuard — Assumptions · C'!B17 -> 2609.6721 | H28: ='CheckoutGuard — Forecast · Chec'!H20*'CheckoutGuard — Business pl (2)'!C7*'CheckoutGuard — Assumptions · C'!B17 -> 3169.5227 | I28: ='CheckoutGuard — Forecast · Chec'!I20*'CheckoutGuard — Business pl (2)'!C7*'CheckoutGuard — Assumptions · C'!B17 -> 3744.4849 | J28: ='CheckoutGuard — Forecast · Chec'!J20*'CheckoutGuard — Business pl (2)'!C7*'CheckoutGuard — Assumptions · C'!B17 -> 4335.7005 | K28: ='CheckoutGuard — Forecast · Chec'!K20*'CheckoutGuard — Business pl (2)'!C7*'CheckoutGuard — Assumptions · C'!B17 -> 4944.3572 | L28: ='CheckoutGuard — Forecast · Chec'!L20*'CheckoutGuard — Business pl (2)'!C7*'CheckoutGuard — Assumptions · C'!B17 -> 5571.6906 | M28: ='CheckoutGuard — Forecast · Chec'!M20*'CheckoutGuard — Business pl (2)'!C7*'CheckoutGuard — Assumptions · C'!B17 -> 6218.9872 | N28: ='CheckoutGuard — Forecast · Chec'!N20*'CheckoutGuard — Business pl (2)'!C7*'CheckoutGuard — Assumptions · C'!B17 -> 6887.5873 | O28: ='CheckoutGuard — Forecast · Chec'!O20*'CheckoutGuard — Business pl (2)'!C7*'CheckoutGuard — Assumptions · C'!B17 -> 7578.8878 | P28: ='CheckoutGuard — Forecast · Chec'!P20*'CheckoutGuard — Business pl (2)'!C7*'CheckoutGuard — Assumptions · C'!B17 -> 8294.3458 | Q28: ='CheckoutGuard — Forecast · Chec'!Q20*'CheckoutGuard — Business pl (2)'!C7*'CheckoutGuard — Assumptions · C'!B17 -> 9035.4812 | R28: ='CheckoutGuard — Forecast · Chec'!R20*'CheckoutGuard — Business pl (2)'!C7*'CheckoutGuard — Assumptions · C'!B17 -> 9803.8808 | S28: ='CheckoutGuard — Forecast · Chec'!S20*'CheckoutGuard — Business pl (2)'!C7*'CheckoutGuard — Assumptions · C'!B17 -> 10601.202 | T28: ='CheckoutGuard — Forecast · Chec'!T20*'CheckoutGuard — Business pl (2)'!C7*'CheckoutGuard — Assumptions · C'!B17 -> 11429.175 | U28: ='CheckoutGuard — Forecast · Chec'!U20*'CheckoutGuard — Business pl (2)'!C7*'CheckoutGuard — Assumptions · C'!B17 -> 12289.609 | V28: ='CheckoutGuard — Forecast · Chec'!V20*'CheckoutGuard — Business pl (2)'!C7*'CheckoutGuard — Assumptions · C'!B17 -> 13184.396 | W28: ='CheckoutGuard — Forecast · Chec'!W20*'CheckoutGuard — Business pl (2)'!C7*'CheckoutGuard — Assumptions · C'!B17 -> 14115.513 | X28: ='CheckoutGuard — Forecast · Chec'!X20*'CheckoutGuard — Business pl (2)'!C7*'CheckoutGuard — Assumptions · C'!B17 -> 15085.029 | Y28: ='CheckoutGuard — Forecast · Chec'!Y20*'CheckoutGuard — Business pl (2)'!C7*'CheckoutGuard — Assumptions · C'!B17 -> 16095.108 | Z28: ='CheckoutGuard — Forecast · Chec'!Z20*'CheckoutGuard — Business pl (2)'!C7*'CheckoutGuard — Assumptions · C'!B17 -> 17148.017
A29: Run delivery costs | B29: =SUM('CheckoutGuard — Forecast · Chec'!B30,'CheckoutGuard — Forecast · Chec'!B31,'CheckoutGuard — Forecast · Chec'!B32) -> 0 | C29: =SUM('CheckoutGuard — Forecast · Chec'!C30,'CheckoutGuard — Forecast · Chec'!C31,'CheckoutGuard — Forecast · Chec'!C32) -> 20.99416 | D29: =SUM('CheckoutGuard — Forecast · Chec'!D30,'CheckoutGuard — Forecast · Chec'!D31,'CheckoutGuard — Forecast · Chec'!D32) -> 42.408203 | E29: =SUM('CheckoutGuard — Forecast · Chec'!E30,'CheckoutGuard — Forecast · Chec'!E31,'CheckoutGuard — Forecast · Chec'!E32) -> 64.282019 | F29: =SUM('CheckoutGuard — Forecast · Chec'!F30,'CheckoutGuard — Forecast · Chec'!F31,'CheckoutGuard — Forecast · Chec'!F32) -> 86.656922 | G29: =SUM('CheckoutGuard — Forecast · Chec'!G30,'CheckoutGuard — Forecast · Chec'!G31,'CheckoutGuard — Forecast · Chec'!G32) -> 109.57575 | H29: =SUM('CheckoutGuard — Forecast · Chec'!H30,'CheckoutGuard — Forecast · Chec'!H31,'CheckoutGuard — Forecast · Chec'!H32) -> 133.08293 | I29: =SUM('CheckoutGuard — Forecast · Chec'!I30,'CheckoutGuard — Forecast · Chec'!I31,'CheckoutGuard — Forecast · Chec'!I32) -> 157.22463 | ... Z29: =SUM('CheckoutGuard — Forecast · Chec'!Z30,'CheckoutGuard — Forecast · Chec'!Z31,'CheckoutGuard — Forecast · Chec'!Z32) -> 720.01643
A30: Agency | B30: ='CheckoutGuard — Forecast · Chec'!B26*'CheckoutGuard — Assumptions (2)'!B12 -> 0 | C30: ='CheckoutGuard — Forecast · Chec'!C26*'CheckoutGuard — Assumptions (2)'!B12 -> 9.5428 | D30: ='CheckoutGuard — Forecast · Chec'!D26*'CheckoutGuard — Assumptions (2)'!B12 -> 19.276456 | E30: ='CheckoutGuard — Forecast · Chec'!E26*'CheckoutGuard — Assumptions (2)'!B12 -> 29.219099 | F30: ='CheckoutGuard — Forecast · Chec'!F26*'CheckoutGuard — Assumptions (2)'!B12 -> 39.38951 | G30: ='CheckoutGuard — Forecast · Chec'!G26*'CheckoutGuard — Assumptions (2)'!B12 -> 49.807158 | H30: ='CheckoutGuard — Forecast · Chec'!H26*'CheckoutGuard — Assumptions (2)'!B12 -> 60.492243 | I30: ='CheckoutGuard — Forecast · Chec'!I26*'CheckoutGuard — Assumptions (2)'!B12 -> 71.46574 | J30: ='CheckoutGuard — Forecast · Chec'!J26*'CheckoutGuard — Assumptions (2)'!B12 -> 82.749446 | K30: ='CheckoutGuard — Forecast · Chec'!K26*'CheckoutGuard — Assumptions (2)'!B12 -> 94.366024 | L30: ='CheckoutGuard — Forecast · Chec'!L26*'CheckoutGuard — Assumptions (2)'!B12 -> 106.33906 | M30: ='CheckoutGuard — Forecast · Chec'!M26*'CheckoutGuard — Assumptions (2)'!B12 -> 118.6931 | N30: ='CheckoutGuard — Forecast · Chec'!N26*'CheckoutGuard — Assumptions (2)'!B12 -> 131.45374 | O30: ='CheckoutGuard — Forecast · Chec'!O26*'CheckoutGuard — Assumptions (2)'!B12 -> 144.64762 | P30: ='CheckoutGuard — Forecast · Chec'!P26*'CheckoutGuard — Assumptions (2)'!B12 -> 158.30257 | Q30: ='CheckoutGuard — Forecast · Chec'!Q26*'CheckoutGuard — Assumptions (2)'!B12 -> 172.44758 | R30: ='CheckoutGuard — Forecast · Chec'!R26*'CheckoutGuard — Assumptions (2)'!B12 -> 187.11295 | S30: ='CheckoutGuard — Forecast · Chec'!S26*'CheckoutGuard — Assumptions (2)'!B12 -> 202.3303 | T30: ='CheckoutGuard — Forecast · Chec'!T26*'CheckoutGuard — Assumptions (2)'!B12 -> 218.13266 | U30: ='CheckoutGuard — Forecast · Chec'!U26*'CheckoutGuard — Assumptions (2)'!B12 -> 234.55457 | V30: ='CheckoutGuard — Forecast · Chec'!V26*'CheckoutGuard — Assumptions (2)'!B12 -> 251.63211 | W30: ='CheckoutGuard — Forecast · Chec'!W26*'CheckoutGuard — Assumptions (2)'!B12 -> 269.40303 | X30: ='CheckoutGuard — Forecast · Chec'!X26*'CheckoutGuard — Assumptions (2)'!B12 -> 287.90683 | Y30: ='CheckoutGuard — Forecast · Chec'!Y26*'CheckoutGuard — Assumptions (2)'!B12 -> 307.1848 | Z30: ='CheckoutGuard — Forecast · Chec'!Z26*'CheckoutGuard — Assumptions (2)'!B12 -> 327.28019
A31: Developer | B31: ='CheckoutGuard — Forecast · Chec'!B27*'CheckoutGuard — Assumptions (2)'!B12 -> 0 | C31: ='CheckoutGuard — Forecast · Chec'!C27*'CheckoutGuard — Assumptions (2)'!B12 -> 1.90856 | D31: ='CheckoutGuard — Forecast · Chec'!D27*'CheckoutGuard — Assumptions (2)'!B12 -> 3.8552912 | E31: ='CheckoutGuard — Forecast · Chec'!E27*'CheckoutGuard — Assumptions (2)'!B12 -> 5.8438199 | F31: ='CheckoutGuard — Forecast · Chec'!F27*'CheckoutGuard — Assumptions (2)'!B12 -> 7.877902 | G31: ='CheckoutGuard — Forecast · Chec'!G27*'CheckoutGuard — Assumptions (2)'!B12 -> 9.9614316 | H31: ='CheckoutGuard — Forecast · Chec'!H27*'CheckoutGuard — Assumptions (2)'!B12 -> 12.098449 | I31: ='CheckoutGuard — Forecast · Chec'!I27*'CheckoutGuard — Assumptions (2)'!B12 -> 14.293148 | J31: ='CheckoutGuard — Forecast · Chec'!J27*'CheckoutGuard — Assumptions (2)'!B12 -> 16.549889 | K31: ='CheckoutGuard — Forecast · Chec'!K27*'CheckoutGuard — Assumptions (2)'!B12 -> 18.873205 | L31: ='CheckoutGuard — Forecast · Chec'!L27*'CheckoutGuard — Assumptions (2)'!B12 -> 21.267812 | M31: ='CheckoutGuard — Forecast · Chec'!M27*'CheckoutGuard — Assumptions (2)'!B12 -> 23.73862 | N31: ='CheckoutGuard — Forecast · Chec'!N27*'CheckoutGuard — Assumptions (2)'!B12 -> 26.290747 | O31: ='CheckoutGuard — Forecast · Chec'!O27*'CheckoutGuard — Assumptions (2)'!B12 -> 28.929524 | P31: ='CheckoutGuard — Forecast · Chec'!P27*'CheckoutGuard — Assumptions (2)'!B12 -> 31.660513 | Q31: ='CheckoutGuard — Forecast · Chec'!Q27*'CheckoutGuard — Assumptions (2)'!B12 -> 34.489516 | R31: ='CheckoutGuard — Forecast · Chec'!R27*'CheckoutGuard — Assumptions (2)'!B12 -> 37.42259 | S31: ='CheckoutGuard — Forecast · Chec'!S27*'CheckoutGuard — Assumptions (2)'!B12 -> 40.466059 | T31: ='CheckoutGuard — Forecast · Chec'!T27*'CheckoutGuard — Assumptions (2)'!B12 -> 43.626532 | U31: ='CheckoutGuard — Forecast · Chec'!U27*'CheckoutGuard — Assumptions (2)'!B12 -> 46.910913 | V31: ='CheckoutGuard — Forecast · Chec'!V27*'CheckoutGuard — Assumptions (2)'!B12 -> 50.326422 | W31: ='CheckoutGuard — Forecast · Chec'!W27*'CheckoutGuard — Assumptions (2)'!B12 -> 53.880607 | X31: ='CheckoutGuard — Forecast · Chec'!X27*'CheckoutGuard — Assumptions (2)'!B12 -> 57.581365 | Y31: ='CheckoutGuard — Forecast · Chec'!Y27*'CheckoutGuard — Assumptions (2)'!B12 -> 61.43696 | Z31: ='CheckoutGuard — Forecast · Chec'!Z27*'CheckoutGuard — Assumptions (2)'!B12 -> 65.456039
A32: Team | B32: ='CheckoutGuard — Forecast · Chec'!B28*'CheckoutGuard — Assumptions (2)'!B12 -> 0 | C32: ='CheckoutGuard — Forecast · Chec'!C28*'CheckoutGuard — Assumptions (2)'!B12 -> 9.5428 | D32: ='CheckoutGuard — Forecast · Chec'!D28*'CheckoutGuard — Assumptions (2)'!B12 -> 19.276456 | E32: ='CheckoutGuard — Forecast · Chec'!E28*'CheckoutGuard — Assumptions (2)'!B12 -> 29.219099 | F32: ='CheckoutGuard — Forecast · Chec'!F28*'CheckoutGuard — Assumptions (2)'!B12 -> 39.38951 | G32: ='CheckoutGuard — Forecast · Chec'!G28*'CheckoutGuard — Assumptions (2)'!B12 -> 49.807158 | H32: ='CheckoutGuard — Forecast · Chec'!H28*'CheckoutGuard — Assumptions (2)'!B12 -> 60.492243 | I32: ='CheckoutGuard — Forecast · Chec'!I28*'CheckoutGuard — Assumptions (2)'!B12 -> 71.46574 | J32: ='CheckoutGuard — Forecast · Chec'!J28*'CheckoutGuard — Assumptions (2)'!B12 -> 82.749446 | K32: ='CheckoutGuard — Forecast · Chec'!K28*'CheckoutGuard — Assumptions (2)'!B12 -> 94.366024 | L32: ='CheckoutGuard — Forecast · Chec'!L28*'CheckoutGuard — Assumptions (2)'!B12 -> 106.33906 | M32: ='CheckoutGuard — Forecast · Chec'!M28*'CheckoutGuard — Assumptions (2)'!B12 -> 118.6931 | N32: ='CheckoutGuard — Forecast · Chec'!N28*'CheckoutGuard — Assumptions (2)'!B12 -> 131.45374 | O32: ='CheckoutGuard — Forecast · Chec'!O28*'CheckoutGuard — Assumptions (2)'!B12 -> 144.64762 | P32: ='CheckoutGuard — Forecast · Chec'!P28*'CheckoutGuard — Assumptions (2)'!B12 -> 158.30257 | Q32: ='CheckoutGuard — Forecast · Chec'!Q28*'CheckoutGuard — Assumptions (2)'!B12 -> 172.44758 | R32: ='CheckoutGuard — Forecast · Chec'!R28*'CheckoutGuard — Assumptions (2)'!B12 -> 187.11295 | S32: ='CheckoutGuard — Forecast · Chec'!S28*'CheckoutGuard — Assumptions (2)'!B12 -> 202.3303 | T32: ='CheckoutGuard — Forecast · Chec'!T28*'CheckoutGuard — Assumptions (2)'!B12 -> 218.13266 | U32: ='CheckoutGuard — Forecast · Chec'!U28*'CheckoutGuard — Assumptions (2)'!B12 -> 234.55457 | V32: ='CheckoutGuard — Forecast · Chec'!V28*'CheckoutGuard — Assumptions (2)'!B12 -> 251.63211 | W32: ='CheckoutGuard — Forecast · Chec'!W28*'CheckoutGuard — Assumptions (2)'!B12 -> 269.40303 | X32: ='CheckoutGuard — Forecast · Chec'!X28*'CheckoutGuard — Assumptions (2)'!B12 -> 287.90683 | Y32: ='CheckoutGuard — Forecast · Chec'!Y28*'CheckoutGuard — Assumptions (2)'!B12 -> 307.1848 | Z32: ='CheckoutGuard — Forecast · Chec'!Z28*'CheckoutGuard — Assumptions (2)'!B12 -> 327.28019
A33: Workspace support costs | B33: =SUM('CheckoutGuard — Forecast · Chec'!B34,'CheckoutGuard — Forecast · Chec'!B35,'CheckoutGuard — Forecast · Chec'!B36) -> 0 | C33: =SUM('CheckoutGuard — Forecast · Chec'!C34,'CheckoutGuard — Forecast · Chec'!C35,'CheckoutGuard — Forecast · Chec'!C36) -> 50 | D33: =SUM('CheckoutGuard — Forecast · Chec'!D34,'CheckoutGuard — Forecast · Chec'!D35,'CheckoutGuard — Forecast · Chec'!D36) -> 101 | E33: =SUM('CheckoutGuard — Forecast · Chec'!E34,'CheckoutGuard — Forecast · Chec'!E35,'CheckoutGuard — Forecast · Chec'!E36) -> 153.095 | F33: =SUM('CheckoutGuard — Forecast · Chec'!F34,'CheckoutGuard — Forecast · Chec'!F35,'CheckoutGuard — Forecast · Chec'!F36) -> 206.3834 | G33: =SUM('CheckoutGuard — Forecast · Chec'!G34,'CheckoutGuard — Forecast · Chec'!G35,'CheckoutGuard — Forecast · Chec'!G36) -> 260.96721 | H33: =SUM('CheckoutGuard — Forecast · Chec'!H34,'CheckoutGuard — Forecast · Chec'!H35,'CheckoutGuard — Forecast · Chec'!H36) -> 316.95227 | I33: =SUM('CheckoutGuard — Forecast · Chec'!I34,'CheckoutGuard — Forecast · Chec'!I35,'CheckoutGuard — Forecast · Chec'!I36) -> 374.44849 | ... Z33: =SUM('CheckoutGuard — Forecast · Chec'!Z34,'CheckoutGuard — Forecast · Chec'!Z35,'CheckoutGuard — Forecast · Chec'!Z36) -> 1714.8017
A34: Agency | B34: ='CheckoutGuard — Forecast · Chec'!B18*'CheckoutGuard — Assumptions · W'!E5/60*'CheckoutGuard — Assumptions · C'!B16 -> 0 | C34: ='CheckoutGuard — Forecast · Chec'!C18*'CheckoutGuard — Assumptions · W'!E5/60*'CheckoutGuard — Assumptions · C'!B16 -> 15 | D34: ='CheckoutGuard — Forecast · Chec'!D18*'CheckoutGuard — Assumptions · W'!E5/60*'CheckoutGuard — Assumptions · C'!B16 -> 30.3 | E34: ='CheckoutGuard — Forecast · Chec'!E18*'CheckoutGuard — Assumptions · W'!E5/60*'CheckoutGuard — Assumptions · C'!B16 -> 45.9285 | F34: ='CheckoutGuard — Forecast · Chec'!F18*'CheckoutGuard — Assumptions · W'!E5/60*'CheckoutGuard — Assumptions · C'!B16 -> 61.91502 | G34: ='CheckoutGuard — Forecast · Chec'!G18*'CheckoutGuard — Assumptions · W'!E5/60*'CheckoutGuard — Assumptions · C'!B16 -> 78.290163 | H34: ='CheckoutGuard — Forecast · Chec'!H18*'CheckoutGuard — Assumptions · W'!E5/60*'CheckoutGuard — Assumptions · C'!B16 -> 95.085682 | I34: ='CheckoutGuard — Forecast · Chec'!I18*'CheckoutGuard — Assumptions · W'!E5/60*'CheckoutGuard — Assumptions · C'!B16 -> 112.33455 | J34: ='CheckoutGuard — Forecast · Chec'!J18*'CheckoutGuard — Assumptions · W'!E5/60*'CheckoutGuard — Assumptions · C'!B16 -> 130.07102 | K34: ='CheckoutGuard — Forecast · Chec'!K18*'CheckoutGuard — Assumptions · W'!E5/60*'CheckoutGuard — Assumptions · C'!B16 -> 148.33072 | L34: ='CheckoutGuard — Forecast · Chec'!L18*'CheckoutGuard — Assumptions · W'!E5/60*'CheckoutGuard — Assumptions · C'!B16 -> 167.15072 | M34: ='CheckoutGuard — Forecast · Chec'!M18*'CheckoutGuard — Assumptions · W'!E5/60*'CheckoutGuard — Assumptions · C'!B16 -> 186.56962 | N34: ='CheckoutGuard — Forecast · Chec'!N18*'CheckoutGuard — Assumptions · W'!E5/60*'CheckoutGuard — Assumptions · C'!B16 -> 206.62762 | O34: ='CheckoutGuard — Forecast · Chec'!O18*'CheckoutGuard — Assumptions · W'!E5/60*'CheckoutGuard — Assumptions · C'!B16 -> 227.36663 | P34: ='CheckoutGuard — Forecast · Chec'!P18*'CheckoutGuard — Assumptions · W'!E5/60*'CheckoutGuard — Assumptions · C'!B16 -> 248.83037 | Q34: ='CheckoutGuard — Forecast · Chec'!Q18*'CheckoutGuard — Assumptions · W'!E5/60*'CheckoutGuard — Assumptions · C'!B16 -> 271.06444 | R34: ='CheckoutGuard — Forecast · Chec'!R18*'CheckoutGuard — Assumptions · W'!E5/60*'CheckoutGuard — Assumptions · C'!B16 -> 294.11643 | S34: ='CheckoutGuard — Forecast · Chec'!S18*'CheckoutGuard — Assumptions · W'!E5/60*'CheckoutGuard — Assumptions · C'!B16 -> 318.03605 | T34: ='CheckoutGuard — Forecast · Chec'!T18*'CheckoutGuard — Assumptions · W'!E5/60*'CheckoutGuard — Assumptions · C'!B16 -> 342.87524 | U34: ='CheckoutGuard — Forecast · Chec'!U18*'CheckoutGuard — Assumptions · W'!E5/60*'CheckoutGuard — Assumptions · C'!B16 -> 368.68828 | V34: ='CheckoutGuard — Forecast · Chec'!V18*'CheckoutGuard — Assumptions · W'!E5/60*'CheckoutGuard — Assumptions · C'!B16 -> 395.53188 | W34: ='CheckoutGuard — Forecast · Chec'!W18*'CheckoutGuard — Assumptions · W'!E5/60*'CheckoutGuard — Assumptions · C'!B16 -> 423.46539 | X34: ='CheckoutGuard — Forecast · Chec'!X18*'CheckoutGuard — Assumptions · W'!E5/60*'CheckoutGuard — Assumptions · C'!B16 -> 452.55087 | Y34: ='CheckoutGuard — Forecast · Chec'!Y18*'CheckoutGuard — Assumptions · W'!E5/60*'CheckoutGuard — Assumptions · C'!B16 -> 482.85325 | Z34: ='CheckoutGuard — Forecast · Chec'!Z18*'CheckoutGuard — Assumptions · W'!E5/60*'CheckoutGuard — Assumptions · C'!B16 -> 514.44051
A35: Developer | B35: ='CheckoutGuard — Forecast · Chec'!B19*'CheckoutGuard — Assumptions · W'!E6/60*'CheckoutGuard — Assumptions · C'!B16 -> 0 | C35: ='CheckoutGuard — Forecast · Chec'!C19*'CheckoutGuard — Assumptions · W'!E6/60*'CheckoutGuard — Assumptions · C'!B16 -> 10 | D35: ='CheckoutGuard — Forecast · Chec'!D19*'CheckoutGuard — Assumptions · W'!E6/60*'CheckoutGuard — Assumptions · C'!B16 -> 20.2 | E35: ='CheckoutGuard — Forecast · Chec'!E19*'CheckoutGuard — Assumptions · W'!E6/60*'CheckoutGuard — Assumptions · C'!B16 -> 30.619 | F35: ='CheckoutGuard — Forecast · Chec'!F19*'CheckoutGuard — Assumptions · W'!E6/60*'CheckoutGuard — Assumptions · C'!B16 -> 41.27668 | G35: ='CheckoutGuard — Forecast · Chec'!G19*'CheckoutGuard — Assumptions · W'!E6/60*'CheckoutGuard — Assumptions · C'!B16 -> 52.193442 | H35: ='CheckoutGuard — Forecast · Chec'!H19*'CheckoutGuard — Assumptions · W'!E6/60*'CheckoutGuard — Assumptions · C'!B16 -> 63.390454 | I35: ='CheckoutGuard — Forecast · Chec'!I19*'CheckoutGuard — Assumptions · W'!E6/60*'CheckoutGuard — Assumptions · C'!B16 -> 74.889697 | J35: ='CheckoutGuard — Forecast · Chec'!J19*'CheckoutGuard — Assumptions · W'!E6/60*'CheckoutGuard — Assumptions · C'!B16 -> 86.714011 | K35: ='CheckoutGuard — Forecast · Chec'!K19*'CheckoutGuard — Assumptions · W'!E6/60*'CheckoutGuard — Assumptions · C'!B16 -> 98.887145 | L35: ='CheckoutGuard — Forecast · Chec'!L19*'CheckoutGuard — Assumptions · W'!E6/60*'CheckoutGuard — Assumptions · C'!B16 -> 111.43381 | M35: ='CheckoutGuard — Forecast · Chec'!M19*'CheckoutGuard — Assumptions · W'!E6/60*'CheckoutGuard — Assumptions · C'!B16 -> 124.37974 | N35: ='CheckoutGuard — Forecast · Chec'!N19*'CheckoutGuard — Assumptions · W'!E6/60*'CheckoutGuard — Assumptions · C'!B16 -> 137.75175 | O35: ='CheckoutGuard — Forecast · Chec'!O19*'CheckoutGuard — Assumptions · W'!E6/60*'CheckoutGuard — Assumptions · C'!B16 -> 151.57776 | P35: ='CheckoutGuard — Forecast · Chec'!P19*'CheckoutGuard — Assumptions · W'!E6/60*'CheckoutGuard — Assumptions · C'!B16 -> 165.88692 | Q35: ='CheckoutGuard — Forecast · Chec'!Q19*'CheckoutGuard — Assumptions · W'!E6/60*'CheckoutGuard — Assumptions · C'!B16 -> 180.70962 | R35: ='CheckoutGuard — Forecast · Chec'!R19*'CheckoutGuard — Assumptions · W'!E6/60*'CheckoutGuard — Assumptions · C'!B16 -> 196.07762 | S35: ='CheckoutGuard — Forecast · Chec'!S19*'CheckoutGuard — Assumptions · W'!E6/60*'CheckoutGuard — Assumptions · C'!B16 -> 212.02403 | T35: ='CheckoutGuard — Forecast · Chec'!T19*'CheckoutGuard — Assumptions · W'!E6/60*'CheckoutGuard — Assumptions · C'!B16 -> 228.5835 | U35: ='CheckoutGuard — Forecast · Chec'!U19*'CheckoutGuard — Assumptions · W'!E6/60*'CheckoutGuard — Assumptions · C'!B16 -> 245.79218 | V35: ='CheckoutGuard — Forecast · Chec'!V19*'CheckoutGuard — Assumptions · W'!E6/60*'CheckoutGuard — Assumptions · C'!B16 -> 263.68792 | W35: ='CheckoutGuard — Forecast · Chec'!W19*'CheckoutGuard — Assumptions · W'!E6/60*'CheckoutGuard — Assumptions · C'!B16 -> 282.31026 | X35: ='CheckoutGuard — Forecast · Chec'!X19*'CheckoutGuard — Assumptions · W'!E6/60*'CheckoutGuard — Assumptions · C'!B16 -> 301.70058 | Y35: ='CheckoutGuard — Forecast · Chec'!Y19*'CheckoutGuard — Assumptions · W'!E6/60*'CheckoutGuard — Assumptions · C'!B16 -> 321.90217 | Z35: ='CheckoutGuard — Forecast · Chec'!Z19*'CheckoutGuard — Assumptions · W'!E6/60*'CheckoutGuard — Assumptions · C'!B16 -> 342.96034
A36: Team | B36: ='CheckoutGuard — Forecast · Chec'!B20*'CheckoutGuard — Assumptions · W'!E7/60*'CheckoutGuard — Assumptions · C'!B16 -> 0 | C36: ='CheckoutGuard — Forecast · Chec'!C20*'CheckoutGuard — Assumptions · W'!E7/60*'CheckoutGuard — Assumptions · C'!B16 -> 25 | D36: ='CheckoutGuard — Forecast · Chec'!D20*'CheckoutGuard — Assumptions · W'!E7/60*'CheckoutGuard — Assumptions · C'!B16 -> 50.5 | E36: ='CheckoutGuard — Forecast · Chec'!E20*'CheckoutGuard — Assumptions · W'!E7/60*'CheckoutGuard — Assumptions · C'!B16 -> 76.5475 | F36: ='CheckoutGuard — Forecast · Chec'!F20*'CheckoutGuard — Assumptions · W'!E7/60*'CheckoutGuard — Assumptions · C'!B16 -> 103.1917 | G36: ='CheckoutGuard — Forecast · Chec'!G20*'CheckoutGuard — Assumptions · W'!E7/60*'CheckoutGuard — Assumptions · C'!B16 -> 130.48361 | H36: ='CheckoutGuard — Forecast · Chec'!H20*'CheckoutGuard — Assumptions · W'!E7/60*'CheckoutGuard — Assumptions · C'!B16 -> 158.47614 | I36: ='CheckoutGuard — Forecast · Chec'!I20*'CheckoutGuard — Assumptions · W'!E7/60*'CheckoutGuard — Assumptions · C'!B16 -> 187.22424 | J36: ='CheckoutGuard — Forecast · Chec'!J20*'CheckoutGuard — Assumptions · W'!E7/60*'CheckoutGuard — Assumptions · C'!B16 -> 216.78503 | K36: ='CheckoutGuard — Forecast · Chec'!K20*'CheckoutGuard — Assumptions · W'!E7/60*'CheckoutGuard — Assumptions · C'!B16 -> 247.21786 | L36: ='CheckoutGuard — Forecast · Chec'!L20*'CheckoutGuard — Assumptions · W'!E7/60*'CheckoutGuard — Assumptions · C'!B16 -> 278.58453 | M36: ='CheckoutGuard — Forecast · Chec'!M20*'CheckoutGuard — Assumptions · W'!E7/60*'CheckoutGuard — Assumptions · C'!B16 -> 310.94936 | N36: ='CheckoutGuard — Forecast · Chec'!N20*'CheckoutGuard — Assumptions · W'!E7/60*'CheckoutGuard — Assumptions · C'!B16 -> 344.37936 | O36: ='CheckoutGuard — Forecast · Chec'!O20*'CheckoutGuard — Assumptions · W'!E7/60*'CheckoutGuard — Assumptions · C'!B16 -> 378.94439 | P36: ='CheckoutGuard — Forecast · Chec'!P20*'CheckoutGuard — Assumptions · W'!E7/60*'CheckoutGuard — Assumptions · C'!B16 -> 414.71729 | Q36: ='CheckoutGuard — Forecast · Chec'!Q20*'CheckoutGuard — Assumptions · W'!E7/60*'CheckoutGuard — Assumptions · C'!B16 -> 451.77406 | R36: ='CheckoutGuard — Forecast · Chec'!R20*'CheckoutGuard — Assumptions · W'!E7/60*'CheckoutGuard — Assumptions · C'!B16 -> 490.19404 | S36: ='CheckoutGuard — Forecast · Chec'!S20*'CheckoutGuard — Assumptions · W'!E7/60*'CheckoutGuard — Assumptions · C'!B16 -> 530.06009 | T36: ='CheckoutGuard — Forecast · Chec'!T20*'CheckoutGuard — Assumptions · W'!E7/60*'CheckoutGuard — Assumptions · C'!B16 -> 571.45874 | U36: ='CheckoutGuard — Forecast · Chec'!U20*'CheckoutGuard — Assumptions · W'!E7/60*'CheckoutGuard — Assumptions · C'!B16 -> 614.48046 | V36: ='CheckoutGuard — Forecast · Chec'!V20*'CheckoutGuard — Assumptions · W'!E7/60*'CheckoutGuard — Assumptions · C'!B16 -> 659.2198 | W36: ='CheckoutGuard — Forecast · Chec'!W20*'CheckoutGuard — Assumptions · W'!E7/60*'CheckoutGuard — Assumptions · C'!B16 -> 705.77565 | X36: ='CheckoutGuard — Forecast · Chec'!X20*'CheckoutGuard — Assumptions · W'!E7/60*'CheckoutGuard — Assumptions · C'!B16 -> 754.25144 | Y36: ='CheckoutGuard — Forecast · Chec'!Y20*'CheckoutGuard — Assumptions · W'!E7/60*'CheckoutGuard — Assumptions · C'!B16 -> 804.75542 | Z36: ='CheckoutGuard — Forecast · Chec'!Z20*'CheckoutGuard — Assumptions · W'!E7/60*'CheckoutGuard — Assumptions · C'!B16 -> 857.40085
A37: Contribution | B37: =SUM('CheckoutGuard — Forecast · Chec'!B38,'CheckoutGuard — Forecast · Chec'!B39,'CheckoutGuard — Forecast · Chec'!B40) -> 0 | C37: =SUM('CheckoutGuard — Forecast · Chec'!C38,'CheckoutGuard — Forecast · Chec'!C39,'CheckoutGuard — Forecast · Chec'!C40) -> 320.99084 | D37: =SUM('CheckoutGuard — Forecast · Chec'!D38,'CheckoutGuard — Forecast · Chec'!D39,'CheckoutGuard — Forecast · Chec'!D40) -> 648.4015 | E37: =SUM('CheckoutGuard — Forecast · Chec'!E38,'CheckoutGuard — Forecast · Chec'!E39,'CheckoutGuard — Forecast · Chec'!E40) -> 982.84185 | F37: =SUM('CheckoutGuard — Forecast · Chec'!F38,'CheckoutGuard — Forecast · Chec'!F39,'CheckoutGuard — Forecast · Chec'!F40) -> 1324.9436 | G37: =SUM('CheckoutGuard — Forecast · Chec'!G38,'CheckoutGuard — Forecast · Chec'!G39,'CheckoutGuard — Forecast · Chec'!G40) -> 1675.3617 | H37: =SUM('CheckoutGuard — Forecast · Chec'!H38,'CheckoutGuard — Forecast · Chec'!H39,'CheckoutGuard — Forecast · Chec'!H40) -> 2034.7755 | I37: =SUM('CheckoutGuard — Forecast · Chec'!I38,'CheckoutGuard — Forecast · Chec'!I39,'CheckoutGuard — Forecast · Chec'!I40) -> 2403.8907 | ... Z37: =SUM('CheckoutGuard — Forecast · Chec'!Z38,'CheckoutGuard — Forecast · Chec'!Z39,'CheckoutGuard — Forecast · Chec'!Z40) -> 11008.713
A38: Agency | B38: ='CheckoutGuard — Forecast · Chec'!B22-'CheckoutGuard — Forecast · Chec'!B30-'CheckoutGuard — Forecast · Chec'!B34-'CheckoutGuard — Forecast · Paym'!B6 -> 0 | C38: ='CheckoutGuard — Forecast · Chec'!C22-'CheckoutGuard — Forecast · Chec'!C30-'CheckoutGuard — Forecast · Chec'!C34-'CheckoutGuard — Forecast · Paym'!C6 -> 120.3222 | D38: ='CheckoutGuard — Forecast · Chec'!D22-'CheckoutGuard — Forecast · Chec'!D30-'CheckoutGuard — Forecast · Chec'!D34-'CheckoutGuard — Forecast · Paym'!D6 -> 243.05084 | E38: ='CheckoutGuard — Forecast · Chec'!E22-'CheckoutGuard — Forecast · Chec'!E30-'CheckoutGuard — Forecast · Chec'!E34-'CheckoutGuard — Forecast · Paym'!E6 -> 368.41454 | F38: ='CheckoutGuard — Forecast · Chec'!F22-'CheckoutGuard — Forecast · Chec'!F30-'CheckoutGuard — Forecast · Chec'!F34-'CheckoutGuard — Forecast · Paym'!F6 -> 496.65009 | G38: ='CheckoutGuard — Forecast · Chec'!G22-'CheckoutGuard — Forecast · Chec'!G30-'CheckoutGuard — Forecast · Chec'!G34-'CheckoutGuard — Forecast · Paym'!G6 -> 628.00298 | H38: ='CheckoutGuard — Forecast · Chec'!H22-'CheckoutGuard — Forecast · Chec'!H30-'CheckoutGuard — Forecast · Chec'!H34-'CheckoutGuard — Forecast · Paym'!H6 -> 762.72789 | I38: ='CheckoutGuard — Forecast · Chec'!I22-'CheckoutGuard — Forecast · Chec'!I30-'CheckoutGuard — Forecast · Chec'!I34-'CheckoutGuard — Forecast · Paym'!I6 -> 901.08931 | ... Z38: ='CheckoutGuard — Forecast · Chec'!Z22-'CheckoutGuard — Forecast · Chec'!Z30-'CheckoutGuard — Forecast · Chec'!Z34-'CheckoutGuard — Forecast · Paym'!Z6 -> 4126.5743
A39: Developer | B39: ='CheckoutGuard — Forecast · Chec'!B23-'CheckoutGuard — Forecast · Chec'!B31-'CheckoutGuard — Forecast · Chec'!B35-'CheckoutGuard — Forecast · Paym'!B7 -> 0 | C39: ='CheckoutGuard — Forecast · Chec'!C23-'CheckoutGuard — Forecast · Chec'!C31-'CheckoutGuard — Forecast · Chec'!C35-'CheckoutGuard — Forecast · Paym'!C7 -> 43.75144 | D39: ='CheckoutGuard — Forecast · Chec'!D23-'CheckoutGuard — Forecast · Chec'!D31-'CheckoutGuard — Forecast · Chec'!D35-'CheckoutGuard — Forecast · Paym'!D7 -> 88.377909 | E39: ='CheckoutGuard — Forecast · Chec'!E23-'CheckoutGuard — Forecast · Chec'!E31-'CheckoutGuard — Forecast · Chec'!E35-'CheckoutGuard — Forecast · Paym'!E7 -> 133.96253 | F39: ='CheckoutGuard — Forecast · Chec'!F23-'CheckoutGuard — Forecast · Chec'!F31-'CheckoutGuard — Forecast · Chec'!F35-'CheckoutGuard — Forecast · Paym'!F7 -> 180.59142 | G39: ='CheckoutGuard — Forecast · Chec'!G23-'CheckoutGuard — Forecast · Chec'!G31-'CheckoutGuard — Forecast · Chec'!G35-'CheckoutGuard — Forecast · Paym'!G7 -> 228.35383 | H39: ='CheckoutGuard — Forecast · Chec'!H23-'CheckoutGuard — Forecast · Chec'!H31-'CheckoutGuard — Forecast · Chec'!H35-'CheckoutGuard — Forecast · Paym'!H7 -> 277.34237 | I39: ='CheckoutGuard — Forecast · Chec'!I23-'CheckoutGuard — Forecast · Chec'!I31-'CheckoutGuard — Forecast · Chec'!I35-'CheckoutGuard — Forecast · Paym'!I7 -> 327.65321 | ... Z39: ='CheckoutGuard — Forecast · Chec'!Z23-'CheckoutGuard — Forecast · Chec'!Z31-'CheckoutGuard — Forecast · Chec'!Z35-'CheckoutGuard — Forecast · Paym'!Z7 -> 1500.5009
A40: Team | B40: ='CheckoutGuard — Forecast · Chec'!B24-'CheckoutGuard — Forecast · Chec'!B32-'CheckoutGuard — Forecast · Chec'!B36-'CheckoutGuard — Forecast · Paym'!B8 -> 0 | C40: ='CheckoutGuard — Forecast · Chec'!C24-'CheckoutGuard — Forecast · Chec'!C32-'CheckoutGuard — Forecast · Chec'!C36-'CheckoutGuard — Forecast · Paym'!C8 -> 156.9172 | D40: ='CheckoutGuard — Forecast · Chec'!D24-'CheckoutGuard — Forecast · Chec'!D32-'CheckoutGuard — Forecast · Chec'!D36-'CheckoutGuard — Forecast · Paym'!D8 -> 316.97274 | E40: ='CheckoutGuard — Forecast · Chec'!E24-'CheckoutGuard — Forecast · Chec'!E32-'CheckoutGuard — Forecast · Chec'!E36-'CheckoutGuard — Forecast · Paym'!E8 -> 480.46477 | F40: ='CheckoutGuard — Forecast · Chec'!F24-'CheckoutGuard — Forecast · Chec'!F32-'CheckoutGuard — Forecast · Chec'!F36-'CheckoutGuard — Forecast · Paym'!F8 -> 647.70211 | G40: ='CheckoutGuard — Forecast · Chec'!G24-'CheckoutGuard — Forecast · Chec'!G32-'CheckoutGuard — Forecast · Chec'!G36-'CheckoutGuard — Forecast · Paym'!G8 -> 819.00488 | H40: ='CheckoutGuard — Forecast · Chec'!H24-'CheckoutGuard — Forecast · Chec'!H32-'CheckoutGuard — Forecast · Chec'!H36-'CheckoutGuard — Forecast · Paym'!H8 -> 994.70526 | I40: ='CheckoutGuard — Forecast · Chec'!I24-'CheckoutGuard — Forecast · Chec'!I32-'CheckoutGuard — Forecast · Chec'!I36-'CheckoutGuard — Forecast · Paym'!I8 -> 1175.1482 | ... Z40: ='CheckoutGuard — Forecast · Chec'!Z24-'CheckoutGuard — Forecast · Chec'!Z32-'CheckoutGuard — Forecast · Chec'!Z36-'CheckoutGuard — Forecast · Paym'!Z8 -> 5381.6376
A41: Contribution margin | B41: =IFERROR('CheckoutGuard — Forecast · Chec'!B37/'CheckoutGuard — Forecast · Chec'!B21,"") | C41: =IFERROR('CheckoutGuard — Forecast · Chec'!C37/'CheckoutGuard — Forecast · Chec'!C21,"") -> 0.7915927 | D41: =IFERROR('CheckoutGuard — Forecast · Chec'!D37/'CheckoutGuard — Forecast · Chec'!D21,"") -> 0.7915927 | E41: =IFERROR('CheckoutGuard — Forecast · Chec'!E37/'CheckoutGuard — Forecast · Chec'!E21,"") -> 0.7915927 | F41: =IFERROR('CheckoutGuard — Forecast · Chec'!F37/'CheckoutGuard — Forecast · Chec'!F21,"") -> 0.7915927 | G41: =IFERROR('CheckoutGuard — Forecast · Chec'!G37/'CheckoutGuard — Forecast · Chec'!G21,"") -> 0.7915927 | H41: =IFERROR('CheckoutGuard — Forecast · Chec'!H37/'CheckoutGuard — Forecast · Chec'!H21,"") -> 0.7915927 | I41: =IFERROR('CheckoutGuard — Forecast · Chec'!I37/'CheckoutGuard — Forecast · Chec'!I21,"") -> 0.7915927 | ... Z41: =IFERROR('CheckoutGuard — Forecast · Chec'!Z37/'CheckoutGuard — Forecast · Chec'!Z21,"") -> 0.7915927
A42: Agency | B42: =IFERROR('CheckoutGuard — Forecast · Chec'!B38/'CheckoutGuard — Forecast · Chec'!B22,"") | C42: =IFERROR('CheckoutGuard — Forecast · Chec'!C38/'CheckoutGuard — Forecast · Chec'!C22,"") -> 0.80483077 | D42: =IFERROR('CheckoutGuard — Forecast · Chec'!D38/'CheckoutGuard — Forecast · Chec'!D22,"") -> 0.80483077 | E42: =IFERROR('CheckoutGuard — Forecast · Chec'!E38/'CheckoutGuard — Forecast · Chec'!E22,"") -> 0.80483077 | F42: =IFERROR('CheckoutGuard — Forecast · Chec'!F38/'CheckoutGuard — Forecast · Chec'!F22,"") -> 0.80483077 | G42: =IFERROR('CheckoutGuard — Forecast · Chec'!G38/'CheckoutGuard — Forecast · Chec'!G22,"") -> 0.80483077 | H42: =IFERROR('CheckoutGuard — Forecast · Chec'!H38/'CheckoutGuard — Forecast · Chec'!H22,"") -> 0.80483077 | I42: =IFERROR('CheckoutGuard — Forecast · Chec'!I38/'CheckoutGuard — Forecast · Chec'!I22,"") -> 0.80483077 | ... Z42: =IFERROR('CheckoutGuard — Forecast · Chec'!Z38/'CheckoutGuard — Forecast · Chec'!Z22,"") -> 0.80483077
A43: Developer | B43: =IFERROR('CheckoutGuard — Forecast · Chec'!B39/'CheckoutGuard — Forecast · Chec'!B23,"") | C43: =IFERROR('CheckoutGuard — Forecast · Chec'!C39/'CheckoutGuard — Forecast · Chec'!C23,"") -> 0.75433517 | D43: =IFERROR('CheckoutGuard — Forecast · Chec'!D39/'CheckoutGuard — Forecast · Chec'!D23,"") -> 0.75433517 | E43: =IFERROR('CheckoutGuard — Forecast · Chec'!E39/'CheckoutGuard — Forecast · Chec'!E23,"") -> 0.75433517 | F43: =IFERROR('CheckoutGuard — Forecast · Chec'!F39/'CheckoutGuard — Forecast · Chec'!F23,"") -> 0.75433517 | G43: =IFERROR('CheckoutGuard — Forecast · Chec'!G39/'CheckoutGuard — Forecast · Chec'!G23,"") -> 0.75433517 | H43: =IFERROR('CheckoutGuard — Forecast · Chec'!H39/'CheckoutGuard — Forecast · Chec'!H23,"") -> 0.75433517 | I43: =IFERROR('CheckoutGuard — Forecast · Chec'!I39/'CheckoutGuard — Forecast · Chec'!I23,"") -> 0.75433517 | ... Z43: =IFERROR('CheckoutGuard — Forecast · Chec'!Z39/'CheckoutGuard — Forecast · Chec'!Z23,"") -> 0.75433517
A44: Team | B44: =IFERROR('CheckoutGuard — Forecast · Chec'!B40/'CheckoutGuard — Forecast · Chec'!B24,"") | C44: =IFERROR('CheckoutGuard — Forecast · Chec'!C40/'CheckoutGuard — Forecast · Chec'!C24,"") -> 0.79251111 | D44: =IFERROR('CheckoutGuard — Forecast · Chec'!D40/'CheckoutGuard — Forecast · Chec'!D24,"") -> 0.79251111 | E44: =IFERROR('CheckoutGuard — Forecast · Chec'!E40/'CheckoutGuard — Forecast · Chec'!E24,"") -> 0.79251111 | F44: =IFERROR('CheckoutGuard — Forecast · Chec'!F40/'CheckoutGuard — Forecast · Chec'!F24,"") -> 0.79251111 | G44: =IFERROR('CheckoutGuard — Forecast · Chec'!G40/'CheckoutGuard — Forecast · Chec'!G24,"") -> 0.79251111 | H44: =IFERROR('CheckoutGuard — Forecast · Chec'!H40/'CheckoutGuard — Forecast · Chec'!H24,"") -> 0.79251111 | I44: =IFERROR('CheckoutGuard — Forecast · Chec'!I40/'CheckoutGuard — Forecast · Chec'!I24,"") -> 0.79251111 | ... Z44: =IFERROR('CheckoutGuard — Forecast · Chec'!Z40/'CheckoutGuard — Forecast · Chec'!Z24,"") -> 0.79251111
A45: Operating result | B45: =0 -> 0 | C45: ='CheckoutGuard — Forecast · Chec'!C37-'CheckoutGuard — Assumptions (2)'!B13 -> -6479.0092 | D45: ='CheckoutGuard — Forecast · Chec'!D37-'CheckoutGuard — Assumptions (2)'!B13 -> -6151.5985 | E45: ='CheckoutGuard — Forecast · Chec'!E37-'CheckoutGuard — Assumptions (2)'!B13 -> -5817.1581 | F45: ='CheckoutGuard — Forecast · Chec'!F37-'CheckoutGuard — Assumptions (2)'!B13 -> -5475.0564 | G45: ='CheckoutGuard — Forecast · Chec'!G37-'CheckoutGuard — Assumptions (2)'!B13 -> -5124.6383 | H45: ='CheckoutGuard — Forecast · Chec'!H37-'CheckoutGuard — Assumptions (2)'!B13 -> -4765.2245 | I45: ='CheckoutGuard — Forecast · Chec'!I37-'CheckoutGuard — Assumptions (2)'!B13 -> -4396.1093 | J45: ='CheckoutGuard — Forecast · Chec'!J37-'CheckoutGuard — Assumptions (2)'!B13 -> -4016.5597 | K45: ='CheckoutGuard — Forecast · Chec'!K37-'CheckoutGuard — Assumptions (2)'!B13 -> -3625.8132 | L45: ='CheckoutGuard — Forecast · Chec'!L37-'CheckoutGuard — Assumptions (2)'!B13 -> -3223.0767 | M45: ='CheckoutGuard — Forecast · Chec'!M37-'CheckoutGuard — Assumptions (2)'!B13 -> -2807.5241 | N45: ='CheckoutGuard — Forecast · Chec'!N37-'CheckoutGuard — Assumptions (2)'!B13 -> -2378.2951 | O45: ='CheckoutGuard — Forecast · Chec'!O37-'CheckoutGuard — Assumptions (2)'!B13 -> -1934.4929 | P45: ='CheckoutGuard — Forecast · Chec'!P37-'CheckoutGuard — Assumptions (2)'!B13 -> -1475.182 | Q45: ='CheckoutGuard — Forecast · Chec'!Q37-'CheckoutGuard — Assumptions (2)'!B13 -> -999.38661 | R45: ='CheckoutGuard — Forecast · Chec'!R37-'CheckoutGuard — Assumptions (2)'!B13 -> -506.08811 | S45: ='CheckoutGuard — Forecast · Chec'!S37-'CheckoutGuard — Assumptions (2)'!B13 -> 5.7772852 | T45: ='CheckoutGuard — Forecast · Chec'!T37-'CheckoutGuard — Assumptions (2)'!B13 -> 537.32085 | U45: ='CheckoutGuard — Forecast · Chec'!U37-'CheckoutGuard — Assumptions (2)'!B13 -> 1089.704 | V45: ='CheckoutGuard — Forecast · Chec'!V37-'CheckoutGuard — Assumptions (2)'!B13 -> 1664.1407 | W45: ='CheckoutGuard — Forecast · Chec'!W37-'CheckoutGuard — Assumptions (2)'!B13 -> 2261.9007 | X45: ='CheckoutGuard — Forecast · Chec'!X37-'CheckoutGuard — Assumptions (2)'!B13 -> 2884.3122 | Y45: ='CheckoutGuard — Forecast · Chec'!Y37-'CheckoutGuard — Assumptions (2)'!B13 -> 3532.7647 | Z45: ='CheckoutGuard — Forecast · Chec'!Z37-'CheckoutGuard — Assumptions (2)'!B13 -> 4208.7128
A46: Break-even subscriptions | B46: =IFERROR(CEILING('CheckoutGuard — Assumptions (2)'!B13/('CheckoutGuard — Forecast · Chec'!B37/'CheckoutGuard — Forecast · Chec'!B17),1),"") | C46: =IFERROR(CEILING('CheckoutGuard — Assumptions (2)'!B13/('CheckoutGuard — Forecast · Chec'!C37/'CheckoutGuard — Forecast · Chec'!C17),1),"") -> 96 | D46: =IFERROR(CEILING('CheckoutGuard — Assumptions (2)'!B13/('CheckoutGuard — Forecast · Chec'!D37/'CheckoutGuard — Forecast · Chec'!D17),1),"") -> 96 | E46: =IFERROR(CEILING('CheckoutGuard — Assumptions (2)'!B13/('CheckoutGuard — Forecast · Chec'!E37/'CheckoutGuard — Forecast · Chec'!E17),1),"") -> 96 | F46: =IFERROR(CEILING('CheckoutGuard — Assumptions (2)'!B13/('CheckoutGuard — Forecast · Chec'!F37/'CheckoutGuard — Forecast · Chec'!F17),1),"") -> 96 | G46: =IFERROR(CEILING('CheckoutGuard — Assumptions (2)'!B13/('CheckoutGuard — Forecast · Chec'!G37/'CheckoutGuard — Forecast · Chec'!G17),1),"") -> 96 | H46: =IFERROR(CEILING('CheckoutGuard — Assumptions (2)'!B13/('CheckoutGuard — Forecast · Chec'!H37/'CheckoutGuard — Forecast · Chec'!H17),1),"") -> 96 | I46: =IFERROR(CEILING('CheckoutGuard — Assumptions (2)'!B13/('CheckoutGuard — Forecast · Chec'!I37/'CheckoutGuard — Forecast · Chec'!I17),1),"") -> 96 | J46: =IFERROR(CEILING('CheckoutGuard — Assumptions (2)'!B13/('CheckoutGuard — Forecast · Chec'!J37/'CheckoutGuard — Forecast · Chec'!J17),1),"") -> 96 | K46: =IFERROR(CEILING('CheckoutGuard — Assumptions (2)'!B13/('CheckoutGuard — Forecast · Chec'!K37/'CheckoutGuard — Forecast · Chec'!K17),1),"") -> 96 | L46: =IFERROR(CEILING('CheckoutGuard — Assumptions (2)'!B13/('CheckoutGuard — Forecast · Chec'!L37/'CheckoutGuard — Forecast · Chec'!L17),1),"") -> 96 | M46: =IFERROR(CEILING('CheckoutGuard — Assumptions (2)'!B13/('CheckoutGuard — Forecast · Chec'!M37/'CheckoutGuard — Forecast · Chec'!M17),1),"") -> 96 | N46: =IFERROR(CEILING('CheckoutGuard — Assumptions (2)'!B13/('CheckoutGuard — Forecast · Chec'!N37/'CheckoutGuard — Forecast · Chec'!N17),1),"") -> 96 | O46: =IFERROR(CEILING('CheckoutGuard — Assumptions (2)'!B13/('CheckoutGuard — Forecast · Chec'!O37/'CheckoutGuard — Forecast · Chec'!O17),1),"") -> 96 | P46: =IFERROR(CEILING('CheckoutGuard — Assumptions (2)'!B13/('CheckoutGuard — Forecast · Chec'!P37/'CheckoutGuard — Forecast · Chec'!P17),1),"") -> 96 | Q46: =IFERROR(CEILING('CheckoutGuard — Assumptions (2)'!B13/('CheckoutGuard — Forecast · Chec'!Q37/'CheckoutGuard — Forecast · Chec'!Q17),1),"") -> 96 | R46: =IFERROR(CEILING('CheckoutGuard — Assumptions (2)'!B13/('CheckoutGuard — Forecast · Chec'!R37/'CheckoutGuard — Forecast · Chec'!R17),1),"") -> 96 | S46: =IFERROR(CEILING('CheckoutGuard — Assumptions (2)'!B13/('CheckoutGuard — Forecast · Chec'!S37/'CheckoutGuard — Forecast · Chec'!S17),1),"") -> 96 | T46: =IFERROR(CEILING('CheckoutGuard — Assumptions (2)'!B13/('CheckoutGuard — Forecast · Chec'!T37/'CheckoutGuard — Forecast · Chec'!T17),1),"") -> 96 | U46: =IFERROR(CEILING('CheckoutGuard — Assumptions (2)'!B13/('CheckoutGuard — Forecast · Chec'!U37/'CheckoutGuard — Forecast · Chec'!U17),1),"") -> 96 | V46: =IFERROR(CEILING('CheckoutGuard — Assumptions (2)'!B13/('CheckoutGuard — Forecast · Chec'!V37/'CheckoutGuard — Forecast · Chec'!V17),1),"") -> 96 | W46: =IFERROR(CEILING('CheckoutGuard — Assumptions (2)'!B13/('CheckoutGuard — Forecast · Chec'!W37/'CheckoutGuard — Forecast · Chec'!W17),1),"") -> 96 | X46: =IFERROR(CEILING('CheckoutGuard — Assumptions (2)'!B13/('CheckoutGuard — Forecast · Chec'!X37/'CheckoutGuard — Forecast · Chec'!X17),1),"") -> 96 | Y46: =IFERROR(CEILING('CheckoutGuard — Assumptions (2)'!B13/('CheckoutGuard — Forecast · Chec'!Y37/'CheckoutGuard — Forecast · Chec'!Y17),1),"") -> 96 | Z46: =IFERROR(CEILING('CheckoutGuard — Assumptions (2)'!B13/('CheckoutGuard — Forecast · Chec'!Z37/'CheckoutGuard — Forecast · Chec'!Z17),1),"") -> 96
A47: Break-even revenue | B47: =IFERROR(IF('CheckoutGuard — Forecast · Chec'!B46="",0,'CheckoutGuard — Forecast · Chec'!B46)*'CheckoutGuard — Forecast · Chec'!B21/'CheckoutGuard — Forecast · Chec'!B17,"") | C47: =IFERROR('CheckoutGuard — Forecast · Chec'!C46*'CheckoutGuard — Forecast · Chec'!C21/'CheckoutGuard — Forecast · Chec'!C17,"") -> 8650.6667 | D47: =IFERROR('CheckoutGuard — Forecast · Chec'!D46*'CheckoutGuard — Forecast · Chec'!D21/'CheckoutGuard — Forecast · Chec'!D17,"") -> 8650.6667 | E47: =IFERROR('CheckoutGuard — Forecast · Chec'!E46*'CheckoutGuard — Forecast · Chec'!E21/'CheckoutGuard — Forecast · Chec'!E17,"") -> 8650.6667 | F47: =IFERROR('CheckoutGuard — Forecast · Chec'!F46*'CheckoutGuard — Forecast · Chec'!F21/'CheckoutGuard — Forecast · Chec'!F17,"") -> 8650.6667 | G47: =IFERROR('CheckoutGuard — Forecast · Chec'!G46*'CheckoutGuard — Forecast · Chec'!G21/'CheckoutGuard — Forecast · Chec'!G17,"") -> 8650.6667 | H47: =IFERROR('CheckoutGuard — Forecast · Chec'!H46*'CheckoutGuard — Forecast · Chec'!H21/'CheckoutGuard — Forecast · Chec'!H17,"") -> 8650.6667 | I47: =IFERROR('CheckoutGuard — Forecast · Chec'!I46*'CheckoutGuard — Forecast · Chec'!I21/'CheckoutGuard — Forecast · Chec'!I17,"") -> 8650.6667 | J47: =IFERROR('CheckoutGuard — Forecast · Chec'!J46*'CheckoutGuard — Forecast · Chec'!J21/'CheckoutGuard — Forecast · Chec'!J17,"") -> 8650.6667 | ... Z47: =IFERROR('CheckoutGuard — Forecast · Chec'!Z46*'CheckoutGuard — Forecast · Chec'!Z21/'CheckoutGuard — Forecast · Chec'!Z17,"") -> 8650.6667
A48: Monthly funding gap | B48: =MAX(-'CheckoutGuard — Forecast · Chec'!B45,0) -> 0 | C48: =MAX(-'CheckoutGuard — Forecast · Chec'!C45,0) -> 6479.0092 | D48: =MAX(-'CheckoutGuard — Forecast · Chec'!D45,0) -> 6151.5985 | E48: =MAX(-'CheckoutGuard — Forecast · Chec'!E45,0) -> 5817.1581 | F48: =MAX(-'CheckoutGuard — Forecast · Chec'!F45,0) -> 5475.0564 | G48: =MAX(-'CheckoutGuard — Forecast · Chec'!G45,0) -> 5124.6383 | H48: =MAX(-'CheckoutGuard — Forecast · Chec'!H45,0) -> 4765.2245 | I48: =MAX(-'CheckoutGuard — Forecast · Chec'!I45,0) -> 4396.1093 | ... Z48: =MAX(-'CheckoutGuard — Forecast · Chec'!Z45,0) -> 0
A49: Cumulative operating result | B49: =0 -> 0 | C49: ='CheckoutGuard — Forecast · Chec'!B49+'CheckoutGuard — Forecast · Chec'!C45 -> -6479.0092 | D49: ='CheckoutGuard — Forecast · Chec'!C49+'CheckoutGuard — Forecast · Chec'!D45 -> -12630.608 | E49: ='CheckoutGuard — Forecast · Chec'!D49+'CheckoutGuard — Forecast · Chec'!E45 -> -18447.766 | F49: ='CheckoutGuard — Forecast · Chec'!E49+'CheckoutGuard — Forecast · Chec'!F45 -> -23922.822 | G49: ='CheckoutGuard — Forecast · Chec'!F49+'CheckoutGuard — Forecast · Chec'!G45 -> -29047.461 | H49: ='CheckoutGuard — Forecast · Chec'!G49+'CheckoutGuard — Forecast · Chec'!H45 -> -33812.685 | I49: ='CheckoutGuard — Forecast · Chec'!H49+'CheckoutGuard — Forecast · Chec'!I45 -> -38208.794 | J49: ='CheckoutGuard — Forecast · Chec'!I49+'CheckoutGuard — Forecast · Chec'!J45 -> -42225.354 | ... Z49: ='CheckoutGuard — Forecast · Chec'!Y49+'CheckoutGuard — Forecast · Chec'!Z45 -> -42990.58

Sheet CheckoutGuard — Forecast · Paym
A1: CheckoutGuard — Forecast · Payment cost estimates
A2: Financial model (3 pages) · Main Scenario
A4: Variable / dimension | B4: 2026-10 | C4: 2026-11 | D4: 2026-12 | E4: 2027-01 | F4: 2027-02 | G4: 2027-03 | H4: 2027-04 | I4: 2027-05 | J4: 2027-06 | K4: 2027-07 | L4: 2027-08 | M4: 2027-09 | N4: 2027-10 | O4: 2027-11 | P4: 2027-12 | Q4: 2028-01 | R4: 2028-02 | S4: 2028-03 | T4: 2028-04 | U4: 2028-05 | V4: 2028-06 | W4: 2028-07 | X4: 2028-08 | Y4: 2028-09 | Z4: 2028-10
A5: Payment processing costs | B5: =SUM('CheckoutGuard — Forecast · Paym'!B6,'CheckoutGuard — Forecast · Paym'!B7,'CheckoutGuard — Forecast · Paym'!B8) -> 0 | C5: =SUM('CheckoutGuard — Forecast · Paym'!C6,'CheckoutGuard — Forecast · Paym'!C7,'CheckoutGuard — Forecast · Paym'!C8) -> 13.515 | D5: =SUM('CheckoutGuard — Forecast · Paym'!D6,'CheckoutGuard — Forecast · Paym'!D7,'CheckoutGuard — Forecast · Paym'!D8) -> 27.3003 | E5: =SUM('CheckoutGuard — Forecast · Paym'!E6,'CheckoutGuard — Forecast · Paym'!E7,'CheckoutGuard — Forecast · Paym'!E8) -> 41.381579 | F5: =SUM('CheckoutGuard — Forecast · Paym'!F6,'CheckoutGuard — Forecast · Paym'!F7,'CheckoutGuard — Forecast · Paym'!F8) -> 55.785433 | G5: =SUM('CheckoutGuard — Forecast · Paym'!G6,'CheckoutGuard — Forecast · Paym'!G7,'CheckoutGuard — Forecast · Paym'!G8) -> 70.539437 | H5: =SUM('CheckoutGuard — Forecast · Paym'!H6,'CheckoutGuard — Forecast · Paym'!H7,'CheckoutGuard — Forecast · Paym'!H8) -> 85.672199 | I5: =SUM('CheckoutGuard — Forecast · Paym'!I6,'CheckoutGuard — Forecast · Paym'!I7,'CheckoutGuard — Forecast · Paym'!I8) -> 101.21343 | ... Z5: =SUM('CheckoutGuard — Forecast · Paym'!Z6,'CheckoutGuard — Forecast · Paym'!Z7,'CheckoutGuard — Forecast · Paym'!Z8) -> 463.5109
A6: Agency | B6: ='CheckoutGuard — Forecast · Chec'!B22*'CheckoutGuard — Assumptions · S'!B5+'CheckoutGuard — Forecast · Chec'!B18*'CheckoutGuard — Assumptions · S'!B6 -> 0 | C6: ='CheckoutGuard — Forecast · Chec'!C22*'CheckoutGuard — Assumptions · S'!B5+'CheckoutGuard — Forecast · Chec'!C18*'CheckoutGuard — Assumptions · S'!B6 -> 4.635 | D6: ='CheckoutGuard — Forecast · Chec'!D22*'CheckoutGuard — Assumptions · S'!B5+'CheckoutGuard — Forecast · Chec'!D18*'CheckoutGuard — Assumptions · S'!B6 -> 9.3627 | E6: ='CheckoutGuard — Forecast · Chec'!E22*'CheckoutGuard — Assumptions · S'!B5+'CheckoutGuard — Forecast · Chec'!E18*'CheckoutGuard — Assumptions · S'!B6 -> 14.191906 | F6: ='CheckoutGuard — Forecast · Chec'!F22*'CheckoutGuard — Assumptions · S'!B5+'CheckoutGuard — Forecast · Chec'!F18*'CheckoutGuard — Assumptions · S'!B6 -> 19.131741 | G6: ='CheckoutGuard — Forecast · Chec'!G22*'CheckoutGuard — Assumptions · S'!B5+'CheckoutGuard — Forecast · Chec'!G18*'CheckoutGuard — Assumptions · S'!B6 -> 24.19166 | H6: ='CheckoutGuard — Forecast · Chec'!H22*'CheckoutGuard — Assumptions · S'!B5+'CheckoutGuard — Forecast · Chec'!H18*'CheckoutGuard — Assumptions · S'!B6 -> 29.381476 | I6: ='CheckoutGuard — Forecast · Chec'!I22*'CheckoutGuard — Assumptions · S'!B5+'CheckoutGuard — Forecast · Chec'!I18*'CheckoutGuard — Assumptions · S'!B6 -> 34.711375 | J6: ='CheckoutGuard — Forecast · Chec'!J22*'CheckoutGuard — Assumptions · S'!B5+'CheckoutGuard — Forecast · Chec'!J18*'CheckoutGuard — Assumptions · S'!B6 -> 40.191944 | K6: ='CheckoutGuard — Forecast · Chec'!K22*'CheckoutGuard — Assumptions · S'!B5+'CheckoutGuard — Forecast · Chec'!K18*'CheckoutGuard — Assumptions · S'!B6 -> 45.834192 | L6: ='CheckoutGuard — Forecast · Chec'!L22*'CheckoutGuard — Assumptions · S'!B5+'CheckoutGuard — Forecast · Chec'!L18*'CheckoutGuard — Assumptions · S'!B6 -> 51.649572 | M6: ='CheckoutGuard — Forecast · Chec'!M22*'CheckoutGuard — Assumptions · S'!B5+'CheckoutGuard — Forecast · Chec'!M18*'CheckoutGuard — Assumptions · S'!B6 -> 57.650012 | N6: ='CheckoutGuard — Forecast · Chec'!N22*'CheckoutGuard — Assumptions · S'!B5+'CheckoutGuard — Forecast · Chec'!N18*'CheckoutGuard — Assumptions · S'!B6 -> 63.847934 | O6: ='CheckoutGuard — Forecast · Chec'!O22*'CheckoutGuard — Assumptions · S'!B5+'CheckoutGuard — Forecast · Chec'!O18*'CheckoutGuard — Assumptions · S'!B6 -> 70.25629 | P6: ='CheckoutGuard — Forecast · Chec'!P22*'CheckoutGuard — Assumptions · S'!B5+'CheckoutGuard — Forecast · Chec'!P18*'CheckoutGuard — Assumptions · S'!B6 -> 76.888585 | Q6: ='CheckoutGuard — Forecast · Chec'!Q22*'CheckoutGuard — Assumptions · S'!B5+'CheckoutGuard — Forecast · Chec'!Q18*'CheckoutGuard — Assumptions · S'!B6 -> 83.758911 | R6: ='CheckoutGuard — Forecast · Chec'!R22*'CheckoutGuard — Assumptions · S'!B5+'CheckoutGuard — Forecast · Chec'!R18*'CheckoutGuard — Assumptions · S'!B6 -> 90.881975 | S6: ='CheckoutGuard — Forecast · Chec'!S22*'CheckoutGuard — Assumptions · S'!B5+'CheckoutGuard — Forecast · Chec'!S18*'CheckoutGuard — Assumptions · S'!B6 -> 98.27314 | T6: ='CheckoutGuard — Forecast · Chec'!T22*'CheckoutGuard — Assumptions · S'!B5+'CheckoutGuard — Forecast · Chec'!T18*'CheckoutGuard — Assumptions · S'!B6 -> 105.94845 | U6: ='CheckoutGuard — Forecast · Chec'!U22*'CheckoutGuard — Assumptions · S'!B5+'CheckoutGuard — Forecast · Chec'!U18*'CheckoutGuard — Assumptions · S'!B6 -> 113.92468 | V6: ='CheckoutGuard — Forecast · Chec'!V22*'CheckoutGuard — Assumptions · S'!B5+'CheckoutGuard — Forecast · Chec'!V18*'CheckoutGuard — Assumptions · S'!B6 -> 122.21935 | W6: ='CheckoutGuard — Forecast · Chec'!W22*'CheckoutGuard — Assumptions · S'!B5+'CheckoutGuard — Forecast · Chec'!W18*'CheckoutGuard — Assumptions · S'!B6 -> 130.85081 | X6: ='CheckoutGuard — Forecast · Chec'!X22*'CheckoutGuard — Assumptions · S'!B5+'CheckoutGuard — Forecast · Chec'!X18*'CheckoutGuard — Assumptions · S'!B6 -> 139.83822 | Y6: ='CheckoutGuard — Forecast · Chec'!Y22*'CheckoutGuard — Assumptions · S'!B5+'CheckoutGuard — Forecast · Chec'!Y18*'CheckoutGuard — Assumptions · S'!B6 -> 149.20165 | Z6: ='CheckoutGuard — Forecast · Chec'!Z22*'CheckoutGuard — Assumptions · S'!B5+'CheckoutGuard — Forecast · Chec'!Z18*'CheckoutGuard — Assumptions · S'!B6 -> 158.96212
A7: Developer | B7: ='CheckoutGuard — Forecast · Chec'!B23*'CheckoutGuard — Assumptions · S'!B5+'CheckoutGuard — Forecast · Chec'!B19*'CheckoutGuard — Assumptions · S'!B6 -> 0 | C7: ='CheckoutGuard — Forecast · Chec'!C23*'CheckoutGuard — Assumptions · S'!B5+'CheckoutGuard — Forecast · Chec'!C19*'CheckoutGuard — Assumptions · S'!B6 -> 2.34 | D7: ='CheckoutGuard — Forecast · Chec'!D23*'CheckoutGuard — Assumptions · S'!B5+'CheckoutGuard — Forecast · Chec'!D19*'CheckoutGuard — Assumptions · S'!B6 -> 4.7268 | E7: ='CheckoutGuard — Forecast · Chec'!E23*'CheckoutGuard — Assumptions · S'!B5+'CheckoutGuard — Forecast · Chec'!E19*'CheckoutGuard — Assumptions · S'!B6 -> 7.164846 | F7: ='CheckoutGuard — Forecast · Chec'!F23*'CheckoutGuard — Assumptions · S'!B5+'CheckoutGuard — Forecast · Chec'!F19*'CheckoutGuard — Assumptions · S'!B6 -> 9.6587431 | G7: ='CheckoutGuard — Forecast · Chec'!G23*'CheckoutGuard — Assumptions · S'!B5+'CheckoutGuard — Forecast · Chec'!G19*'CheckoutGuard — Assumptions · S'!B6 -> 12.213265 | H7: ='CheckoutGuard — Forecast · Chec'!H23*'CheckoutGuard — Assumptions · S'!B5+'CheckoutGuard — Forecast · Chec'!H19*'CheckoutGuard — Assumptions · S'!B6 -> 14.833366 | I7: ='CheckoutGuard — Forecast · Chec'!I23*'CheckoutGuard — Assumptions · S'!B5+'CheckoutGuard — Forecast · Chec'!I19*'CheckoutGuard — Assumptions · S'!B6 -> 17.524189 | J7: ='CheckoutGuard — Forecast · Chec'!J23*'CheckoutGuard — Assumptions · S'!B5+'CheckoutGuard — Forecast · Chec'!J19*'CheckoutGuard — Assumptions · S'!B6 -> 20.291078 | K7: ='CheckoutGuard — Forecast · Chec'!K23*'CheckoutGuard — Assumptions · S'!B5+'CheckoutGuard — Forecast · Chec'!K19*'CheckoutGuard — Assumptions · S'!B6 -> 23.139592 | L7: ='CheckoutGuard — Forecast · Chec'!L23*'CheckoutGuard — Assumptions · S'!B5+'CheckoutGuard — Forecast · Chec'!L19*'CheckoutGuard — Assumptions · S'!B6 -> 26.075512 | M7: ='CheckoutGuard — Forecast · Chec'!M23*'CheckoutGuard — Assumptions · S'!B5+'CheckoutGuard — Forecast · Chec'!M19*'CheckoutGuard — Assumptions · S'!B6 -> 29.10486 | N7: ='CheckoutGuard — Forecast · Chec'!N23*'CheckoutGuard — Assumptions · S'!B5+'CheckoutGuard — Forecast · Chec'!N19*'CheckoutGuard — Assumptions · S'!B6 -> 32.233908 | O7: ='CheckoutGuard — Forecast · Chec'!O23*'CheckoutGuard — Assumptions · S'!B5+'CheckoutGuard — Forecast · Chec'!O19*'CheckoutGuard — Assumptions · S'!B6 -> 35.469195 | P7: ='CheckoutGuard — Forecast · Chec'!P23*'CheckoutGuard — Assumptions · S'!B5+'CheckoutGuard — Forecast · Chec'!P19*'CheckoutGuard — Assumptions · S'!B6 -> 38.817538 | Q7: ='CheckoutGuard — Forecast · Chec'!Q23*'CheckoutGuard — Assumptions · S'!B5+'CheckoutGuard — Forecast · Chec'!Q19*'CheckoutGuard — Assumptions · S'!B6 -> 42.286052 | R7: ='CheckoutGuard — Forecast · Chec'!R23*'CheckoutGuard — Assumptions · S'!B5+'CheckoutGuard — Forecast · Chec'!R19*'CheckoutGuard — Assumptions · S'!B6 -> 45.882162 | S7: ='CheckoutGuard — Forecast · Chec'!S23*'CheckoutGuard — Assumptions · S'!B5+'CheckoutGuard — Forecast · Chec'!S19*'CheckoutGuard — Assumptions · S'!B6 -> 49.613624 | T7: ='CheckoutGuard — Forecast · Chec'!T23*'CheckoutGuard — Assumptions · S'!B5+'CheckoutGuard — Forecast · Chec'!T19*'CheckoutGuard — Assumptions · S'!B6 -> 53.488538 | U7: ='CheckoutGuard — Forecast · Chec'!U23*'CheckoutGuard — Assumptions · S'!B5+'CheckoutGuard — Forecast · Chec'!U19*'CheckoutGuard — Assumptions · S'!B6 -> 57.515371 | V7: ='CheckoutGuard — Forecast · Chec'!V23*'CheckoutGuard — Assumptions · S'!B5+'CheckoutGuard — Forecast · Chec'!V19*'CheckoutGuard — Assumptions · S'!B6 -> 61.702973 | W7: ='CheckoutGuard — Forecast · Chec'!W23*'CheckoutGuard — Assumptions · S'!B5+'CheckoutGuard — Forecast · Chec'!W19*'CheckoutGuard — Assumptions · S'!B6 -> 66.060601 | X7: ='CheckoutGuard — Forecast · Chec'!X23*'CheckoutGuard — Assumptions · S'!B5+'CheckoutGuard — Forecast · Chec'!X19*'CheckoutGuard — Assumptions · S'!B6 -> 70.597935 | Y7: ='CheckoutGuard — Forecast · Chec'!Y23*'CheckoutGuard — Assumptions · S'!B5+'CheckoutGuard — Forecast · Chec'!Y19*'CheckoutGuard — Assumptions · S'!B6 -> 75.325107 | Z7: ='CheckoutGuard — Forecast · Chec'!Z23*'CheckoutGuard — Assumptions · S'!B5+'CheckoutGuard — Forecast · Chec'!Z19*'CheckoutGuard — Assumptions · S'!B6 -> 80.25272
A8: Team | B8: ='CheckoutGuard — Forecast · Chec'!B24*'CheckoutGuard — Assumptions · S'!B5+'CheckoutGuard — Forecast · Chec'!B20*'CheckoutGuard — Assumptions · S'!B6 -> 0 | C8: ='CheckoutGuard — Forecast · Chec'!C24*'CheckoutGuard — Assumptions · S'!B5+'CheckoutGuard — Forecast · Chec'!C20*'CheckoutGuard — Assumptions · S'!B6 -> 6.54 | D8: ='CheckoutGuard — Forecast · Chec'!D24*'CheckoutGuard — Assumptions · S'!B5+'CheckoutGuard — Forecast · Chec'!D20*'CheckoutGuard — Assumptions · S'!B6 -> 13.2108 | E8: ='CheckoutGuard — Forecast · Chec'!E24*'CheckoutGuard — Assumptions · S'!B5+'CheckoutGuard — Forecast · Chec'!E20*'CheckoutGuard — Assumptions · S'!B6 -> 20.024826 | F8: ='CheckoutGuard — Forecast · Chec'!F24*'CheckoutGuard — Assumptions · S'!B5+'CheckoutGuard — Forecast · Chec'!F20*'CheckoutGuard — Assumptions · S'!B6 -> 26.994949 | G8: ='CheckoutGuard — Forecast · Chec'!G24*'CheckoutGuard — Assumptions · S'!B5+'CheckoutGuard — Forecast · Chec'!G20*'CheckoutGuard — Assumptions · S'!B6 -> 34.134511 | H8: ='CheckoutGuard — Forecast · Chec'!H24*'CheckoutGuard — Assumptions · S'!B5+'CheckoutGuard — Forecast · Chec'!H20*'CheckoutGuard — Assumptions · S'!B6 -> 41.457357 | I8: ='CheckoutGuard — Forecast · Chec'!I24*'CheckoutGuard — Assumptions · S'!B5+'CheckoutGuard — Forecast · Chec'!I20*'CheckoutGuard — Assumptions · S'!B6 -> 48.977862 | J8: ='CheckoutGuard — Forecast · Chec'!J24*'CheckoutGuard — Assumptions · S'!B5+'CheckoutGuard — Forecast · Chec'!J20*'CheckoutGuard — Assumptions · S'!B6 -> 56.710963 | K8: ='CheckoutGuard — Forecast · Chec'!K24*'CheckoutGuard — Assumptions · S'!B5+'CheckoutGuard — Forecast · Chec'!K20*'CheckoutGuard — Assumptions · S'!B6 -> 64.672193 | L8: ='CheckoutGuard — Forecast · Chec'!L24*'CheckoutGuard — Assumptions · S'!B5+'CheckoutGuard — Forecast · Chec'!L20*'CheckoutGuard — Assumptions · S'!B6 -> 72.877713 | M8: ='CheckoutGuard — Forecast · Chec'!M24*'CheckoutGuard — Assumptions · S'!B5+'CheckoutGuard — Forecast · Chec'!M20*'CheckoutGuard — Assumptions · S'!B6 -> 81.344353 | N8: ='CheckoutGuard — Forecast · Chec'!N24*'CheckoutGuard — Assumptions · S'!B5+'CheckoutGuard — Forecast · Chec'!N20*'CheckoutGuard — Assumptions · S'!B6 -> 90.089642 | O8: ='CheckoutGuard — Forecast · Chec'!O24*'CheckoutGuard — Assumptions · S'!B5+'CheckoutGuard — Forecast · Chec'!O20*'CheckoutGuard — Assumptions · S'!B6 -> 99.131853 | P8: ='CheckoutGuard — Forecast · Chec'!P24*'CheckoutGuard — Assumptions · S'!B5+'CheckoutGuard — Forecast · Chec'!P20*'CheckoutGuard — Assumptions · S'!B6 -> 108.49004 | Q8: ='CheckoutGuard — Forecast · Chec'!Q24*'CheckoutGuard — Assumptions · S'!B5+'CheckoutGuard — Forecast · Chec'!Q20*'CheckoutGuard — Assumptions · S'!B6 -> 118.18409 | R8: ='CheckoutGuard — Forecast · Chec'!R24*'CheckoutGuard — Assumptions · S'!B5+'CheckoutGuard — Forecast · Chec'!R20*'CheckoutGuard — Assumptions · S'!B6 -> 128.23476 | S8: ='CheckoutGuard — Forecast · Chec'!S24*'CheckoutGuard — Assumptions · S'!B5+'CheckoutGuard — Forecast · Chec'!S20*'CheckoutGuard — Assumptions · S'!B6 -> 138.66372 | T8: ='CheckoutGuard — Forecast · Chec'!T24*'CheckoutGuard — Assumptions · S'!B5+'CheckoutGuard — Forecast · Chec'!T20*'CheckoutGuard — Assumptions · S'!B6 -> 149.49361 | U8: ='CheckoutGuard — Forecast · Chec'!U24*'CheckoutGuard — Assumptions · S'!B5+'CheckoutGuard — Forecast · Chec'!U20*'CheckoutGuard — Assumptions · S'!B6 -> 160.74809 | V8: ='CheckoutGuard — Forecast · Chec'!V24*'CheckoutGuard — Assumptions · S'!B5+'CheckoutGuard — Forecast · Chec'!V20*'CheckoutGuard — Assumptions · S'!B6 -> 172.4519 | W8: ='CheckoutGuard — Forecast · Chec'!W24*'CheckoutGuard — Assumptions · S'!B5+'CheckoutGuard — Forecast · Chec'!W20*'CheckoutGuard — Assumptions · S'!B6 -> 184.63091 | X8: ='CheckoutGuard — Forecast · Chec'!X24*'CheckoutGuard — Assumptions · S'!B5+'CheckoutGuard — Forecast · Chec'!X20*'CheckoutGuard — Assumptions · S'!B6 -> 197.31218 | Y8: ='CheckoutGuard — Forecast · Chec'!Y24*'CheckoutGuard — Assumptions · S'!B5+'CheckoutGuard — Forecast · Chec'!Y20*'CheckoutGuard — Assumptions · S'!B6 -> 210.52402 | Z8: ='CheckoutGuard — Forecast · Chec'!Z24*'CheckoutGuard — Assumptions · S'!B5+'CheckoutGuard — Forecast · Chec'!Z20*'CheckoutGuard — Assumptions · S'!B6 -> 224.29606

Sheet CheckoutGuard — Forecast · One-
A1: CheckoutGuard — Forecast · One-way operating sensitivity — assumptions
A2: Financial model (3 pages) · Main Scenario
A4: Variable / dimension | B4: 2026-11 | C4: 2026-12 | D4: 2027-01 | E4: 2027-02 | F4: 2027-03 | G4: 2027-04 | H4: 2027-05 | I4: 2027-06 | J4: 2027-07 | K4: 2027-08 | L4: 2027-09 | M4: 2027-10 | N4: 2027-11 | O4: 2027-12 | P4: 2028-01 | Q4: 2028-02 | R4: 2028-03 | S4: 2028-04 | T4: 2028-05 | U4: 2028-06 | V4: 2028-07 | W4: 2028-08 | X4: 2028-09 | Y4: 2028-10
A5: Operating result | B5: ='CheckoutGuard — Forecast · Chec'!C37-'CheckoutGuard — Assumptions (2)'!B13 -> -6479.0092 | C5: ='CheckoutGuard — Forecast · Chec'!D37-'CheckoutGuard — Assumptions (2)'!B13 -> -6151.5985 | D5: ='CheckoutGuard — Forecast · Chec'!E37-'CheckoutGuard — Assumptions (2)'!B13 -> -5817.1581 | E5: ='CheckoutGuard — Forecast · Chec'!F37-'CheckoutGuard — Assumptions (2)'!B13 -> -5475.0564 | F5: ='CheckoutGuard — Forecast · Chec'!G37-'CheckoutGuard — Assumptions (2)'!B13 -> -5124.6383 | G5: ='CheckoutGuard — Forecast · Chec'!H37-'CheckoutGuard — Assumptions (2)'!B13 -> -4765.2245 | H5: ='CheckoutGuard — Forecast · Chec'!I37-'CheckoutGuard — Assumptions (2)'!B13 -> -4396.1093 | I5: ='CheckoutGuard — Forecast · Chec'!J37-'CheckoutGuard — Assumptions (2)'!B13 -> -4016.5597 | J5: ='CheckoutGuard — Forecast · Chec'!K37-'CheckoutGuard — Assumptions (2)'!B13 -> -3625.8132 | K5: ='CheckoutGuard — Forecast · Chec'!L37-'CheckoutGuard — Assumptions (2)'!B13 -> -3223.0767 | L5: ='CheckoutGuard — Forecast · Chec'!M37-'CheckoutGuard — Assumptions (2)'!B13 -> -2807.5241 | M5: ='CheckoutGuard — Business pl (3)'!B7-'CheckoutGuard — Assumptions (2)'!B13 -> -2378.2951 | N5: ='CheckoutGuard — Business pl (3)'!E7-'CheckoutGuard — Assumptions (2)'!B13 -> -1934.4929 | O5: ='CheckoutGuard — Business pl (3)'!H7-'CheckoutGuard — Assumptions (2)'!B13 -> -1475.182 | P5: ='CheckoutGuard — Business pl (3)'!K7-'CheckoutGuard — Assumptions (2)'!B13 -> -999.38661 | Q5: ='CheckoutGuard — Business pl (3)'!N7-'CheckoutGuard — Assumptions (2)'!B13 -> -506.08811 | R5: ='CheckoutGuard — Business pl (3)'!Q7-'CheckoutGuard — Assumptions (2)'!B13 -> 5.7772852 | S5: ='CheckoutGuard — Business pl (3)'!T7-'CheckoutGuard — Assumptions (2)'!B13 -> 537.32085 | T5: ='CheckoutGuard — Business pl (3)'!W7-'CheckoutGuard — Assumptions (2)'!B13 -> 1089.704 | U5: ='CheckoutGuard — Business pl (3)'!Z7-'CheckoutGuard — Assumptions (2)'!B13 -> 1664.1407 | V5: ='CheckoutGuard — Business pl (3)'!AC7-'CheckoutGuard — Assumptions (2)'!B13 -> 2261.9007 | W5: ='CheckoutGuard — Business pl (3)'!AF7-'CheckoutGuard — Assumptions (2)'!B13 -> 2884.3122 | X5: ='CheckoutGuard — Business pl (3)'!AI7-'CheckoutGuard — Assumptions (2)'!B13 -> 3532.7647 | Y5: ='CheckoutGuard — Business pl (3)'!AL7-'CheckoutGuard — Assumptions (2)'!B13 -> 4208.7128
A6: Provider 10x operating result | B6: ='CheckoutGuard — Forecast · Chec'!C21-('CheckoutGuard — Forecast · Chec'!C25)*('CheckoutGuard — Assumptions (2)'!B12+'CheckoutGuard — Assumptions (2)'!B9*('CheckoutGuard — Assumptions · S'!B7-1))-('CheckoutGuard — Forecast · Chec'!C33)-'CheckoutGuard — Forecast · Paym'!C5-'CheckoutGuard — Assumptions (2)'!B13 -> -6516.4866 | C6: ='CheckoutGuard — Forecast · Chec'!D21-('CheckoutGuard — Forecast · Chec'!D25)*('CheckoutGuard — Assumptions (2)'!B12+'CheckoutGuard — Assumptions (2)'!B9*('CheckoutGuard — Assumptions · S'!B7-1))-('CheckoutGuard — Forecast · Chec'!D33)-'CheckoutGuard — Forecast · Paym'!D5-'CheckoutGuard — Assumptions (2)'!B13 -> -6227.3029 | D6: ='CheckoutGuard — Forecast · Chec'!E21-('CheckoutGuard — Forecast · Chec'!E25)*('CheckoutGuard — Assumptions (2)'!B12+'CheckoutGuard — Assumptions (2)'!B9*('CheckoutGuard — Assumptions · S'!B7-1))-('CheckoutGuard — Forecast · Chec'!E33)-'CheckoutGuard — Forecast · Paym'!E5-'CheckoutGuard — Assumptions (2)'!B13 -> -5931.9103 | E6: ='CheckoutGuard — Forecast · Chec'!F21-('CheckoutGuard — Forecast · Chec'!F25)*('CheckoutGuard — Assumptions (2)'!B12+'CheckoutGuard — Assumptions (2)'!B9*('CheckoutGuard — Assumptions · S'!B7-1))-('CheckoutGuard — Forecast · Chec'!F33)-'CheckoutGuard — Forecast · Paym'!F5-'CheckoutGuard — Assumptions (2)'!B13 -> -5629.7508 | F6: ='CheckoutGuard — Forecast · Chec'!G21-('CheckoutGuard — Forecast · Chec'!G25)*('CheckoutGuard — Assumptions (2)'!B12+'CheckoutGuard — Assumptions (2)'!B9*('CheckoutGuard — Assumptions · S'!B7-1))-('CheckoutGuard — Forecast · Chec'!G33)-'CheckoutGuard — Forecast · Paym'!G5-'CheckoutGuard — Assumptions (2)'!B13 -> -5320.246 | G6: ='CheckoutGuard — Forecast · Chec'!H21-('CheckoutGuard — Forecast · Chec'!H25)*('CheckoutGuard — Assumptions (2)'!B12+'CheckoutGuard — Assumptions (2)'!B9*('CheckoutGuard — Assumptions · S'!B7-1))-('CheckoutGuard — Forecast · Chec'!H33)-'CheckoutGuard — Forecast · Paym'!H5-'CheckoutGuard — Assumptions (2)'!B13 -> -5002.7957 | H6: ='CheckoutGuard — Forecast · Chec'!I21-('CheckoutGuard — Forecast · Chec'!I25)*('CheckoutGuard — Assumptions (2)'!B12+'CheckoutGuard — Assumptions (2)'!B9*('CheckoutGuard — Assumptions · S'!B7-1))-('CheckoutGuard — Forecast · Chec'!I33)-'CheckoutGuard — Forecast · Paym'!I5-'CheckoutGuard — Assumptions (2)'!B13 -> -4676.7767 | I6: ='CheckoutGuard — Forecast · Chec'!J21-('CheckoutGuard — Forecast · Chec'!J25)*('CheckoutGuard — Assumptions (2)'!B12+'CheckoutGuard — Assumptions (2)'!B9*('CheckoutGuard — Assumptions · S'!B7-1))-('CheckoutGuard — Forecast · Chec'!J33)-'CheckoutGuard — Forecast · Paym'!J5-'CheckoutGuard — Assumptions (2)'!B13 -> -4341.5416 | J6: ='CheckoutGuard — Forecast · Chec'!K21-('CheckoutGuard — Forecast · Chec'!K25)*('CheckoutGuard — Assumptions (2)'!B12+'CheckoutGuard — Assumptions (2)'!B9*('CheckoutGuard — Assumptions · S'!B7-1))-('CheckoutGuard — Forecast · Chec'!K33)-'CheckoutGuard — Forecast · Paym'!K5-'CheckoutGuard — Assumptions (2)'!B13 -> -3996.4169 | K6: ='CheckoutGuard — Forecast · Chec'!L21-('CheckoutGuard — Forecast · Chec'!L25)*('CheckoutGuard — Assumptions (2)'!B12+'CheckoutGuard — Assumptions (2)'!B9*('CheckoutGuard — Assumptions · S'!B7-1))-('CheckoutGuard — Forecast · Chec'!L33)-'CheckoutGuard — Forecast · Paym'!L5-'CheckoutGuard — Assumptions (2)'!B13 -> -3640.7021 | L6: ='CheckoutGuard — Forecast · Chec'!M21-('CheckoutGuard — Forecast · Chec'!M25)*('CheckoutGuard — Assumptions (2)'!B12+'CheckoutGuard — Assumptions (2)'!B9*('CheckoutGuard — Assumptions · S'!B7-1))-('CheckoutGuard — Forecast · Chec'!M33)-'CheckoutGuard — Forecast · Paym'!M5-'CheckoutGuard — Assumptions (2)'!B13 -> -3273.6676 | M6: ='CheckoutGuard — Business pl (3)'!B6-('CheckoutGuard — Forecast · Chec'!N25)*('CheckoutGuard — Assumptions (2)'!B12+'CheckoutGuard — Assumptions (2)'!B9*('CheckoutGuard — Assumptions · S'!B7-1))-('CheckoutGuard — Forecast · Chec'!N33)-'CheckoutGuard — Forecast · Paym'!N5-'CheckoutGuard — Assumptions (2)'!B13 -> -2894.5534 | N6: ='CheckoutGuard — Business pl (3)'!E6-('CheckoutGuard — Forecast · Chec'!O25)*('CheckoutGuard — Assumptions (2)'!B12+'CheckoutGuard — Assumptions (2)'!B9*('CheckoutGuard — Assumptions · S'!B7-1))-('CheckoutGuard — Forecast · Chec'!O33)-'CheckoutGuard — Forecast · Paym'!O5-'CheckoutGuard — Assumptions (2)'!B13 -> -2502.5675 | O6: ='CheckoutGuard — Business pl (3)'!H6-('CheckoutGuard — Forecast · Chec'!P25)*('CheckoutGuard — Assumptions (2)'!B12+'CheckoutGuard — Assumptions (2)'!B9*('CheckoutGuard — Assumptions · S'!B7-1))-('CheckoutGuard — Forecast · Chec'!P33)-'CheckoutGuard — Forecast · Paym'!P5-'CheckoutGuard — Assumptions (2)'!B13 -> -2096.8837 | P6: ='CheckoutGuard — Business pl (3)'!K6-('CheckoutGuard — Forecast · Chec'!Q25)*('CheckoutGuard — Assumptions (2)'!B12+'CheckoutGuard — Assumptions (2)'!B9*('CheckoutGuard — Assumptions · S'!B7-1))-('CheckoutGuard — Forecast · Chec'!Q33)-'CheckoutGuard — Forecast · Paym'!Q5-'CheckoutGuard — Assumptions (2)'!B13 -> -1676.64 | Q6: ='CheckoutGuard — Business pl (3)'!N6-('CheckoutGuard — Forecast · Chec'!R25)*('CheckoutGuard — Assumptions (2)'!B12+'CheckoutGuard — Assumptions (2)'!B9*('CheckoutGuard — Assumptions · S'!B7-1))-('CheckoutGuard — Forecast · Chec'!R33)-'CheckoutGuard — Forecast · Paym'!R5-'CheckoutGuard — Assumptions (2)'!B13 -> -1240.9368 | R6: ='CheckoutGuard — Business pl (3)'!Q6-('CheckoutGuard — Forecast · Chec'!S25)*('CheckoutGuard — Assumptions (2)'!B12+'CheckoutGuard — Assumptions (2)'!B9*('CheckoutGuard — Assumptions · S'!B7-1))-('CheckoutGuard — Forecast · Chec'!S33)-'CheckoutGuard — Forecast · Paym'!S5-'CheckoutGuard — Assumptions (2)'!B13 -> -788.83452 | S6: ='CheckoutGuard — Business pl (3)'!T6-('CheckoutGuard — Forecast · Chec'!T25)*('CheckoutGuard — Assumptions (2)'!B12+'CheckoutGuard — Assumptions (2)'!B9*('CheckoutGuard — Assumptions · S'!B7-1))-('CheckoutGuard — Forecast · Chec'!T33)-'CheckoutGuard — Forecast · Paym'!T5-'CheckoutGuard — Assumptions (2)'!B13 -> -319.35158 | T6: ='CheckoutGuard — Business pl (3)'!W6-('CheckoutGuard — Forecast · Chec'!U25)*('CheckoutGuard — Assumptions (2)'!B12+'CheckoutGuard — Assumptions (2)'!B9*('CheckoutGuard — Assumptions · S'!B7-1))-('CheckoutGuard — Forecast · Chec'!U33)-'CheckoutGuard — Forecast · Paym'!U5-'CheckoutGuard — Assumptions (2)'!B13 -> 168.53777 | U6: ='CheckoutGuard — Business pl (3)'!Z6-('CheckoutGuard — Forecast · Chec'!V25)*('CheckoutGuard — Assumptions (2)'!B12+'CheckoutGuard — Assumptions (2)'!B9*('CheckoutGuard — Assumptions · S'!B7-1))-('CheckoutGuard — Forecast · Chec'!V33)-'CheckoutGuard — Forecast · Paym'!V5-'CheckoutGuard — Assumptions (2)'!B13 -> 675.90588 | V6: ='CheckoutGuard — Business pl (3)'!AC6-('CheckoutGuard — Forecast · Chec'!W25)*('CheckoutGuard — Assumptions (2)'!B12+'CheckoutGuard — Assumptions (2)'!B9*('CheckoutGuard — Assumptions · S'!B7-1))-('CheckoutGuard — Forecast · Chec'!W33)-'CheckoutGuard — Forecast · Paym'!W5-'CheckoutGuard — Assumptions (2)'!B13 -> 1203.8742 | W6: ='CheckoutGuard — Business pl (3)'!AF6-('CheckoutGuard — Forecast · Chec'!X25)*('CheckoutGuard — Assumptions (2)'!B12+'CheckoutGuard — Assumptions (2)'!B9*('CheckoutGuard — Assumptions · S'!B7-1))-('CheckoutGuard — Forecast · Chec'!X33)-'CheckoutGuard — Forecast · Paym'!X5-'CheckoutGuard — Assumptions (2)'!B13 -> 1753.6157 | X6: ='CheckoutGuard — Business pl (3)'!AI6-('CheckoutGuard — Forecast · Chec'!Y25)*('CheckoutGuard — Assumptions (2)'!B12+'CheckoutGuard — Assumptions (2)'!B9*('CheckoutGuard — Assumptions · S'!B7-1))-('CheckoutGuard — Forecast · Chec'!Y33)-'CheckoutGuard — Forecast · Paym'!Y5-'CheckoutGuard — Assumptions (2)'!B13 -> 2326.3578 | Y6: ='CheckoutGuard — Business pl (3)'!AL6-('CheckoutGuard — Forecast · Chec'!Z25)*('CheckoutGuard — Assumptions (2)'!B12+'CheckoutGuard — Assumptions (2)'!B9*('CheckoutGuard — Assumptions · S'!B7-1))-('CheckoutGuard — Forecast · Chec'!Z33)-'CheckoutGuard — Forecast · Paym'!Z5-'CheckoutGuard — Assumptions (2)'!B13 -> 2923.3852
A7: Extra attempts 100 percent operating result | B7: ='CheckoutGuard — Forecast · Chec'!C21-('CheckoutGuard — Forecast · Chec'!C25)*('CheckoutGuard — Assumptions (2)'!B12+'CheckoutGuard — Assumptions (2)'!B8*'CheckoutGuard — Assumptions · C'!B7*'CheckoutGuard — Assumptions · C'!B9*('CheckoutGuard — Assumptions · S'!B8-'CheckoutGuard — Assumptions · C'!B8)+'CheckoutGuard — Assumptions · C'!B10/3600*'CheckoutGuard — Assumptions · C'!B11*('CheckoutGuard — Assumptions · S'!B8-'CheckoutGuard — Assumptions · C'!B8))-('CheckoutGuard — Forecast · Chec'!C33)-'CheckoutGuard — Forecast · Paym'!C5-'CheckoutGuard — Assumptions (2)'!B13 -> -6483.1053 | C7: ='CheckoutGuard — Forecast · Chec'!D21-('CheckoutGuard — Forecast · Chec'!D25)*('CheckoutGuard — Assumptions (2)'!B12+'CheckoutGuard — Assumptions (2)'!B8*'CheckoutGuard — Assumptions · C'!B7*'CheckoutGuard — Assumptions · C'!B9*('CheckoutGuard — Assumptions · S'!B8-'CheckoutGuard — Assumptions · C'!B8)+'CheckoutGuard — Assumptions · C'!B10/3600*'CheckoutGuard — Assumptions · C'!B11*('CheckoutGuard — Assumptions · S'!B8-'CheckoutGuard — Assumptions · C'!B8))-('CheckoutGuard — Forecast · Chec'!D33)-'CheckoutGuard — Forecast · Paym'!D5-'CheckoutGuard — Assumptions (2)'!B13 -> -6159.8726 | D7: ='CheckoutGuard — Forecast · Chec'!E21-('CheckoutGuard — Forecast · Chec'!E25)*('CheckoutGuard — Assumptions (2)'!B12+'CheckoutGuard — Assumptions (2)'!B8*'CheckoutGuard — Assumptions · C'!B7*'CheckoutGuard — Assumptions · C'!B9*('CheckoutGuard — Assumptions · S'!B8-'CheckoutGuard — Assumptions · C'!B8)+'CheckoutGuard — Assumptions · C'!B10/3600*'CheckoutGuard — Assumptions · C'!B11*('CheckoutGuard — Assumptions · S'!B8-'CheckoutGuard — Assumptions · C'!B8))-('CheckoutGuard — Forecast · Chec'!E33)-'CheckoutGuard — Forecast · Paym'!E5-'CheckoutGuard — Assumptions (2)'!B13 -> -5829.7 | E7: ='CheckoutGuard — Forecast · Chec'!F21-('CheckoutGuard — Forecast · Chec'!F25)*('CheckoutGuard — Assumptions (2)'!B12+'CheckoutGuard — Assumptions (2)'!B8*'CheckoutGuard — Assumptions · C'!B7*'CheckoutGuard — Assumptions · C'!B9*('CheckoutGuard — Assumptions · S'!B8-'CheckoutGuard — Assumptions · C'!B8)+'CheckoutGuard — Assumptions · C'!B10/3600*'CheckoutGuard — Assumptions · C'!B11*('CheckoutGuard — Assumptions · S'!B8-'CheckoutGuard — Assumptions · C'!B8))-('CheckoutGuard — Forecast · Chec'!F33)-'CheckoutGuard — Forecast · Paym'!F5-'CheckoutGuard — Assumptions (2)'!B13 -> -5491.9637 | F7: ='CheckoutGuard — Forecast · Chec'!G21-('CheckoutGuard — Forecast · Chec'!G25)*('CheckoutGuard — Assumptions (2)'!B12+'CheckoutGuard — Assumptions (2)'!B8*'CheckoutGuard — Assumptions · C'!B7*'CheckoutGuard — Assumptions · C'!B9*('CheckoutGuard — Assumptions · S'!B8-'CheckoutGuard — Assumptions · C'!B8)+'CheckoutGuard — Assumptions · C'!B10/3600*'CheckoutGuard — Assumptions · C'!B11*('CheckoutGuard — Assumptions · S'!B8-'CheckoutGuard — Assumptions · C'!B8))-('CheckoutGuard — Forecast · Chec'!G33)-'CheckoutGuard — Forecast · Paym'!G5-'CheckoutGuard — Assumptions (2)'!B13 -> -5146.0173 | G7: ='CheckoutGuard — Forecast · Chec'!H21-('CheckoutGuard — Forecast · Chec'!H25)*('CheckoutGuard — Assumptions (2)'!B12+'CheckoutGuard — Assumptions (2)'!B8*'CheckoutGuard — Assumptions · C'!B7*'CheckoutGuard — Assumptions · C'!B9*('CheckoutGuard — Assumptions · S'!B8-'CheckoutGuard — Assumptions · C'!B8)+'CheckoutGuard — Assumptions · C'!B10/3600*'CheckoutGuard — Assumptions · C'!B11*('CheckoutGuard — Assumptions · S'!B8-'CheckoutGuard — Assumptions · C'!B8))-('CheckoutGuard — Forecast · Chec'!H33)-'CheckoutGuard — Forecast · Paym'!H5-'CheckoutGuard — Assumptions (2)'!B13 -> -4791.1899 | H7: ='CheckoutGuard — Forecast · Chec'!I21-('CheckoutGuard — Forecast · Chec'!I25)*('CheckoutGuard — Assumptions (2)'!B12+'CheckoutGuard — Assumptions (2)'!B8*'CheckoutGuard — Assumptions · C'!B7*'CheckoutGuard — Assumptions · C'!B9*('CheckoutGuard — Assumptions · S'!B8-'CheckoutGuard — Assumptions · C'!B8)+'CheckoutGuard — Assumptions · C'!B10/3600*'CheckoutGuard — Assumptions · C'!B11*('CheckoutGuard — Assumptions · S'!B8-'CheckoutGuard — Assumptions · C'!B8))-('CheckoutGuard — Forecast · Chec'!I33)-'CheckoutGuard — Forecast · Paym'!I5-'CheckoutGuard — Assumptions (2)'!B13 -> -4426.7849 | I7: ='CheckoutGuard — Forecast · Chec'!J21-('CheckoutGuard — Forecast · Chec'!J25)*('CheckoutGuard — Assumptions (2)'!B12+'CheckoutGuard — Assumptions (2)'!B8*'CheckoutGuard — Assumptions · C'!B7*'CheckoutGuard — Assumptions · C'!B9*('CheckoutGuard — Assumptions · S'!B8-'CheckoutGuard — Assumptions · C'!B8)+'CheckoutGuard — Assumptions · C'!B10/3600*'CheckoutGuard — Assumptions · C'!B11*('CheckoutGuard — Assumptions · S'!B8-'CheckoutGuard — Assumptions · C'!B8))-('CheckoutGuard — Forecast · Chec'!J33)-'CheckoutGuard — Forecast · Paym'!J5-'CheckoutGuard — Assumptions (2)'!B13 -> -4052.0787 | J7: ='CheckoutGuard — Forecast · Chec'!K21-('CheckoutGuard — Forecast · Chec'!K25)*('CheckoutGuard — Assumptions (2)'!B12+'CheckoutGuard — Assumptions (2)'!B8*'CheckoutGuard — Assumptions · C'!B7*'CheckoutGuard — Assumptions · C'!B9*('CheckoutGuard — Assumptions · S'!B8-'CheckoutGuard — Assumptions · C'!B8)+'CheckoutGuard — Assumptions · C'!B10/3600*'CheckoutGuard — Assumptions · C'!B11*('CheckoutGuard — Assumptions · S'!B8-'CheckoutGuard — Assumptions · C'!B8))-('CheckoutGuard — Forecast · Chec'!K33)-'CheckoutGuard — Forecast · Paym'!K5-'CheckoutGuard — Assumptions (2)'!B13 -> -3666.3185 | K7: ='CheckoutGuard — Forecast · Chec'!L21-('CheckoutGuard — Forecast · Chec'!L25)*('CheckoutGuard — Assumptions (2)'!B12+'CheckoutGuard — Assumptions (2)'!B8*'CheckoutGuard — Assumptions · C'!B7*'CheckoutGuard — Assumptions · C'!B9*('CheckoutGuard — Assumptions · S'!B8-'CheckoutGuard — Assumptions · C'!B8)+'CheckoutGuard — Assumptions · C'!B10/3600*'CheckoutGuard — Assumptions · C'!B11*('CheckoutGuard — Assumptions · S'!B8-'CheckoutGuard — Assumptions · C'!B8))-('CheckoutGuard — Forecast · Chec'!L33)-'CheckoutGuard — Forecast · Paym'!L5-'CheckoutGuard — Assumptions (2)'!B13 -> -3268.7212 | L7: ='CheckoutGuard — Forecast · Chec'!M21-('CheckoutGuard — Forecast · Chec'!M25)*('CheckoutGuard — Assumptions (2)'!B12+'CheckoutGuard — Assumptions (2)'!B8*'CheckoutGuard — Assumptions · C'!B7*'CheckoutGuard — Assumptions · C'!B9*('CheckoutGuard — Assumptions · S'!B8-'CheckoutGuard — Assumptions · C'!B8)+'CheckoutGuard — Assumptions · C'!B10/3600*'CheckoutGuard — Assumptions · C'!B11*('CheckoutGuard — Assumptions · S'!B8-'CheckoutGuard — Assumptions · C'!B8))-('CheckoutGuard — Forecast · Chec'!M33)-'CheckoutGuard — Forecast · Paym'!M5-'CheckoutGuard — Assumptions (2)'!B13 -> -2858.4714 | M7: ='CheckoutGuard — Business pl (3)'!B6-('CheckoutGuard — Forecast · Chec'!N25)*('CheckoutGuard — Assumptions (2)'!B12+'CheckoutGuard — Assumptions (2)'!B8*'CheckoutGuard — Assumptions · C'!B7*'CheckoutGuard — Assumptions · C'!B9*('CheckoutGuard — Assumptions · S'!B8-'CheckoutGuard — Assumptions · C'!B8)+'CheckoutGuard — Assumptions · C'!B10/3600*'CheckoutGuard — Assumptions · C'!B11*('CheckoutGuard — Assumptions · S'!B8-'CheckoutGuard — Assumptions · C'!B8))-('CheckoutGuard — Forecast · Chec'!N33)-'CheckoutGuard — Forecast · Paym'!N5-'CheckoutGuard — Assumptions (2)'!B13 -> -2434.7197 | N7: ='CheckoutGuard — Business pl (3)'!E6-('CheckoutGuard — Forecast · Chec'!O25)*('CheckoutGuard — Assumptions (2)'!B12+'CheckoutGuard — Assumptions (2)'!B8*'CheckoutGuard — Assumptions · C'!B7*'CheckoutGuard — Assumptions · C'!B9*('CheckoutGuard — Assumptions · S'!B8-'CheckoutGuard — Assumptions · C'!B8)+'CheckoutGuard — Assumptions · C'!B10/3600*'CheckoutGuard — Assumptions · C'!B11*('CheckoutGuard — Assumptions · S'!B8-'CheckoutGuard — Assumptions · C'!B8))-('CheckoutGuard — Forecast · Chec'!O33)-'CheckoutGuard — Forecast · Paym'!O5-'CheckoutGuard — Assumptions (2)'!B13 -> -1996.5807 | O7: ='CheckoutGuard — Business pl (3)'!H6-('CheckoutGuard — Forecast · Chec'!P25)*('CheckoutGuard — Assumptions (2)'!B12+'CheckoutGuard — Assumptions (2)'!B8*'CheckoutGuard — Assumptions · C'!B7*'CheckoutGuard — Assumptions · C'!B9*('CheckoutGuard — Assumptions · S'!B8-'CheckoutGuard — Assumptions · C'!B8)+'CheckoutGuard — Assumptions · C'!B10/3600*'CheckoutGuard — Assumptions · C'!B11*('CheckoutGuard — Assumptions · S'!B8-'CheckoutGuard — Assumptions · C'!B8))-('CheckoutGuard — Forecast · Chec'!P33)-'CheckoutGuard — Forecast · Paym'!P5-'CheckoutGuard — Assumptions (2)'!B13 -> -1543.131 | P7: ='CheckoutGuard — Business pl (3)'!K6-('CheckoutGuard — Forecast · Chec'!Q25)*('CheckoutGuard — Assumptions (2)'!B12+'CheckoutGuard — Assumptions (2)'!B8*'CheckoutGuard — Assumptions · C'!B7*'CheckoutGuard — Assumptions · C'!B9*('CheckoutGuard — Assumptions · S'!B8-'CheckoutGuard — Assumptions · C'!B8)+'CheckoutGuard — Assumptions · C'!B10/3600*'CheckoutGuard — Assumptions · C'!B11*('CheckoutGuard — Assumptions · S'!B8-'CheckoutGuard — Assumptions · C'!B8))-('CheckoutGuard — Forecast · Chec'!Q33)-'CheckoutGuard — Forecast · Paym'!Q5-'CheckoutGuard — Assumptions (2)'!B13 -> -1073.4072 | Q7: ='CheckoutGuard — Business pl (3)'!N6-('CheckoutGuard — Forecast · Chec'!R25)*('CheckoutGuard — Assumptions (2)'!B12+'CheckoutGuard — Assumptions (2)'!B8*'CheckoutGuard — Assumptions · C'!B7*'CheckoutGuard — Assumptions · C'!B9*('CheckoutGuard — Assumptions · S'!B8-'CheckoutGuard — Assumptions · C'!B8)+'CheckoutGuard — Assumptions · C'!B10/3600*'CheckoutGuard — Assumptions · C'!B11*('CheckoutGuard — Assumptions · S'!B8-'CheckoutGuard — Assumptions · C'!B8))-('CheckoutGuard — Forecast · Chec'!R33)-'CheckoutGuard — Forecast · Paym'!R5-'CheckoutGuard — Assumptions (2)'!B13 -> -586.40359 | R7: ='CheckoutGuard — Business pl (3)'!Q6-('CheckoutGuard — Forecast · Chec'!S25)*('CheckoutGuard — Assumptions (2)'!B12+'CheckoutGuard — Assumptions (2)'!B8*'CheckoutGuard — Assumptions · C'!B7*'CheckoutGuard — Assumptions · C'!B9*('CheckoutGuard — Assumptions · S'!B8-'CheckoutGuard — Assumptions · C'!B8)+'CheckoutGuard — Assumptions · C'!B10/3600*'CheckoutGuard — Assumptions · C'!B11*('CheckoutGuard — Assumptions · S'!B8-'CheckoutGuard — Assumptions · C'!B8))-('CheckoutGuard — Forecast · Chec'!S33)-'CheckoutGuard — Forecast · Paym'!S5-'CheckoutGuard — Assumptions (2)'!B13 -> -81.070021 | S7: ='CheckoutGuard — Business pl (3)'!T6-('CheckoutGuard — Forecast · Chec'!T25)*('CheckoutGuard — Assumptions (2)'!B12+'CheckoutGuard — Assumptions (2)'!B8*'CheckoutGuard — Assumptions · C'!B7*'CheckoutGuard — Assumptions · C'!B9*('CheckoutGuard — Assumptions · S'!B8-'CheckoutGuard — Assumptions · C'!B8)+'CheckoutGuard — Assumptions · C'!B10/3600*'CheckoutGuard — Assumptions · C'!B11*('CheckoutGuard — Assumptions · S'!B8-'CheckoutGuard — Assumptions · C'!B8))-('CheckoutGuard — Forecast · Chec'!T33)-'CheckoutGuard — Forecast · Paym'!T5-'CheckoutGuard — Assumptions (2)'!B13 -> 443.69061 | T7: ='CheckoutGuard — Business pl (3)'!W6-('CheckoutGuard — Forecast · Chec'!U25)*('CheckoutGuard — Assumptions (2)'!B12+'CheckoutGuard — Assumptions (2)'!B8*'CheckoutGuard — Assumptions · C'!B7*'CheckoutGuard — Assumptions · C'!B9*('CheckoutGuard — Assumptions · S'!B8-'CheckoutGuard — Assumptions · C'!B8)+'CheckoutGuard — Assumptions · C'!B10/3600*'CheckoutGuard — Assumptions · C'!B11*('CheckoutGuard — Assumptions · S'!B8-'CheckoutGuard — Assumptions · C'!B8))-('CheckoutGuard — Forecast · Chec'!U33)-'CheckoutGuard — Forecast · Paym'!U5-'CheckoutGuard — Assumptions (2)'!B13 -> 989.02486 | U7: ='CheckoutGuard — Business pl (3)'!Z6-('CheckoutGuard — Forecast · Chec'!V25)*('CheckoutGuard — Assumptions (2)'!B12+'CheckoutGuard — Assumptions (2)'!B8*'CheckoutGuard — Assumptions · C'!B7*'CheckoutGuard — Assumptions · C'!B9*('CheckoutGuard — Assumptions · S'!B8-'CheckoutGuard — Assumptions · C'!B8)+'CheckoutGuard — Assumptions · C'!B10/3600*'CheckoutGuard — Assumptions · C'!B11*('CheckoutGuard — Assumptions · S'!B8-'CheckoutGuard — Assumptions · C'!B8))-('CheckoutGuard — Forecast · Chec'!V33)-'CheckoutGuard — Forecast · Paym'!V5-'CheckoutGuard — Assumptions (2)'!B13 -> 1556.1313 | V7: ='CheckoutGuard — Business pl (3)'!AC6-('CheckoutGuard — Forecast · Chec'!W25)*('CheckoutGuard — Assumptions (2)'!B12+'CheckoutGuard — Assumptions (2)'!B8*'CheckoutGuard — Assumptions · C'!B7*'CheckoutGuard — Assumptions · C'!B9*('CheckoutGuard — Assumptions · S'!B8-'CheckoutGuard — Assumptions · C'!B8)+'CheckoutGuard — Assumptions · C'!B10/3600*'CheckoutGuard — Assumptions · C'!B11*('CheckoutGuard — Assumptions · S'!B8-'CheckoutGuard — Assumptions · C'!B8))-('CheckoutGuard — Forecast · Chec'!W33)-'CheckoutGuard — Forecast · Paym'!W5-'CheckoutGuard — Assumptions (2)'!B13 -> 2146.2634 | W7: ='CheckoutGuard — Business pl (3)'!AF6-('CheckoutGuard — Forecast · Chec'!X25)*('CheckoutGuard — Assumptions (2)'!B12+'CheckoutGuard — Assumptions (2)'!B8*'CheckoutGuard — Assumptions · C'!B7*'CheckoutGuard — Assumptions · C'!B9*('CheckoutGuard — Assumptions · S'!B8-'CheckoutGuard — Assumptions · C'!B8)+'CheckoutGuard — Assumptions · C'!B10/3600*'CheckoutGuard — Assumptions · C'!B11*('CheckoutGuard — Assumptions · S'!B8-'CheckoutGuard — Assumptions · C'!B8))-('CheckoutGuard — Forecast · Chec'!X33)-'CheckoutGuard — Forecast · Paym'!X5-'CheckoutGuard — Assumptions (2)'!B13 -> 2760.7324 | X7: ='CheckoutGuard — Business pl (3)'!AI6-('CheckoutGuard — Forecast · Chec'!Y25)*('CheckoutGuard — Assumptions (2)'!B12+'CheckoutGuard — Assumptions (2)'!B8*'CheckoutGuard — Assumptions · C'!B7*'CheckoutGuard — Assumptions · C'!B9*('CheckoutGuard — Assumptions · S'!B8-'CheckoutGuard — Assumptions · C'!B8)+'CheckoutGuard — Assumptions · C'!B10/3600*'CheckoutGuard — Assumptions · C'!B11*('CheckoutGuard — Assumptions · S'!B8-'CheckoutGuard — Assumptions · C'!B8))-('CheckoutGuard — Forecast · Chec'!Y33)-'CheckoutGuard — Forecast · Paym'!Y5-'CheckoutGuard — Assumptions (2)'!B13 -> 3400.9102 | Y7: ='CheckoutGuard — Business pl (3)'!AL6-('CheckoutGuard — Forecast · Chec'!Z25)*('CheckoutGuard — Assumptions (2)'!B12+'CheckoutGuard — Assumptions (2)'!B8*'CheckoutGuard — Assumptions · C'!B7*'CheckoutGuard — Assumptions · C'!B9*('CheckoutGuard — Assumptions · S'!B8-'CheckoutGuard — Assumptions · C'!B8)+'CheckoutGuard — Assumptions · C'!B10/3600*'CheckoutGuard — Assumptions · C'!B11*('CheckoutGuard — Assumptions · S'!B8-'CheckoutGuard — Assumptions · C'!B8))-('CheckoutGuard — Forecast · Chec'!Z33)-'CheckoutGuard — Forecast · Paym'!Z5-'CheckoutGuard — Assumptions (2)'!B13 -> 4068.2326
A8: Browser 3x operating result | B8: ='CheckoutGuard — Forecast · Chec'!C21-('CheckoutGuard — Forecast · Chec'!C25)*('CheckoutGuard — Assumptions (2)'!B12+'CheckoutGuard — Assumptions (2)'!B10*('CheckoutGuard — Assumptions · S'!B11-1))-('CheckoutGuard — Forecast · Chec'!C33)-'CheckoutGuard — Forecast · Paym'!C5-'CheckoutGuard — Assumptions (2)'!B13 -> -6482.9692 | C8: ='CheckoutGuard — Forecast · Chec'!D21-('CheckoutGuard — Forecast · Chec'!D25)*('CheckoutGuard — Assumptions (2)'!B12+'CheckoutGuard — Assumptions (2)'!B10*('CheckoutGuard — Assumptions · S'!B11-1))-('CheckoutGuard — Forecast · Chec'!D33)-'CheckoutGuard — Forecast · Paym'!D5-'CheckoutGuard — Assumptions (2)'!B13 -> -6159.5977 | D8: ='CheckoutGuard — Forecast · Chec'!E21-('CheckoutGuard — Forecast · Chec'!E25)*('CheckoutGuard — Assumptions (2)'!B12+'CheckoutGuard — Assumptions (2)'!B10*('CheckoutGuard — Assumptions · S'!B11-1))-('CheckoutGuard — Forecast · Chec'!E33)-'CheckoutGuard — Forecast · Paym'!E5-'CheckoutGuard — Assumptions (2)'!B13 -> -5829.2833 | E8: ='CheckoutGuard — Forecast · Chec'!F21-('CheckoutGuard — Forecast · Chec'!F25)*('CheckoutGuard — Assumptions (2)'!B12+'CheckoutGuard — Assumptions (2)'!B10*('CheckoutGuard — Assumptions · S'!B11-1))-('CheckoutGuard — Forecast · Chec'!F33)-'CheckoutGuard — Forecast · Paym'!F5-'CheckoutGuard — Assumptions (2)'!B13 -> -5491.4019 | F8: ='CheckoutGuard — Forecast · Chec'!G21-('CheckoutGuard — Forecast · Chec'!G25)*('CheckoutGuard — Assumptions (2)'!B12+'CheckoutGuard — Assumptions (2)'!B10*('CheckoutGuard — Assumptions · S'!B11-1))-('CheckoutGuard — Forecast · Chec'!G33)-'CheckoutGuard — Forecast · Paym'!G5-'CheckoutGuard — Assumptions (2)'!B13 -> -5145.3069 | G8: ='CheckoutGuard — Forecast · Chec'!H21-('CheckoutGuard — Forecast · Chec'!H25)*('CheckoutGuard — Assumptions (2)'!B12+'CheckoutGuard — Assumptions (2)'!B10*('CheckoutGuard — Assumptions · S'!B11-1))-('CheckoutGuard — Forecast · Chec'!H33)-'CheckoutGuard — Forecast · Paym'!H5-'CheckoutGuard — Assumptions (2)'!B13 -> -4790.3271 | H8: ='CheckoutGuard — Forecast · Chec'!I21-('CheckoutGuard — Forecast · Chec'!I25)*('CheckoutGuard — Assumptions (2)'!B12+'CheckoutGuard — Assumptions (2)'!B10*('CheckoutGuard — Assumptions · S'!B11-1))-('CheckoutGuard — Forecast · Chec'!I33)-'CheckoutGuard — Forecast · Paym'!I5-'CheckoutGuard — Assumptions (2)'!B13 -> -4425.7656 | I8: ='CheckoutGuard — Forecast · Chec'!J21-('CheckoutGuard — Forecast · Chec'!J25)*('CheckoutGuard — Assumptions (2)'!B12+'CheckoutGuard — Assumptions (2)'!B10*('CheckoutGuard — Assumptions · S'!B11-1))-('CheckoutGuard — Forecast · Chec'!J33)-'CheckoutGuard — Forecast · Paym'!J5-'CheckoutGuard — Assumptions (2)'!B13 -> -4050.8984 | J8: ='CheckoutGuard — Forecast · Chec'!K21-('CheckoutGuard — Forecast · Chec'!K25)*('CheckoutGuard — Assumptions (2)'!B12+'CheckoutGuard — Assumptions (2)'!B10*('CheckoutGuard — Assumptions · S'!B11-1))-('CheckoutGuard — Forecast · Chec'!K33)-'CheckoutGuard — Forecast · Paym'!K5-'CheckoutGuard — Assumptions (2)'!B13 -> -3664.9725 | K8: ='CheckoutGuard — Forecast · Chec'!L21-('CheckoutGuard — Forecast · Chec'!L25)*('CheckoutGuard — Assumptions (2)'!B12+'CheckoutGuard — Assumptions (2)'!B10*('CheckoutGuard — Assumptions · S'!B11-1))-('CheckoutGuard — Forecast · Chec'!L33)-'CheckoutGuard — Forecast · Paym'!L5-'CheckoutGuard — Assumptions (2)'!B13 -> -3267.2045 | L8: ='CheckoutGuard — Forecast · Chec'!M21-('CheckoutGuard — Forecast · Chec'!M25)*('CheckoutGuard — Assumptions (2)'!B12+'CheckoutGuard — Assumptions (2)'!B10*('CheckoutGuard — Assumptions · S'!B11-1))-('CheckoutGuard — Forecast · Chec'!M33)-'CheckoutGuard — Forecast · Paym'!M5-'CheckoutGuard — Assumptions (2)'!B13 -> -2856.7785 | M8: ='CheckoutGuard — Business pl (3)'!B6-('CheckoutGuard — Forecast · Chec'!N25)*('CheckoutGuard — Assumptions (2)'!B12+'CheckoutGuard — Assumptions (2)'!B10*('CheckoutGuard — Assumptions · S'!B11-1))-('CheckoutGuard — Forecast · Chec'!N33)-'CheckoutGuard — Forecast · Paym'!N5-'CheckoutGuard — Assumptions (2)'!B13 -> -2432.8448 | N8: ='CheckoutGuard — Business pl (3)'!E6-('CheckoutGuard — Forecast · Chec'!O25)*('CheckoutGuard — Assumptions (2)'!B12+'CheckoutGuard — Assumptions (2)'!B10*('CheckoutGuard — Assumptions · S'!B11-1))-('CheckoutGuard — Forecast · Chec'!O33)-'CheckoutGuard — Forecast · Paym'!O5-'CheckoutGuard — Assumptions (2)'!B13 -> -1994.5177 | O8: ='CheckoutGuard — Business pl (3)'!H6-('CheckoutGuard — Forecast · Chec'!P25)*('CheckoutGuard — Assumptions (2)'!B12+'CheckoutGuard — Assumptions (2)'!B10*('CheckoutGuard — Assumptions · S'!B11-1))-('CheckoutGuard — Forecast · Chec'!P33)-'CheckoutGuard — Forecast · Paym'!P5-'CheckoutGuard — Assumptions (2)'!B13 -> -1540.8732 | P8: ='CheckoutGuard — Business pl (3)'!K6-('CheckoutGuard — Forecast · Chec'!Q25)*('CheckoutGuard — Assumptions (2)'!B12+'CheckoutGuard — Assumptions (2)'!B10*('CheckoutGuard — Assumptions · S'!B11-1))-('CheckoutGuard — Forecast · Chec'!Q33)-'CheckoutGuard — Forecast · Paym'!Q5-'CheckoutGuard — Assumptions (2)'!B13 -> -1070.9476 | Q8: ='CheckoutGuard — Business pl (3)'!N6-('CheckoutGuard — Forecast · Chec'!R25)*('CheckoutGuard — Assumptions (2)'!B12+'CheckoutGuard — Assumptions (2)'!B10*('CheckoutGuard — Assumptions · S'!B11-1))-('CheckoutGuard — Forecast · Chec'!R33)-'CheckoutGuard — Forecast · Paym'!R5-'CheckoutGuard — Assumptions (2)'!B13 -> -583.73484 | R8: ='CheckoutGuard — Business pl (3)'!Q6-('CheckoutGuard — Forecast · Chec'!S25)*('CheckoutGuard — Assumptions (2)'!B12+'CheckoutGuard — Assumptions (2)'!B10*('CheckoutGuard — Assumptions · S'!B11-1))-('CheckoutGuard — Forecast · Chec'!S33)-'CheckoutGuard — Forecast · Paym'!S5-'CheckoutGuard — Assumptions (2)'!B13 -> -78.184232 | S8: ='CheckoutGuard — Business pl (3)'!T6-('CheckoutGuard — Forecast · Chec'!T25)*('CheckoutGuard — Assumptions (2)'!B12+'CheckoutGuard — Assumptions (2)'!B10*('CheckoutGuard — Assumptions · S'!B11-1))-('CheckoutGuard — Forecast · Chec'!T33)-'CheckoutGuard — Forecast · Paym'!T5-'CheckoutGuard — Assumptions (2)'!B13 -> 446.80179 | T8: ='CheckoutGuard — Business pl (3)'!W6-('CheckoutGuard — Forecast · Chec'!U25)*('CheckoutGuard — Assumptions (2)'!B12+'CheckoutGuard — Assumptions (2)'!B10*('CheckoutGuard — Assumptions · S'!B11-1))-('CheckoutGuard — Forecast · Chec'!U33)-'CheckoutGuard — Forecast · Paym'!U5-'CheckoutGuard — Assumptions (2)'!B13 -> 992.37025 | U8: ='CheckoutGuard — Business pl (3)'!Z6-('CheckoutGuard — Forecast · Chec'!V25)*('CheckoutGuard — Assumptions (2)'!B12+'CheckoutGuard — Assumptions (2)'!B10*('CheckoutGuard — Assumptions · S'!B11-1))-('CheckoutGuard — Forecast · Chec'!V33)-'CheckoutGuard — Forecast · Paym'!V5-'CheckoutGuard — Assumptions (2)'!B13 -> 1559.7203 | V8: ='CheckoutGuard — Business pl (3)'!AC6-('CheckoutGuard — Forecast · Chec'!W25)*('CheckoutGuard — Assumptions (2)'!B12+'CheckoutGuard — Assumptions (2)'!B10*('CheckoutGuard — Assumptions · S'!B11-1))-('CheckoutGuard — Forecast · Chec'!W33)-'CheckoutGuard — Forecast · Paym'!W5-'CheckoutGuard — Assumptions (2)'!B13 -> 2150.1059 | W8: ='CheckoutGuard — Business pl (3)'!AF6-('CheckoutGuard — Forecast · Chec'!X25)*('CheckoutGuard — Assumptions (2)'!B12+'CheckoutGuard — Assumptions (2)'!B10*('CheckoutGuard — Assumptions · S'!B11-1))-('CheckoutGuard — Forecast · Chec'!X33)-'CheckoutGuard — Forecast · Paym'!X5-'CheckoutGuard — Assumptions (2)'!B13 -> 2764.8388 | X8: ='CheckoutGuard — Business pl (3)'!AI6-('CheckoutGuard — Forecast · Chec'!Y25)*('CheckoutGuard — Assumptions (2)'!B12+'CheckoutGuard — Assumptions (2)'!B10*('CheckoutGuard — Assumptions · S'!B11-1))-('CheckoutGuard — Forecast · Chec'!Y33)-'CheckoutGuard — Forecast · Paym'!Y5-'CheckoutGuard — Assumptions (2)'!B13 -> 3405.2915 | Y8: ='CheckoutGuard — Business pl (3)'!AL6-('CheckoutGuard — Forecast · Chec'!Z25)*('CheckoutGuard — Assumptions (2)'!B12+'CheckoutGuard — Assumptions (2)'!B10*('CheckoutGuard — Assumptions · S'!B11-1))-('CheckoutGuard — Forecast · Chec'!Z33)-'CheckoutGuard — Forecast · Paym'!Z5-'CheckoutGuard — Assumptions (2)'!B13 -> 4072.9005
A9: Support 2x operating result | B9: ='CheckoutGuard — Forecast · Chec'!C21-('CheckoutGuard — Forecast · Chec'!C25)*('CheckoutGuard — Assumptions (2)'!B12+'CheckoutGuard — Assumptions (2)'!B11*('CheckoutGuard — Assumptions · S'!B10-1))-('CheckoutGuard — Forecast · Chec'!C33*'CheckoutGuard — Assumptions · S'!B10)-'CheckoutGuard — Forecast · Paym'!C5-'CheckoutGuard — Assumptions (2)'!B13 -> -6540.0092 | C9: ='CheckoutGuard — Forecast · Chec'!D21-('CheckoutGuard — Forecast · Chec'!D25)*('CheckoutGuard — Assumptions (2)'!B12+'CheckoutGuard — Assumptions (2)'!B11*('CheckoutGuard — Assumptions · S'!B10-1))-('CheckoutGuard — Forecast · Chec'!D33*'CheckoutGuard — Assumptions · S'!B10)-'CheckoutGuard — Forecast · Paym'!D5-'CheckoutGuard — Assumptions (2)'!B13 -> -6274.8185 | D9: ='CheckoutGuard — Forecast · Chec'!E21-('CheckoutGuard — Forecast · Chec'!E25)*('CheckoutGuard — Assumptions (2)'!B12+'CheckoutGuard — Assumptions (2)'!B11*('CheckoutGuard — Assumptions · S'!B10-1))-('CheckoutGuard — Forecast · Chec'!E33*'CheckoutGuard — Assumptions · S'!B10)-'CheckoutGuard — Forecast · Paym'!E5-'CheckoutGuard — Assumptions (2)'!B13 -> -6003.934 | E9: ='CheckoutGuard — Forecast · Chec'!F21-('CheckoutGuard — Forecast · Chec'!F25)*('CheckoutGuard — Assumptions (2)'!B12+'CheckoutGuard — Assumptions (2)'!B11*('CheckoutGuard — Assumptions · S'!B10-1))-('CheckoutGuard — Forecast · Chec'!F33*'CheckoutGuard — Assumptions · S'!B10)-'CheckoutGuard — Forecast · Paym'!F5-'CheckoutGuard — Assumptions (2)'!B13 -> -5726.8441 | F9: ='CheckoutGuard — Forecast · Chec'!G21-('CheckoutGuard — Forecast · Chec'!G25)*('CheckoutGuard — Assumptions (2)'!B12+'CheckoutGuard — Assumptions (2)'!B11*('CheckoutGuard — Assumptions · S'!B10-1))-('CheckoutGuard — Forecast · Chec'!G33*'CheckoutGuard — Assumptions · S'!B10)-'CheckoutGuard — Forecast · Paym'!G5-'CheckoutGuard — Assumptions (2)'!B13 -> -5443.0183 | G9: ='CheckoutGuard — Forecast · Chec'!H21-('CheckoutGuard — Forecast · Chec'!H25)*('CheckoutGuard — Assumptions (2)'!B12+'CheckoutGuard — Assumptions (2)'!B11*('CheckoutGuard — Assumptions · S'!B10-1))-('CheckoutGuard — Forecast · Chec'!H33*'CheckoutGuard — Assumptions · S'!B10)-'CheckoutGuard — Forecast · Paym'!H5-'CheckoutGuard — Assumptions (2)'!B13 -> -5151.9062 | H9: ='CheckoutGuard — Forecast · Chec'!I21-('CheckoutGuard — Forecast · Chec'!I25)*('CheckoutGuard — Assumptions (2)'!B12+'CheckoutGuard — Assumptions (2)'!B11*('CheckoutGuard — Assumptions · S'!B10-1))-('CheckoutGuard — Forecast · Chec'!I33*'CheckoutGuard — Assumptions · S'!B10)-'CheckoutGuard — Forecast · Paym'!I5-'CheckoutGuard — Assumptions (2)'!B13 -> -4852.9365 | I9: ='CheckoutGuard — Forecast · Chec'!J21-('CheckoutGuard — Forecast · Chec'!J25)*('CheckoutGuard — Assumptions (2)'!B12+'CheckoutGuard — Assumptions (2)'!B11*('CheckoutGuard — Assumptions · S'!B10-1))-('CheckoutGuard — Forecast · Chec'!J33*'CheckoutGuard — Assumptions · S'!B10)-'CheckoutGuard — Forecast · Paym'!J5-'CheckoutGuard — Assumptions (2)'!B13 -> -4545.5152 | J9: ='CheckoutGuard — Forecast · Chec'!K21-('CheckoutGuard — Forecast · Chec'!K25)*('CheckoutGuard — Assumptions (2)'!B12+'CheckoutGuard — Assumptions (2)'!B11*('CheckoutGuard — Assumptions · S'!B10-1))-('CheckoutGuard — Forecast · Chec'!K33*'CheckoutGuard — Assumptions · S'!B10)-'CheckoutGuard — Forecast · Paym'!K5-'CheckoutGuard — Assumptions (2)'!B13 -> -4229.0248 | K9: ='CheckoutGuard — Forecast · Chec'!L21-('CheckoutGuard — Forecast · Chec'!L25)*('CheckoutGuard — Assumptions (2)'!B12+'CheckoutGuard — Assumptions (2)'!B11*('CheckoutGuard — Assumptions · S'!B10-1))-('CheckoutGuard — Forecast · Chec'!L33*'CheckoutGuard — Assumptions · S'!B10)-'CheckoutGuard — Forecast · Paym'!L5-'CheckoutGuard — Assumptions (2)'!B13 -> -3902.8229 | L9: ='CheckoutGuard — Forecast · Chec'!M21-('CheckoutGuard — Forecast · Chec'!M25)*('CheckoutGuard — Assumptions (2)'!B12+'CheckoutGuard — Assumptions (2)'!B11*('CheckoutGuard — Assumptions · S'!B10-1))-('CheckoutGuard — Forecast · Chec'!M33*'CheckoutGuard — Assumptions · S'!B10)-'CheckoutGuard — Forecast · Paym'!M5-'CheckoutGuard — Assumptions (2)'!B13 -> -3566.2406 | M9: ='CheckoutGuard — Business pl (3)'!B6-('CheckoutGuard — Forecast · Chec'!N25)*('CheckoutGuard — Assumptions (2)'!B12+'CheckoutGuard — Assumptions (2)'!B11*('CheckoutGuard — Assumptions · S'!B10-1))-('CheckoutGuard — Forecast · Chec'!N33*'CheckoutGuard — Assumptions · S'!B10)-'CheckoutGuard — Forecast · Paym'!N5-'CheckoutGuard — Assumptions (2)'!B13 -> -3218.5808 | N9: ='CheckoutGuard — Business pl (3)'!E6-('CheckoutGuard — Forecast · Chec'!O25)*('CheckoutGuard — Assumptions (2)'!B12+'CheckoutGuard — Assumptions (2)'!B11*('CheckoutGuard — Assumptions · S'!B10-1))-('CheckoutGuard — Forecast · Chec'!O33*'CheckoutGuard — Assumptions · S'!B10)-'CheckoutGuard — Forecast · Paym'!O5-'CheckoutGuard — Assumptions (2)'!B13 -> -2859.1172 | O9: ='CheckoutGuard — Business pl (3)'!H6-('CheckoutGuard — Forecast · Chec'!P25)*('CheckoutGuard — Assumptions (2)'!B12+'CheckoutGuard — Assumptions (2)'!B11*('CheckoutGuard — Assumptions · S'!B10-1))-('CheckoutGuard — Forecast · Chec'!P33*'CheckoutGuard — Assumptions · S'!B10)-'CheckoutGuard — Forecast · Paym'!P5-'CheckoutGuard — Assumptions (2)'!B13 -> -2487.0922 | P9: ='CheckoutGuard — Business pl (3)'!K6-('CheckoutGuard — Forecast · Chec'!Q25)*('CheckoutGuard — Assumptions (2)'!B12+'CheckoutGuard — Assumptions (2)'!B11*('CheckoutGuard — Assumptions · S'!B10-1))-('CheckoutGuard — Forecast · Chec'!Q33*'CheckoutGuard — Assumptions · S'!B10)-'CheckoutGuard — Forecast · Paym'!Q5-'CheckoutGuard — Assumptions (2)'!B13 -> -2101.7153 | Q9: ='CheckoutGuard — Business pl (3)'!N6-('CheckoutGuard — Forecast · Chec'!R25)*('CheckoutGuard — Assumptions (2)'!B12+'CheckoutGuard — Assumptions (2)'!B11*('CheckoutGuard — Assumptions · S'!B10-1))-('CheckoutGuard — Forecast · Chec'!R33*'CheckoutGuard — Assumptions · S'!B10)-'CheckoutGuard — Forecast · Paym'!R5-'CheckoutGuard — Assumptions (2)'!B13 -> -1702.1616 | R9: ='CheckoutGuard — Business pl (3)'!Q6-('CheckoutGuard — Forecast · Chec'!S25)*('CheckoutGuard — Assumptions (2)'!B12+'CheckoutGuard — Assumptions (2)'!B11*('CheckoutGuard — Assumptions · S'!B10-1))-('CheckoutGuard — Forecast · Chec'!S33*'CheckoutGuard — Assumptions · S'!B10)-'CheckoutGuard — Forecast · Paym'!S5-'CheckoutGuard — Assumptions (2)'!B13 -> -1287.5693 | S9: ='CheckoutGuard — Business pl (3)'!T6-('CheckoutGuard — Forecast · Chec'!T25)*('CheckoutGuard — Assumptions (2)'!B12+'CheckoutGuard — Assumptions (2)'!B11*('CheckoutGuard — Assumptions · S'!B10-1))-('CheckoutGuard — Forecast · Chec'!T33*'CheckoutGuard — Assumptions · S'!B10)-'CheckoutGuard — Forecast · Paym'!T5-'CheckoutGuard — Assumptions (2)'!B13 -> -857.03848 | T9: ='CheckoutGuard — Business pl (3)'!W6-('CheckoutGuard — Forecast · Chec'!U25)*('CheckoutGuard — Assumptions (2)'!B12+'CheckoutGuard — Assumptions (2)'!B11*('CheckoutGuard — Assumptions · S'!B10-1))-('CheckoutGuard — Forecast · Chec'!U33*'CheckoutGuard — Assumptions · S'!B10)-'CheckoutGuard — Forecast · Paym'!U5-'CheckoutGuard — Assumptions (2)'!B13 -> -409.62837 | U9: ='CheckoutGuard — Business pl (3)'!Z6-('CheckoutGuard — Forecast · Chec'!V25)*('CheckoutGuard — Assumptions (2)'!B12+'CheckoutGuard — Assumptions (2)'!B11*('CheckoutGuard — Assumptions · S'!B10-1))-('CheckoutGuard — Forecast · Chec'!V33*'CheckoutGuard — Assumptions · S'!B10)-'CheckoutGuard — Forecast · Paym'!V5-'CheckoutGuard — Assumptions (2)'!B13 -> 55.644389 | V9: ='CheckoutGuard — Business pl (3)'!AC6-('CheckoutGuard — Forecast · Chec'!W25)*('CheckoutGuard — Assumptions (2)'!B12+'CheckoutGuard — Assumptions (2)'!B11*('CheckoutGuard — Assumptions · S'!B10-1))-('CheckoutGuard — Forecast · Chec'!W33*'CheckoutGuard — Assumptions · S'!B10)-'CheckoutGuard — Forecast · Paym'!W5-'CheckoutGuard — Assumptions (2)'!B13 -> 539.80816 | W9: ='CheckoutGuard — Business pl (3)'!AF6-('CheckoutGuard — Forecast · Chec'!X25)*('CheckoutGuard — Assumptions (2)'!B12+'CheckoutGuard — Assumptions (2)'!B11*('CheckoutGuard — Assumptions · S'!B10-1))-('CheckoutGuard — Forecast · Chec'!X33*'CheckoutGuard — Assumptions · S'!B10)-'CheckoutGuard — Forecast · Paym'!X5-'CheckoutGuard — Assumptions (2)'!B13 -> 1043.9387 | X9: ='CheckoutGuard — Business pl (3)'!AI6-('CheckoutGuard — Forecast · Chec'!Y25)*('CheckoutGuard — Assumptions (2)'!B12+'CheckoutGuard — Assumptions (2)'!B11*('CheckoutGuard — Assumptions · S'!B10-1))-('CheckoutGuard — Forecast · Chec'!Y33*'CheckoutGuard — Assumptions · S'!B10)-'CheckoutGuard — Forecast · Paym'!Y5-'CheckoutGuard — Assumptions (2)'!B13 -> 1569.1615 | Y9: ='CheckoutGuard — Business pl (3)'!AL6-('CheckoutGuard — Forecast · Chec'!Z25)*('CheckoutGuard — Assumptions (2)'!B12+'CheckoutGuard — Assumptions (2)'!B11*('CheckoutGuard — Assumptions · S'!B10-1))-('CheckoutGuard — Forecast · Chec'!Z33*'CheckoutGuard — Assumptions · S'!B10)-'CheckoutGuard — Forecast · Paym'!Z5-'CheckoutGuard — Assumptions (2)'!B13 -> 2116.6547
A10: Full quota usage operating result | B10: ='CheckoutGuard — Forecast · Chec'!C21-('CheckoutGuard — Forecast · Chec'!C25*'CheckoutGuard — Assumptions · S'!B9)*('CheckoutGuard — Assumptions (2)'!B12)-('CheckoutGuard — Forecast · Chec'!C33)-'CheckoutGuard — Forecast · Paym'!C5-'CheckoutGuard — Assumptions (2)'!B13 -> -6500.0033 | C10: ='CheckoutGuard — Forecast · Chec'!D21-('CheckoutGuard — Forecast · Chec'!D25*'CheckoutGuard — Assumptions · S'!B9)*('CheckoutGuard — Assumptions (2)'!B12)-('CheckoutGuard — Forecast · Chec'!D33)-'CheckoutGuard — Forecast · Paym'!D5-'CheckoutGuard — Assumptions (2)'!B13 -> -6194.0067 | D10: ='CheckoutGuard — Forecast · Chec'!E21-('CheckoutGuard — Forecast · Chec'!E25*'CheckoutGuard — Assumptions · S'!B9)*('CheckoutGuard — Assumptions (2)'!B12)-('CheckoutGuard — Forecast · Chec'!E33)-'CheckoutGuard — Forecast · Paym'!E5-'CheckoutGuard — Assumptions (2)'!B13 -> -5881.4402 | E10: ='CheckoutGuard — Forecast · Chec'!F21-('CheckoutGuard — Forecast · Chec'!F25*'CheckoutGuard — Assumptions · S'!B9)*('CheckoutGuard — Assumptions (2)'!B12)-('CheckoutGuard — Forecast · Chec'!F33)-'CheckoutGuard — Forecast · Paym'!F5-'CheckoutGuard — Assumptions (2)'!B13 -> -5561.7133 | F10: ='CheckoutGuard — Forecast · Chec'!G21-('CheckoutGuard — Forecast · Chec'!G25*'CheckoutGuard — Assumptions · S'!B9)*('CheckoutGuard — Assumptions (2)'!B12)-('CheckoutGuard — Forecast · Chec'!G33)-'CheckoutGuard — Forecast · Paym'!G5-'CheckoutGuard — Assumptions (2)'!B13 -> -5234.2141 | G10: ='CheckoutGuard — Forecast · Chec'!H21-('CheckoutGuard — Forecast · Chec'!H25*'CheckoutGuard — Assumptions · S'!B9)*('CheckoutGuard — Assumptions (2)'!B12)-('CheckoutGuard — Forecast · Chec'!H33)-'CheckoutGuard — Forecast · Paym'!H5-'CheckoutGuard — Assumptions (2)'!B13 -> -4898.3074 | H10: ='CheckoutGuard — Forecast · Chec'!I21-('CheckoutGuard — Forecast · Chec'!I25*'CheckoutGuard — Assumptions · S'!B9)*('CheckoutGuard — Assumptions (2)'!B12)-('CheckoutGuard — Forecast · Chec'!I33)-'CheckoutGuard — Forecast · Paym'!I5-'CheckoutGuard — Assumptions (2)'!B13 -> -4553.3339 | I10: ='CheckoutGuard — Forecast · Chec'!J21-('CheckoutGuard — Forecast · Chec'!J25*'CheckoutGuard — Assumptions · S'!B9)*('CheckoutGuard — Assumptions (2)'!B12)-('CheckoutGuard — Forecast · Chec'!J33)-'CheckoutGuard — Forecast · Paym'!J5-'CheckoutGuard — Assumptions (2)'!B13 -> -4198.6085 | J10: ='CheckoutGuard — Forecast · Chec'!K21-('CheckoutGuard — Forecast · Chec'!K25*'CheckoutGuard — Assumptions · S'!B9)*('CheckoutGuard — Assumptions (2)'!B12)-('CheckoutGuard — Forecast · Chec'!K33)-'CheckoutGuard — Forecast · Paym'!K5-'CheckoutGuard — Assumptions (2)'!B13 -> -3833.4185 | K10: ='CheckoutGuard — Forecast · Chec'!L21-('CheckoutGuard — Forecast · Chec'!L25*'CheckoutGuard — Assumptions · S'!B9)*('CheckoutGuard — Assumptions (2)'!B12)-('CheckoutGuard — Forecast · Chec'!L33)-'CheckoutGuard — Forecast · Paym'!L5-'CheckoutGuard — Assumptions (2)'!B13 -> -3457.0226 | L10: ='CheckoutGuard — Forecast · Chec'!M21-('CheckoutGuard — Forecast · Chec'!M25*'CheckoutGuard — Assumptions · S'!B9)*('CheckoutGuard — Assumptions (2)'!B12)-('CheckoutGuard — Forecast · Chec'!M33)-'CheckoutGuard — Forecast · Paym'!M5-'CheckoutGuard — Assumptions (2)'!B13 -> -3068.649 | M10: ='CheckoutGuard — Business pl (3)'!B6-('CheckoutGuard — Forecast · Chec'!N25*'CheckoutGuard — Assumptions · S'!B9)*('CheckoutGuard — Assumptions (2)'!B12)-('CheckoutGuard — Forecast · Chec'!N33)-'CheckoutGuard — Forecast · Paym'!N5-'CheckoutGuard — Assumptions (2)'!B13 -> -2667.4934 | N10: ='CheckoutGuard — Business pl (3)'!E6-('CheckoutGuard — Forecast · Chec'!O25*'CheckoutGuard — Assumptions · S'!B9)*('CheckoutGuard — Assumptions (2)'!B12)-('CheckoutGuard — Forecast · Chec'!O33)-'CheckoutGuard — Forecast · Paym'!O5-'CheckoutGuard — Assumptions (2)'!B13 -> -2252.7176 | O10: ='CheckoutGuard — Business pl (3)'!H6-('CheckoutGuard — Forecast · Chec'!P25*'CheckoutGuard — Assumptions · S'!B9)*('CheckoutGuard — Assumptions (2)'!B12)-('CheckoutGuard — Forecast · Chec'!P33)-'CheckoutGuard — Forecast · Paym'!P5-'CheckoutGuard — Assumptions (2)'!B13 -> -1823.4476 | P10: ='CheckoutGuard — Business pl (3)'!K6-('CheckoutGuard — Forecast · Chec'!Q25*'CheckoutGuard — Assumptions · S'!B9)*('CheckoutGuard — Assumptions (2)'!B12)-('CheckoutGuard — Forecast · Chec'!Q33)-'CheckoutGuard — Forecast · Paym'!Q5-'CheckoutGuard — Assumptions (2)'!B13 -> -1378.7713 | Q10: ='CheckoutGuard — Business pl (3)'!N6-('CheckoutGuard — Forecast · Chec'!R25*'CheckoutGuard — Assumptions · S'!B9)*('CheckoutGuard — Assumptions (2)'!B12)-('CheckoutGuard — Forecast · Chec'!R33)-'CheckoutGuard — Forecast · Paym'!R5-'CheckoutGuard — Assumptions (2)'!B13 -> -917.73659 | R10: ='CheckoutGuard — Business pl (3)'!Q6-('CheckoutGuard — Forecast · Chec'!S25*'CheckoutGuard — Assumptions · S'!B9)*('CheckoutGuard — Assumptions (2)'!B12)-('CheckoutGuard — Forecast · Chec'!S33)-'CheckoutGuard — Forecast · Paym'!S5-'CheckoutGuard — Assumptions (2)'!B13 -> -439.34936 | S10: ='CheckoutGuard — Business pl (3)'!T6-('CheckoutGuard — Forecast · Chec'!T25*'CheckoutGuard — Assumptions · S'!B9)*('CheckoutGuard — Assumptions (2)'!B12)-('CheckoutGuard — Forecast · Chec'!T33)-'CheckoutGuard — Forecast · Paym'!T5-'CheckoutGuard — Assumptions (2)'!B13 -> 57.429002 | T10: ='CheckoutGuard — Business pl (3)'!W6-('CheckoutGuard — Forecast · Chec'!U25*'CheckoutGuard — Assumptions · S'!B9)*('CheckoutGuard — Assumptions (2)'!B12)-('CheckoutGuard — Forecast · Chec'!U33)-'CheckoutGuard — Forecast · Paym'!U5-'CheckoutGuard — Assumptions (2)'!B13 -> 573.68391 | U10: ='CheckoutGuard — Business pl (3)'!Z6-('CheckoutGuard — Forecast · Chec'!V25*'CheckoutGuard — Assumptions · S'!B9)*('CheckoutGuard — Assumptions (2)'!B12)-('CheckoutGuard — Forecast · Chec'!V33)-'CheckoutGuard — Forecast · Paym'!V5-'CheckoutGuard — Assumptions (2)'!B13 -> 1110.5501 | V10: ='CheckoutGuard — Business pl (3)'!AC6-('CheckoutGuard — Forecast · Chec'!W25*'CheckoutGuard — Assumptions · S'!B9)*('CheckoutGuard — Assumptions (2)'!B12)-('CheckoutGuard — Forecast · Chec'!W33)-'CheckoutGuard — Forecast · Paym'!W5-'CheckoutGuard — Assumptions (2)'!B13 -> 1669.2141 | W10: ='CheckoutGuard — Business pl (3)'!AF6-('CheckoutGuard — Forecast · Chec'!X25*'CheckoutGuard — Assumptions · S'!B9)*('CheckoutGuard — Assumptions (2)'!B12)-('CheckoutGuard — Forecast · Chec'!X33)-'CheckoutGuard — Forecast · Paym'!X5-'CheckoutGuard — Assumptions (2)'!B13 -> 2250.9172 | X10: ='CheckoutGuard — Business pl (3)'!AI6-('CheckoutGuard — Forecast · Chec'!Y25*'CheckoutGuard — Assumptions · S'!B9)*('CheckoutGuard — Assumptions (2)'!B12)-('CheckoutGuard — Forecast · Chec'!Y33)-'CheckoutGuard — Forecast · Paym'!Y5-'CheckoutGuard — Assumptions (2)'!B13 -> 2856.9582 | Y10: ='CheckoutGuard — Business pl (3)'!AL6-('CheckoutGuard — Forecast · Chec'!Z25*'CheckoutGuard — Assumptions · S'!B9)*('CheckoutGuard — Assumptions (2)'!B12)-('CheckoutGuard — Forecast · Chec'!Z33)-'CheckoutGuard — Forecast · Paym'!Z5-'CheckoutGuard — Assumptions (2)'!B13 -> 3488.6963

Sheet Model inputs
A1: Model inputs
A2: Integration values are aggregated snapshots; raw source records are not included.
A4: Variables
A5: Variable / segment | B5: 2026-09 | C5: 2026-10 | D5: 2026-11 | E5: 2026-12 | F5: 2027-01 | G5: 2027-02 | H5: 2027-03 | I5: 2027-04 | J5: 2027-05 | K5: 2027-06 | L5: 2027-07 | M5: 2027-08 | N5: 2027-09 | O5: 2027-10 | P5: 2027-11 | Q5: 2027-12 | R5: 2028-01 | S5: 2028-02 | T5: 2028-03 | U5: 2028-04 | V5: 2028-05 | W5: 2028-06 | X5: 2028-07 | Y5: 2028-08 | Z5: 2028-09 | AA5: 2028-10 | AB5: Value | AC5: Value | AD5: 2026-01 | AE5: 2026-02 | AF5: 2026-03 | AG5: 2026-04 | AH5: 2026-05 | AI5: 2026-06 | AJ5: 2026-07 | AK5: 2026-08
A6: Active subscriptions | B6: =SUM('Model inputs'!B7,'Model inputs'!B8,'Model inputs'!B9) -> 0 | C6: =SUM('Model inputs'!C7,'Model inputs'!C8,'Model inputs'!C9) -> 0 | D6: =SUM('Model inputs'!D7,'Model inputs'!D8,'Model inputs'!D9) -> 4.5 | E6: =SUM('Model inputs'!E7,'Model inputs'!E8,'Model inputs'!E9) -> 9.09 | F6: =SUM('Model inputs'!F7,'Model inputs'!F8,'Model inputs'!F9) -> 13.77855 | G6: =SUM('Model inputs'!G7,'Model inputs'!G8,'Model inputs'!G9) -> 18.574506 | H6: =SUM('Model inputs'!H7,'Model inputs'!H8,'Model inputs'!H9) -> 23.487049 | I6: =SUM('Model inputs'!I7,'Model inputs'!I8,'Model inputs'!I9) -> 28.525705 | ... AA6: =SUM('Model inputs'!AA7,'Model inputs'!AA8,'Model inputs'!AA9) -> 154.33215
